<?xml version="1.0" encoding="UTF-8"?>
<!DOCTYPE why3session SYSTEM "/users/demons/melquion/src/why3/share/why3session.dtd">
<why3session
 name="programs/vstte10_max_sum/why3session.xml" shape_version="2">
 <prover
  id="0"
  name="Alt-Ergo"
  version="0.94"/>
 <prover
  id="1"
  name="CVC3"
  version="2.2"/>
 <prover
  id="2"
  name="Coq"
  version="8.3pl4"/>
 <prover
  id="3"
  name="Z3"
  version="2.19"/>
 <prover
  id="4"
  name="Z3"
  version="3.2"/>
 <file
  name="../vstte10_max_sum.mlw"
  verified="true"
  expanded="false">
  <theory
   name="MaxAndSum"
   locfile="programs/vstte10_max_sum/../vstte10_max_sum.mlw"
   loclnum="9" loccnumb="7" loccnume="16"
   verified="true"
   expanded="true">
   <goal
    name="WP_parameter max_sum"
    locfile="programs/vstte10_max_sum/../vstte10_max_sum.mlw"
    loclnum="15" loccnumb="6" loccnume="13"
    expl="parameter max_sum"
    sum="aea749d7f14d5dcd51f43e74a869e4ef"
    proved="true"
    expanded="true"
    shape="ainfix &lt;=V4ainfix *V1V3Iainfix &lt;=V4ainfix *ainfix +ainfix -V1c1c1V3Aiainfix &lt;V3agetV2V5ainfix &lt;=V7ainfix *ainfix +V5c1V6Iainfix =V7ainfix +V4agetV2V5FAainfix &lt;V5V0Aainfix &lt;=c0V5Iainfix =V6agetV2V5FAainfix &lt;V5V0Aainfix &lt;=c0V5ainfix &lt;=V8ainfix *ainfix +V5c1V3Iainfix =V8ainfix +V4agetV2V5FAainfix &lt;V5V0Aainfix &lt;=c0V5Aainfix &lt;V5V0Aainfix &lt;=c0V5Iainfix &lt;=V4ainfix *V5V3Iainfix &lt;=V5ainfix -V1c1Aainfix &lt;=c0V5FFAainfix &lt;=c0ainfix *c0c0Iainfix &lt;=c0ainfix -V1c1Aainfix &lt;=c0ainfix *V1c0Iainfix &gt;c0ainfix -V1c1Iainfix &gt;=agetV2V9c0Iainfix &lt;V9V1Aainfix &lt;=c0V9FAainfix =V1V0Aainfix &lt;=c0V1FF">
    <label
     name="expl:parameter max_sum"/>
    <transf
     name="split_goal"
     proved="true"
     expanded="true">
     <goal
      name="WP_parameter max_sum.1"
      locfile="programs/vstte10_max_sum/../vstte10_max_sum.mlw"
      loclnum="15" loccnumb="6" loccnume="13"
      expl="normal postcondition"
      sum="ae5eac82b4bc9af1c425958ae9770d0d"
      proved="true"
      expanded="true"
      shape="ainfix &lt;=c0ainfix *V1c0Iainfix &gt;c0ainfix -V1c1Iainfix &gt;=agetV2V3c0Iainfix &lt;V3V1Aainfix &lt;=c0V3FAainfix =V1V0Aainfix &lt;=c0V1FF">
      <label
       name="expl:parameter max_sum"/>
      <proof
       prover="3"
       timelimit="10"
       memlimit="0"
       obsolete="false"
       archived="false">
       <result status="valid" time="0.00"/>
      </proof>
      <proof
       prover="1"
       timelimit="10"
       memlimit="0"
       obsolete="false"
       archived="false">
       <result status="valid" time="0.00"/>
      </proof>
      <proof
       prover="0"
       timelimit="10"
       memlimit="0"
       obsolete="false"
       archived="false">
       <result status="valid" time="0.00"/>
      </proof>
     </goal>
     <goal
      name="WP_parameter max_sum.2"
      locfile="programs/vstte10_max_sum/../vstte10_max_sum.mlw"
      loclnum="15" loccnumb="6" loccnume="13"
      expl="for loop initialization"
      sum="4d2d0d3dfd91ebfb544663d358665103"
      proved="true"
      expanded="true"
      shape="ainfix &lt;=c0ainfix *c0c0Iainfix &lt;=c0ainfix -V1c1Iainfix &gt;=agetV2V3c0Iainfix &lt;V3V1Aainfix &lt;=c0V3FAainfix =V1V0Aainfix &lt;=c0V1FF">
      <label
       name="expl:parameter max_sum"/>
      <proof
       prover="3"
       timelimit="10"
       memlimit="0"
       obsolete="false"
       archived="false">
       <result status="valid" time="0.00"/>
      </proof>
      <proof
       prover="1"
       timelimit="10"
       memlimit="0"
       obsolete="false"
       archived="false">
       <result status="valid" time="0.00"/>
      </proof>
      <proof
       prover="0"
       timelimit="10"
       memlimit="0"
       obsolete="false"
       archived="false">
       <result status="valid" time="0.00"/>
      </proof>
     </goal>
     <goal
      name="WP_parameter max_sum.3"
      locfile="programs/vstte10_max_sum/../vstte10_max_sum.mlw"
      loclnum="15" loccnumb="6" loccnume="13"
      expl="for loop preservation"
      sum="469c9b4d850d01b10213059045aa6de1"
      proved="true"
      expanded="true"
      shape="iainfix &lt;V3agetV2V5ainfix &lt;=V7ainfix *ainfix +V5c1V6Iainfix =V7ainfix +V4agetV2V5FAainfix &lt;V5V0Aainfix &lt;=c0V5Iainfix =V6agetV2V5FAainfix &lt;V5V0Aainfix &lt;=c0V5ainfix &lt;=V8ainfix *ainfix +V5c1V3Iainfix =V8ainfix +V4agetV2V5FAainfix &lt;V5V0Aainfix &lt;=c0V5Aainfix &lt;V5V0Aainfix &lt;=c0V5Iainfix &lt;=V4ainfix *V5V3Iainfix &lt;=V5ainfix -V1c1Aainfix &lt;=c0V5FFIainfix &lt;=c0ainfix -V1c1Iainfix &gt;=agetV2V9c0Iainfix &lt;V9V1Aainfix &lt;=c0V9FAainfix =V1V0Aainfix &lt;=c0V1FF">
      <label
       name="expl:parameter max_sum"/>
      <transf
       name="split_goal"
       proved="true"
       expanded="true">
       <goal
        name="WP_parameter max_sum.3.1"
        locfile="programs/vstte10_max_sum/../vstte10_max_sum.mlw"
        loclnum="15" loccnumb="6" loccnume="13"
        expl="for loop preservation"
        sum="404671ba4ffb09dd497da80432f5a3d6"
        proved="true"
        expanded="true"
        shape="ainfix &lt;V5V0Aainfix &lt;=c0V5Iainfix &lt;=V4ainfix *V5V3Iainfix &lt;=V5ainfix -V1c1Aainfix &lt;=c0V5FFIainfix &lt;=c0ainfix -V1c1Iainfix &gt;=agetV2V6c0Iainfix &lt;V6V1Aainfix &lt;=c0V6FAainfix =V1V0Aainfix &lt;=c0V1FF">
        <label
         name="expl:parameter max_sum"/>
        <proof
         prover="3"
         timelimit="10"
         memlimit="0"
         obsolete="false"
         archived="false">
         <result status="valid" time="0.01"/>
        </proof>
        <proof
         prover="1"
         timelimit="10"
         memlimit="0"
         obsolete="false"
         archived="false">
         <result status="valid" time="0.00"/>
        </proof>
        <proof
         prover="0"
         timelimit="10"
         memlimit="0"
         obsolete="false"
         archived="false">
         <result status="valid" time="0.00"/>
        </proof>
       </goal>
       <goal
        name="WP_parameter max_sum.3.2"
        locfile="programs/vstte10_max_sum/../vstte10_max_sum.mlw"
        loclnum="15" loccnumb="6" loccnume="13"
        expl="for loop preservation"
        sum="975f3a082c2b55a6a9eaa7b383d227f3"
        proved="true"
        expanded="true"
        shape="ainfix &lt;V5V0Aainfix &lt;=c0V5Iainfix &lt;V3agetV2V5Iainfix &lt;V5V0Aainfix &lt;=c0V5Iainfix &lt;=V4ainfix *V5V3Iainfix &lt;=V5ainfix -V1c1Aainfix &lt;=c0V5FFIainfix &lt;=c0ainfix -V1c1Iainfix &gt;=agetV2V6c0Iainfix &lt;V6V1Aainfix &lt;=c0V6FAainfix =V1V0Aainfix &lt;=c0V1FF">
        <label
         name="expl:parameter max_sum"/>
        <proof
         prover="3"
         timelimit="10"
         memlimit="0"
         obsolete="false"
         archived="false">
         <result status="valid" time="0.00"/>
        </proof>
        <proof
         prover="1"
         timelimit="10"
         memlimit="0"
         obsolete="false"
         archived="false">
         <result status="valid" time="0.01"/>
        </proof>
        <proof
         prover="0"
         timelimit="10"
         memlimit="0"
         obsolete="false"
         archived="false">
         <result status="valid" time="0.00"/>
        </proof>
       </goal>
       <goal
        name="WP_parameter max_sum.3.3"
        locfile="programs/vstte10_max_sum/../vstte10_max_sum.mlw"
        loclnum="15" loccnumb="6" loccnume="13"
        expl="for loop preservation"
        sum="eaaea73b9c50face12e1bed0c5d09eb0"
        proved="true"
        expanded="true"
        shape="ainfix &lt;V5V0Aainfix &lt;=c0V5Iainfix =V6agetV2V5FIainfix &lt;V5V0Aainfix &lt;=c0V5Iainfix &lt;V3agetV2V5Iainfix &lt;V5V0Aainfix &lt;=c0V5Iainfix &lt;=V4ainfix *V5V3Iainfix &lt;=V5ainfix -V1c1Aainfix &lt;=c0V5FFIainfix &lt;=c0ainfix -V1c1Iainfix &gt;=agetV2V7c0Iainfix &lt;V7V1Aainfix &lt;=c0V7FAainfix =V1V0Aainfix &lt;=c0V1FF">
        <label
         name="expl:parameter max_sum"/>
        <proof
         prover="3"
         timelimit="10"
         memlimit="0"
         obsolete="false"
         archived="false">
         <result status="valid" time="0.02"/>
        </proof>
        <proof
         prover="1"
         timelimit="10"
         memlimit="0"
         obsolete="false"
         archived="false">
         <result status="valid" time="0.01"/>
        </proof>
        <proof
         prover="0"
         timelimit="10"
         memlimit="0"
         obsolete="false"
         archived="false">
         <result status="valid" time="0.01"/>
        </proof>
       </goal>
       <goal
        name="WP_parameter max_sum.3.4"
        locfile="programs/vstte10_max_sum/../vstte10_max_sum.mlw"
        loclnum="15" loccnumb="6" loccnume="13"
        expl="for loop preservation"
        sum="5949cda23840a3edc0dbc31e5941d9e1"
        proved="true"
        expanded="true"
        shape="ainfix &lt;=V7ainfix *ainfix +V5c1V6Iainfix =V7ainfix +V4agetV2V5FIainfix &lt;V5V0Aainfix &lt;=c0V5Iainfix =V6agetV2V5FIainfix &lt;V5V0Aainfix &lt;=c0V5Iainfix &lt;V3agetV2V5Iainfix &lt;V5V0Aainfix &lt;=c0V5Iainfix &lt;=V4ainfix *V5V3Iainfix &lt;=V5ainfix -V1c1Aainfix &lt;=c0V5FFIainfix &lt;=c0ainfix -V1c1Iainfix &gt;=agetV2V8c0Iainfix &lt;V8V1Aainfix &lt;=c0V8FAainfix =V1V0Aainfix &lt;=c0V1FF">
        <label
         name="expl:parameter max_sum"/>
        <proof
         prover="3"
         timelimit="10"
         memlimit="0"
         obsolete="false"
         archived="false">
         <result status="valid" time="0.02"/>
        </proof>
        <proof
         prover="2"
         timelimit="10"
         memlimit="0"
         edited="vstte10_max_sum_MaxAndSum_WP_parameter_max_sum_1.v"
         obsolete="false"
         archived="false">
         <result status="valid" time="0.54"/>
        </proof>
       </goal>
       <goal
        name="WP_parameter max_sum.3.5"
        locfile="programs/vstte10_max_sum/../vstte10_max_sum.mlw"
        loclnum="15" loccnumb="6" loccnume="13"
        expl="for loop preservation"
        sum="83531f5ed7cb754589e35bccd9442397"
        proved="true"
        expanded="true"
        shape="ainfix &lt;V5V0Aainfix &lt;=c0V5Iainfix &lt;V3agetV2V5NIainfix &lt;V5V0Aainfix &lt;=c0V5Iainfix &lt;=V4ainfix *V5V3Iainfix &lt;=V5ainfix -V1c1Aainfix &lt;=c0V5FFIainfix &lt;=c0ainfix -V1c1Iainfix &gt;=agetV2V6c0Iainfix &lt;V6V1Aainfix &lt;=c0V6FAainfix =V1V0Aainfix &lt;=c0V1FF">
        <label
         name="expl:parameter max_sum"/>
        <proof
         prover="3"
         timelimit="10"
         memlimit="0"
         obsolete="false"
         archived="false">
         <result status="valid" time="0.00"/>
        </proof>
        <proof
         prover="1"
         timelimit="10"
         memlimit="0"
         obsolete="false"
         archived="false">
         <result status="valid" time="0.00"/>
        </proof>
        <proof
         prover="0"
         timelimit="10"
         memlimit="0"
         obsolete="false"
         archived="false">
         <result status="valid" time="0.00"/>
        </proof>
       </goal>
       <goal
        name="WP_parameter max_sum.3.6"
        locfile="programs/vstte10_max_sum/../vstte10_max_sum.mlw"
        loclnum="15" loccnumb="6" loccnume="13"
        expl="for loop preservation"
        sum="4d173346a0787ec5b35973d6f6aee6f4"
        proved="true"
        expanded="true"
        shape="ainfix &lt;=V6ainfix *ainfix +V5c1V3Iainfix =V6ainfix +V4agetV2V5FIainfix &lt;V5V0Aainfix &lt;=c0V5Iainfix &lt;V3agetV2V5NIainfix &lt;V5V0Aainfix &lt;=c0V5Iainfix &lt;=V4ainfix *V5V3Iainfix &lt;=V5ainfix -V1c1Aainfix &lt;=c0V5FFIainfix &lt;=c0ainfix -V1c1Iainfix &gt;=agetV2V7c0Iainfix &lt;V7V1Aainfix &lt;=c0V7FAainfix =V1V0Aainfix &lt;=c0V1FF">
        <label
         name="expl:parameter max_sum"/>
        <proof
         prover="3"
         timelimit="10"
         memlimit="0"
         obsolete="false"
         archived="false">
         <result status="valid" time="0.01"/>
        </proof>
        <proof
         prover="1"
         timelimit="10"
         memlimit="0"
         obsolete="false"
         archived="false">
         <result status="valid" time="0.00"/>
        </proof>
        <proof
         prover="0"
         timelimit="10"
         memlimit="0"
         obsolete="false"
         archived="false">
         <result status="valid" time="0.01"/>
        </proof>
       </goal>
      </transf>
     </goal>
     <goal
      name="WP_parameter max_sum.4"
      locfile="programs/vstte10_max_sum/../vstte10_max_sum.mlw"
      loclnum="15" loccnumb="6" loccnume="13"
      expl="normal postcondition"
      sum="517ff6f2a2bd022230d4246fc99f3465"
      proved="true"
      expanded="true"
      shape="ainfix &lt;=V4ainfix *V1V3Iainfix &lt;=V4ainfix *ainfix +ainfix -V1c1c1V3FIainfix &lt;=c0ainfix -V1c1Iainfix &gt;=agetV2V5c0Iainfix &lt;V5V1Aainfix &lt;=c0V5FAainfix =V1V0Aainfix &lt;=c0V1FF">
      <label
       name="expl:parameter max_sum"/>
      <proof
       prover="3"
       timelimit="10"
       memlimit="0"
       obsolete="false"
       archived="false">
       <result status="valid" time="0.00"/>
      </proof>
      <proof
       prover="1"
       timelimit="10"
       memlimit="0"
       obsolete="false"
       archived="false">
       <result status="valid" time="0.01"/>
      </proof>
      <proof
       prover="0"
       timelimit="10"
       memlimit="0"
       obsolete="false"
       archived="false">
       <result status="valid" time="0.01"/>
      </proof>
     </goal>
    </transf>
   </goal>
  </theory>
  <theory
   name="MaxAndSum2"
   locfile="programs/vstte10_max_sum/../vstte10_max_sum.mlw"
   loclnum="29" loccnumb="7" loccnume="17"
   verified="true"
   expanded="true">
   <goal
    name="WP_parameter max_sum"
    locfile="programs/vstte10_max_sum/../vstte10_max_sum.mlw"
    loclnum="41" loccnumb="6" loccnume="13"
    expl="parameter max_sum"
    sum="abe8c5c7cd6f745e56c07b3f225b85c0"
    proved="true"
    expanded="true"
    shape="ainfix &lt;=V5ainfix *V1V4Aais_maxV3c0V1V4Aainfix =V5asumV2c0V1Iainfix &lt;=V5ainfix *ainfix +ainfix -V1c1c1V4Aais_maxV3c0ainfix +ainfix -V1c1c1V4Aainfix =V5asumV2c0ainfix +ainfix -V1c1c1Aiainfix &lt;V4agetV2V6ainfix &lt;=V8ainfix *ainfix +V6c1V7Aais_maxV3c0ainfix +V6c1V7Aainfix =V8asumV2c0ainfix +V6c1Iainfix =V8ainfix +V5agetV2V6FAainfix &lt;V6V0Aainfix &lt;=c0V6Iainfix =V7agetV2V6FAainfix &lt;V6V0Aainfix &lt;=c0V6ainfix &lt;=V9ainfix *ainfix +V6c1V4Aais_maxV3c0ainfix +V6c1V4Aainfix =V9asumV2c0ainfix +V6c1Iainfix =V9ainfix +V5agetV2V6FAainfix &lt;V6V0Aainfix &lt;=c0V6Aainfix &lt;V6V0Aainfix &lt;=c0V6Iainfix &lt;=V5ainfix *V6V4Aais_maxV3c0V6V4Aainfix =V5asumV2c0V6Iainfix &lt;=V6ainfix -V1c1Aainfix &lt;=c0V6FFAainfix &lt;=c0ainfix *c0c0Aais_maxV3c0c0c0Aainfix =c0asumV2c0c0Iainfix &lt;=c0ainfix -V1c1Aainfix &lt;=c0ainfix *V1c0Aais_maxV3c0V1c0Aainfix =c0asumV2c0V1Iainfix &gt;c0ainfix -V1c1Iainfix &gt;=agetV2V10c0Iainfix &lt;V10V1Aainfix &lt;=c0V10FAainfix =V1V0Aainfix &lt;=c0V1Lamk arrayV0V2FF">
    <label
     name="expl:parameter max_sum"/>
    <transf
     name="split_goal"
     proved="true"
     expanded="true">
     <goal
      name="WP_parameter max_sum.1"
      locfile="programs/vstte10_max_sum/../vstte10_max_sum.mlw"
      loclnum="41" loccnumb="6" loccnume="13"
      expl="normal postcondition"
      sum="833bd5fc0e6bc95e5d93b1c194a77988"
      proved="true"
      expanded="true"
      shape="ainfix &lt;=c0ainfix *V1c0Aais_maxV3c0V1c0Aainfix =c0asumV2c0V1Iainfix &gt;c0ainfix -V1c1Iainfix &gt;=agetV2V4c0Iainfix &lt;V4V1Aainfix &lt;=c0V4FAainfix =V1V0Aainfix &lt;=c0V1Lamk arrayV0V2FF">
      <label
       name="expl:parameter max_sum"/>
      <proof
       prover="3"
       timelimit="10"
       memlimit="0"
       obsolete="false"
       archived="false">
       <result status="valid" time="0.02"/>
      </proof>
      <proof
       prover="1"
       timelimit="10"
       memlimit="0"
       obsolete="false"
       archived="false">
       <result status="valid" time="0.01"/>
      </proof>
      <proof
       prover="0"
       timelimit="10"
       memlimit="0"
       obsolete="false"
       archived="false">
       <result status="valid" time="0.01"/>
      </proof>
     </goal>
     <goal
      name="WP_parameter max_sum.2"
      locfile="programs/vstte10_max_sum/../vstte10_max_sum.mlw"
      loclnum="41" loccnumb="6" loccnume="13"
      expl="for loop initialization"
      sum="d9a25e5f40d65c8d0a2bbc5ba1dd53fb"
      proved="true"
      expanded="true"
      shape="ainfix &lt;=c0ainfix *c0c0Aais_maxV3c0c0c0Aainfix =c0asumV2c0c0Iainfix &lt;=c0ainfix -V1c1Iainfix &gt;=agetV2V4c0Iainfix &lt;V4V1Aainfix &lt;=c0V4FAainfix =V1V0Aainfix &lt;=c0V1Lamk arrayV0V2FF">
      <label
       name="expl:parameter max_sum"/>
      <proof
       prover="3"
       timelimit="10"
       memlimit="0"
       obsolete="false"
       archived="false">
       <result status="valid" time="0.02"/>
      </proof>
      <proof
       prover="1"
       timelimit="10"
       memlimit="0"
       obsolete="false"
       archived="false">
       <result status="valid" time="0.01"/>
      </proof>
      <proof
       prover="0"
       timelimit="10"
       memlimit="0"
       obsolete="false"
       archived="false">
       <result status="valid" time="0.02"/>
      </proof>
     </goal>
     <goal
      name="WP_parameter max_sum.3"
      locfile="programs/vstte10_max_sum/../vstte10_max_sum.mlw"
      loclnum="41" loccnumb="6" loccnume="13"
      expl="for loop preservation"
      sum="d276349333ef5473aac9bfaca8477839"
      proved="true"
      expanded="true"
      shape="iainfix &lt;V4agetV2V6ainfix &lt;=V8ainfix *ainfix +V6c1V7Aais_maxV3c0ainfix +V6c1V7Aainfix =V8asumV2c0ainfix +V6c1Iainfix =V8ainfix +V5agetV2V6FAainfix &lt;V6V0Aainfix &lt;=c0V6Iainfix =V7agetV2V6FAainfix &lt;V6V0Aainfix &lt;=c0V6ainfix &lt;=V9ainfix *ainfix +V6c1V4Aais_maxV3c0ainfix +V6c1V4Aainfix =V9asumV2c0ainfix +V6c1Iainfix =V9ainfix +V5agetV2V6FAainfix &lt;V6V0Aainfix &lt;=c0V6Aainfix &lt;V6V0Aainfix &lt;=c0V6Iainfix &lt;=V5ainfix *V6V4Aais_maxV3c0V6V4Aainfix =V5asumV2c0V6Iainfix &lt;=V6ainfix -V1c1Aainfix &lt;=c0V6FFIainfix &lt;=c0ainfix -V1c1Iainfix &gt;=agetV2V10c0Iainfix &lt;V10V1Aainfix &lt;=c0V10FAainfix =V1V0Aainfix &lt;=c0V1Lamk arrayV0V2FF">
      <label
       name="expl:parameter max_sum"/>
      <transf
       name="split_goal"
       proved="true"
       expanded="true">
       <goal
        name="WP_parameter max_sum.3.1"
        locfile="programs/vstte10_max_sum/../vstte10_max_sum.mlw"
        loclnum="41" loccnumb="6" loccnume="13"
        expl="for loop preservation"
        sum="3d0b2b750edee9854a75f5e847aad706"
        proved="true"
        expanded="true"
        shape="ainfix &lt;V6V0Aainfix &lt;=c0V6Iainfix &lt;=V5ainfix *V6V4Aais_maxV3c0V6V4Aainfix =V5asumV2c0V6Iainfix &lt;=V6ainfix -V1c1Aainfix &lt;=c0V6FFIainfix &lt;=c0ainfix -V1c1Iainfix &gt;=agetV2V7c0Iainfix &lt;V7V1Aainfix &lt;=c0V7FAainfix =V1V0Aainfix &lt;=c0V1Lamk arrayV0V2FF">
        <label
         name="expl:parameter max_sum"/>
        <proof
         prover="3"
         timelimit="10"
         memlimit="0"
         obsolete="false"
         archived="false">
         <result status="valid" time="0.02"/>
        </proof>
        <proof
         prover="1"
         timelimit="10"
         memlimit="0"
         obsolete="false"
         archived="false">
         <result status="valid" time="0.01"/>
        </proof>
        <proof
         prover="0"
         timelimit="10"
         memlimit="0"
         obsolete="false"
         archived="false">
         <result status="valid" time="0.01"/>
        </proof>
       </goal>
       <goal
        name="WP_parameter max_sum.3.2"
        locfile="programs/vstte10_max_sum/../vstte10_max_sum.mlw"
        loclnum="41" loccnumb="6" loccnume="13"
        expl="for loop preservation"
        sum="87c369418c3d52c2f0b379196b275069"
        proved="true"
        expanded="true"
        shape="ainfix &lt;V6V0Aainfix &lt;=c0V6Iainfix &lt;V4agetV2V6Iainfix &lt;V6V0Aainfix &lt;=c0V6Iainfix &lt;=V5ainfix *V6V4Aais_maxV3c0V6V4Aainfix =V5asumV2c0V6Iainfix &lt;=V6ainfix -V1c1Aainfix &lt;=c0V6FFIainfix &lt;=c0ainfix -V1c1Iainfix &gt;=agetV2V7c0Iainfix &lt;V7V1Aainfix &lt;=c0V7FAainfix =V1V0Aainfix &lt;=c0V1Lamk arrayV0V2FF">
        <label
         name="expl:parameter max_sum"/>
        <proof
         prover="3"
         timelimit="10"
         memlimit="0"
         obsolete="false"
         archived="false">
         <result status="valid" time="0.00"/>
        </proof>
        <proof
         prover="1"
         timelimit="10"
         memlimit="0"
         obsolete="false"
         archived="false">
         <result status="valid" time="0.01"/>
        </proof>
        <proof
         prover="0"
         timelimit="10"
         memlimit="0"
         obsolete="false"
         archived="false">
         <result status="valid" time="0.02"/>
        </proof>
       </goal>
       <goal
        name="WP_parameter max_sum.3.3"
        locfile="programs/vstte10_max_sum/../vstte10_max_sum.mlw"
        loclnum="41" loccnumb="6" loccnume="13"
        expl="for loop preservation"
        sum="31f7799d86d0de9a637f22ab2a397a26"
        proved="true"
        expanded="true"
        shape="ainfix &lt;V6V0Aainfix &lt;=c0V6Iainfix =V7agetV2V6FIainfix &lt;V6V0Aainfix &lt;=c0V6Iainfix &lt;V4agetV2V6Iainfix &lt;V6V0Aainfix &lt;=c0V6Iainfix &lt;=V5ainfix *V6V4Aais_maxV3c0V6V4Aainfix =V5asumV2c0V6Iainfix &lt;=V6ainfix -V1c1Aainfix &lt;=c0V6FFIainfix &lt;=c0ainfix -V1c1Iainfix &gt;=agetV2V8c0Iainfix &lt;V8V1Aainfix &lt;=c0V8FAainfix =V1V0Aainfix &lt;=c0V1Lamk arrayV0V2FF">
        <label
         name="expl:parameter max_sum"/>
        <proof
         prover="3"
         timelimit="10"
         memlimit="0"
         obsolete="false"
         archived="false">
         <result status="valid" time="0.02"/>
        </proof>
        <proof
         prover="1"
         timelimit="10"
         memlimit="0"
         obsolete="false"
         archived="false">
         <result status="valid" time="0.01"/>
        </proof>
        <proof
         prover="0"
         timelimit="10"
         memlimit="0"
         obsolete="false"
         archived="false">
         <result status="valid" time="0.01"/>
        </proof>
       </goal>
       <goal
        name="WP_parameter max_sum.3.4"
        locfile="programs/vstte10_max_sum/../vstte10_max_sum.mlw"
        loclnum="41" loccnumb="6" loccnume="13"
        expl="for loop preservation"
        sum="b4531c67c715308756b0c9771edcc653"
        proved="true"
        expanded="true"
        shape="ainfix =V8asumV2c0ainfix +V6c1Iainfix =V8ainfix +V5agetV2V6FIainfix &lt;V6V0Aainfix &lt;=c0V6Iainfix =V7agetV2V6FIainfix &lt;V6V0Aainfix &lt;=c0V6Iainfix &lt;V4agetV2V6Iainfix &lt;V6V0Aainfix &lt;=c0V6Iainfix &lt;=V5ainfix *V6V4Aais_maxV3c0V6V4Aainfix =V5asumV2c0V6Iainfix &lt;=V6ainfix -V1c1Aainfix &lt;=c0V6FFIainfix &lt;=c0ainfix -V1c1Iainfix &gt;=agetV2V9c0Iainfix &lt;V9V1Aainfix &lt;=c0V9FAainfix =V1V0Aainfix &lt;=c0V1Lamk arrayV0V2FF">
        <label
         name="expl:parameter max_sum"/>
        <proof
         prover="3"
         timelimit="10"
         memlimit="0"
         obsolete="false"
         archived="false">
         <result status="valid" time="0.02"/>
        </proof>
        <proof
         prover="1"
         timelimit="10"
         memlimit="0"
         obsolete="false"
         archived="false">
         <result status="valid" time="0.02"/>
        </proof>
        <proof
         prover="0"
         timelimit="10"
         memlimit="0"
         obsolete="false"
         archived="false">
         <result status="valid" time="0.01"/>
        </proof>
       </goal>
       <goal
        name="WP_parameter max_sum.3.5"
        locfile="programs/vstte10_max_sum/../vstte10_max_sum.mlw"
        loclnum="41" loccnumb="6" loccnume="13"
        expl="for loop preservation"
        sum="0f58d087e02c27cc5281978b59113446"
        proved="true"
        expanded="true"
        shape="ais_maxV3c0ainfix +V6c1V7Iainfix =V8ainfix +V5agetV2V6FIainfix &lt;V6V0Aainfix &lt;=c0V6Iainfix =V7agetV2V6FIainfix &lt;V6V0Aainfix &lt;=c0V6Iainfix &lt;V4agetV2V6Iainfix &lt;V6V0Aainfix &lt;=c0V6Iainfix &lt;=V5ainfix *V6V4Aais_maxV3c0V6V4Aainfix =V5asumV2c0V6Iainfix &lt;=V6ainfix -V1c1Aainfix &lt;=c0V6FFIainfix &lt;=c0ainfix -V1c1Iainfix &gt;=agetV2V9c0Iainfix &lt;V9V1Aainfix &lt;=c0V9FAainfix =V1V0Aainfix &lt;=c0V1Lamk arrayV0V2FF">
        <label
         name="expl:parameter max_sum"/>
        <proof
         prover="0"
         timelimit="10"
         memlimit="0"
         obsolete="false"
         archived="false">
         <result status="timeout" time="10.01"/>
        </proof>
        <proof
         prover="4"
         timelimit="5"
         memlimit="0"
         obsolete="false"
         archived="false">
         <result status="valid" time="0.02"/>
        </proof>
       </goal>
       <goal
        name="WP_parameter max_sum.3.6"
        locfile="programs/vstte10_max_sum/../vstte10_max_sum.mlw"
        loclnum="41" loccnumb="6" loccnume="13"
        expl="for loop preservation"
        sum="6911c4cae44d719dd3547a377cd7a0ec"
        proved="true"
        expanded="true"
        shape="ainfix &lt;=V8ainfix *ainfix +V6c1V7Iainfix =V8ainfix +V5agetV2V6FIainfix &lt;V6V0Aainfix &lt;=c0V6Iainfix =V7agetV2V6FIainfix &lt;V6V0Aainfix &lt;=c0V6Iainfix &lt;V4agetV2V6Iainfix &lt;V6V0Aainfix &lt;=c0V6Iainfix &lt;=V5ainfix *V6V4Aais_maxV3c0V6V4Aainfix =V5asumV2c0V6Iainfix &lt;=V6ainfix -V1c1Aainfix &lt;=c0V6FFIainfix &lt;=c0ainfix -V1c1Iainfix &gt;=agetV2V9c0Iainfix &lt;V9V1Aainfix &lt;=c0V9FAainfix =V1V0Aainfix &lt;=c0V1Lamk arrayV0V2FF">
        <label
         name="expl:parameter max_sum"/>
        <proof
         prover="2"
         timelimit="10"
         memlimit="0"
         edited="vstte10_max_sum_WP_MaxAndSum2_WP_parameter_max_sum_1.v"
         obsolete="false"
         archived="false">
         <result status="valid" time="0.56"/>
        </proof>
       </goal>
       <goal
        name="WP_parameter max_sum.3.7"
        locfile="programs/vstte10_max_sum/../vstte10_max_sum.mlw"
        loclnum="41" loccnumb="6" loccnume="13"
        expl="for loop preservation"
        sum="44318eb3a4ec8ae4db8d79d50cb77009"
        proved="true"
        expanded="true"
        shape="ainfix &lt;V6V0Aainfix &lt;=c0V6Iainfix &lt;V4agetV2V6NIainfix &lt;V6V0Aainfix &lt;=c0V6Iainfix &lt;=V5ainfix *V6V4Aais_maxV3c0V6V4Aainfix =V5asumV2c0V6Iainfix &lt;=V6ainfix -V1c1Aainfix &lt;=c0V6FFIainfix &lt;=c0ainfix -V1c1Iainfix &gt;=agetV2V7c0Iainfix &lt;V7V1Aainfix &lt;=c0V7FAainfix =V1V0Aainfix &lt;=c0V1Lamk arrayV0V2FF">
        <label
         name="expl:parameter max_sum"/>
        <proof
         prover="3"
         timelimit="10"
         memlimit="0"
         obsolete="false"
         archived="false">
         <result status="valid" time="0.00"/>
        </proof>
        <proof
         prover="1"
         timelimit="10"
         memlimit="0"
         obsolete="false"
         archived="false">
         <result status="valid" time="0.00"/>
        </proof>
        <proof
         prover="0"
         timelimit="10"
         memlimit="0"
         obsolete="false"
         archived="false">
         <result status="valid" time="0.01"/>
        </proof>
       </goal>
       <goal
        name="WP_parameter max_sum.3.8"
        locfile="programs/vstte10_max_sum/../vstte10_max_sum.mlw"
        loclnum="41" loccnumb="6" loccnume="13"
        expl="for loop preservation"
        sum="221e78c30c25f7b9eb1ccd5dec66d0fc"
        proved="true"
        expanded="true"
        shape="ainfix =V7asumV2c0ainfix +V6c1Iainfix =V7ainfix +V5agetV2V6FIainfix &lt;V6V0Aainfix &lt;=c0V6Iainfix &lt;V4agetV2V6NIainfix &lt;V6V0Aainfix &lt;=c0V6Iainfix &lt;=V5ainfix *V6V4Aais_maxV3c0V6V4Aainfix =V5asumV2c0V6Iainfix &lt;=V6ainfix -V1c1Aainfix &lt;=c0V6FFIainfix &lt;=c0ainfix -V1c1Iainfix &gt;=agetV2V8c0Iainfix &lt;V8V1Aainfix &lt;=c0V8FAainfix =V1V0Aainfix &lt;=c0V1Lamk arrayV0V2FF">
        <label
         name="expl:parameter max_sum"/>
        <proof
         prover="3"
         timelimit="10"
         memlimit="0"
         obsolete="false"
         archived="false">
         <result status="valid" time="0.01"/>
        </proof>
        <proof
         prover="1"
         timelimit="10"
         memlimit="0"
         obsolete="false"
         archived="false">
         <result status="valid" time="0.01"/>
        </proof>
        <proof
         prover="0"
         timelimit="10"
         memlimit="0"
         obsolete="false"
         archived="false">
         <result status="valid" time="0.01"/>
        </proof>
       </goal>
       <goal
        name="WP_parameter max_sum.3.9"
        locfile="programs/vstte10_max_sum/../vstte10_max_sum.mlw"
        loclnum="41" loccnumb="6" loccnume="13"
        expl="for loop preservation"
        sum="10a5702098df137df15aefaab2890862"
        proved="true"
        expanded="true"
        shape="ais_maxV3c0ainfix +V6c1V4Iainfix =V7ainfix +V5agetV2V6FIainfix &lt;V6V0Aainfix &lt;=c0V6Iainfix &lt;V4agetV2V6NIainfix &lt;V6V0Aainfix &lt;=c0V6Iainfix &lt;=V5ainfix *V6V4Aais_maxV3c0V6V4Aainfix =V5asumV2c0V6Iainfix &lt;=V6ainfix -V1c1Aainfix &lt;=c0V6FFIainfix &lt;=c0ainfix -V1c1Iainfix &gt;=agetV2V8c0Iainfix &lt;V8V1Aainfix &lt;=c0V8FAainfix =V1V0Aainfix &lt;=c0V1Lamk arrayV0V2FF">
        <label
         name="expl:parameter max_sum"/>
        <proof
         prover="1"
         timelimit="10"
         memlimit="0"
         obsolete="false"
         archived="false">
         <result status="valid" time="0.03"/>
        </proof>
        <proof
         prover="0"
         timelimit="10"
         memlimit="0"
         obsolete="false"
         archived="false">
         <result status="timeout" time="10.10"/>
        </proof>
       </goal>
       <goal
        name="WP_parameter max_sum.3.10"
        locfile="programs/vstte10_max_sum/../vstte10_max_sum.mlw"
        loclnum="41" loccnumb="6" loccnume="13"
        expl="for loop preservation"
        sum="fe0617bd5b4cd3ea91d1f6e50914a863"
        proved="true"
        expanded="true"
        shape="ainfix &lt;=V7ainfix *ainfix +V6c1V4Iainfix =V7ainfix +V5agetV2V6FIainfix &lt;V6V0Aainfix &lt;=c0V6Iainfix &lt;V4agetV2V6NIainfix &lt;V6V0Aainfix &lt;=c0V6Iainfix &lt;=V5ainfix *V6V4Aais_maxV3c0V6V4Aainfix =V5asumV2c0V6Iainfix &lt;=V6ainfix -V1c1Aainfix &lt;=c0V6FFIainfix &lt;=c0ainfix -V1c1Iainfix &gt;=agetV2V8c0Iainfix &lt;V8V1Aainfix &lt;=c0V8FAainfix =V1V0Aainfix &lt;=c0V1Lamk arrayV0V2FF">
        <label
         name="expl:parameter max_sum"/>
        <proof
         prover="3"
         timelimit="10"
         memlimit="0"
         obsolete="false"
         archived="false">
         <result status="valid" time="0.02"/>
        </proof>
        <proof
         prover="1"
         timelimit="10"
         memlimit="0"
         obsolete="false"
         archived="false">
         <result status="valid" time="0.01"/>
        </proof>
        <proof
         prover="0"
         timelimit="10"
         memlimit="0"
         obsolete="false"
         archived="false">
         <result status="valid" time="0.01"/>
        </proof>
       </goal>
      </transf>
     </goal>
     <goal
      name="WP_parameter max_sum.4"
      locfile="programs/vstte10_max_sum/../vstte10_max_sum.mlw"
      loclnum="41" loccnumb="6" loccnume="13"
      expl="normal postcondition"
      sum="3a220d93b8f1652fe30b9c4ad96e11cd"
      proved="true"
      expanded="true"
      shape="ainfix &lt;=V5ainfix *V1V4Aais_maxV3c0V1V4Aainfix =V5asumV2c0V1Iainfix &lt;=V5ainfix *ainfix +ainfix -V1c1c1V4Aais_maxV3c0ainfix +ainfix -V1c1c1V4Aainfix =V5asumV2c0ainfix +ainfix -V1c1c1FIainfix &lt;=c0ainfix -V1c1Iainfix &gt;=agetV2V6c0Iainfix &lt;V6V1Aainfix &lt;=c0V6FAainfix =V1V0Aainfix &lt;=c0V1Lamk arrayV0V2FF">
      <label
       name="expl:parameter max_sum"/>
      <proof
       prover="3"
       timelimit="10"
       memlimit="0"
       obsolete="false"
       archived="false">
       <result status="valid" time="0.00"/>
      </proof>
      <proof
       prover="1"
       timelimit="10"
       memlimit="0"
       obsolete="false"
       archived="false">
       <result status="valid" time="0.00"/>
      </proof>
      <proof
       prover="0"
       timelimit="10"
       memlimit="0"
       obsolete="false"
       archived="false">
       <result status="valid" time="0.00"/>
      </proof>
     </goal>
    </transf>
   </goal>
  </theory>
  <theory
   name="TestCase"
   locfile="programs/vstte10_max_sum/../vstte10_max_sum.mlw"
   loclnum="55" loccnumb="7" loccnume="15"
   verified="true"
   expanded="true">
   <goal
    name="WP_parameter test_case"
    locfile="programs/vstte10_max_sum/../vstte10_max_sum.mlw"
    loclnum="61" loccnumb="6" loccnume="15"
    expl="parameter test_case"
    sum="09b081a4a88e9f7e23b16ebf87411167"
    proved="true"
    expanded="true"
    shape="ainfix =V11c10Aainfix =V10c45Iainfix &lt;=V10ainfix *c10V11Aais_maxamk arrayc10V9c0c10V11Aainfix =V10asumV9c0c10FAainfix &gt;=agetV9V12c0Iainfix &lt;V12c10Aainfix &lt;=c0V12FAainfix &lt;=c0c10Iainfix =V9asetV8c9c6FAainfix &lt;c9c10Aainfix &lt;=c0c9Iainfix =V8asetV7c8c10FAainfix &lt;c8c10Aainfix &lt;=c0c8Iainfix =V7asetV6c7c1FAainfix &lt;c7c10Aainfix &lt;=c0c7Iainfix =V6asetV5c6c2FAainfix &lt;c6c10Aainfix &lt;=c0c6Iainfix =V5asetV4c5c3FAainfix &lt;c5c10Aainfix &lt;=c0c5Iainfix =V4asetV3c4c7FAainfix &lt;c4c10Aainfix &lt;=c0c4Iainfix =V3asetV2c3c2FAainfix &lt;c3c10Aainfix &lt;=c0c3Iainfix =V2asetV1c2c0FAainfix &lt;c2c10Aainfix &lt;=c0c2Iainfix =V1asetV0c1c5FAainfix &lt;c1c10Aainfix &lt;=c0c1Iainfix =V0asetaconstc0c0c9FAainfix &lt;c0c10Aainfix &lt;=c0c0Aainfix &gt;=c10c0">
    <label
     name="expl:parameter test_case"/>
    <transf
     name="split_goal"
     proved="true"
     expanded="true">
     <goal
      name="WP_parameter test_case.1"
      locfile="programs/vstte10_max_sum/../vstte10_max_sum.mlw"
      loclnum="61" loccnumb="6" loccnume="15"
      expl="precondition"
      sum="4d185aeeb94ae3b3a67a8b2100789e93"
      proved="true"
      expanded="true"
      shape="ainfix &gt;=c10c0">
      <label
       name="expl:parameter test_case"/>
      <proof
       prover="3"
       timelimit="10"
       memlimit="0"
       obsolete="false"
       archived="false">
       <result status="valid" time="0.00"/>
      </proof>
      <proof
       prover="1"
       timelimit="10"
       memlimit="0"
       obsolete="false"
       archived="false">
       <result status="valid" time="0.00"/>
      </proof>
      <proof
       prover="0"
       timelimit="10"
       memlimit="0"
       obsolete="false"
       archived="false">
       <result status="valid" time="0.01"/>
      </proof>
     </goal>
     <goal
      name="WP_parameter test_case.2"
      locfile="programs/vstte10_max_sum/../vstte10_max_sum.mlw"
      loclnum="61" loccnumb="6" loccnume="15"
      expl="precondition"
      sum="0994ec94d2ad9dd65bf18adf49e35aaa"
      proved="true"
      expanded="true"
      shape="ainfix &lt;c0c10Aainfix &lt;=c0c0Iainfix &gt;=c10c0">
      <label
       name="expl:parameter test_case"/>
      <proof
       prover="3"
       timelimit="10"
       memlimit="0"
       obsolete="false"
       archived="false">
       <result status="valid" time="0.00"/>
      </proof>
      <proof
       prover="1"
       timelimit="10"
       memlimit="0"
       obsolete="false"
       archived="false">
       <result status="valid" time="0.00"/>
      </proof>
      <proof
       prover="0"
       timelimit="10"
       memlimit="0"
       obsolete="false"
       archived="false">
       <result status="valid" time="0.01"/>
      </proof>
     </goal>
     <goal
      name="WP_parameter test_case.3"
      locfile="programs/vstte10_max_sum/../vstte10_max_sum.mlw"
      loclnum="61" loccnumb="6" loccnume="15"
      expl="precondition"
      sum="301f02e9faff0c70479190edad3db0da"
      proved="true"
      expanded="true"
      shape="ainfix &lt;c1c10Aainfix &lt;=c0c1Iainfix =V0asetaconstc0c0c9FIainfix &lt;c0c10Aainfix &lt;=c0c0Iainfix &gt;=c10c0">
      <label
       name="expl:parameter test_case"/>
      <proof
       prover="3"
       timelimit="10"
       memlimit="0"
       obsolete="false"
       archived="false">
       <result status="valid" time="0.00"/>
      </proof>
      <proof
       prover="1"
       timelimit="10"
       memlimit="0"
       obsolete="false"
       archived="false">
       <result status="valid" time="0.00"/>
      </proof>
      <proof
       prover="0"
       timelimit="10"
       memlimit="0"
       obsolete="false"
       archived="false">
       <result status="valid" time="0.01"/>
      </proof>
     </goal>
     <goal
      name="WP_parameter test_case.4"
      locfile="programs/vstte10_max_sum/../vstte10_max_sum.mlw"
      loclnum="61" loccnumb="6" loccnume="15"
      expl="precondition"
      sum="1c40ff8a362d2cc29035d9fa3ae9ee0f"
      proved="true"
      expanded="true"
      shape="ainfix &lt;c2c10Aainfix &lt;=c0c2Iainfix =V1asetV0c1c5FIainfix &lt;c1c10Aainfix &lt;=c0c1Iainfix =V0asetaconstc0c0c9FIainfix &lt;c0c10Aainfix &lt;=c0c0Iainfix &gt;=c10c0">
      <label
       name="expl:parameter test_case"/>
      <proof
       prover="3"
       timelimit="10"
       memlimit="0"
       obsolete="false"
       archived="false">
       <result status="valid" time="0.00"/>
      </proof>
      <proof
       prover="1"
       timelimit="10"
       memlimit="0"
       obsolete="false"
       archived="false">
       <result status="valid" time="0.00"/>
      </proof>
      <proof
       prover="0"
       timelimit="10"
       memlimit="0"
       obsolete="false"
       archived="false">
       <result status="valid" time="0.00"/>
      </proof>
     </goal>
     <goal
      name="WP_parameter test_case.5"
      locfile="programs/vstte10_max_sum/../vstte10_max_sum.mlw"
      loclnum="61" loccnumb="6" loccnume="15"
      expl="precondition"
      sum="b217dd37fbf60cf82940c09dd5f507e7"
      proved="true"
      expanded="true"
      shape="ainfix &lt;c3c10Aainfix &lt;=c0c3Iainfix =V2asetV1c2c0FIainfix &lt;c2c10Aainfix &lt;=c0c2Iainfix =V1asetV0c1c5FIainfix &lt;c1c10Aainfix &lt;=c0c1Iainfix =V0asetaconstc0c0c9FIainfix &lt;c0c10Aainfix &lt;=c0c0Iainfix &gt;=c10c0">
      <label
       name="expl:parameter test_case"/>
      <proof
       prover="3"
       timelimit="10"
       memlimit="0"
       obsolete="false"
       archived="false">
       <result status="valid" time="0.00"/>
      </proof>
      <proof
       prover="0"
       timelimit="10"
       memlimit="0"
       obsolete="false"
       archived="false">
       <result status="valid" time="0.01"/>
      </proof>
      <proof
       prover="1"
       timelimit="3"
       memlimit="0"
       obsolete="false"
       archived="false">
       <result status="valid" time="0.00"/>
      </proof>
     </goal>
     <goal
      name="WP_parameter test_case.6"
      locfile="programs/vstte10_max_sum/../vstte10_max_sum.mlw"
      loclnum="61" loccnumb="6" loccnume="15"
      expl="precondition"
      sum="a048bb03426d5e0512ee5f99a807f9e3"
      proved="true"
      expanded="true"
      shape="ainfix &lt;c4c10Aainfix &lt;=c0c4Iainfix =V3asetV2c3c2FIainfix &lt;c3c10Aainfix &lt;=c0c3Iainfix =V2asetV1c2c0FIainfix &lt;c2c10Aainfix &lt;=c0c2Iainfix =V1asetV0c1c5FIainfix &lt;c1c10Aainfix &lt;=c0c1Iainfix =V0asetaconstc0c0c9FIainfix &lt;c0c10Aainfix &lt;=c0c0Iainfix &gt;=c10c0">
      <label
       name="expl:parameter test_case"/>
      <proof
       prover="3"
       timelimit="3"
       memlimit="0"
       obsolete="false"
       archived="false">
       <result status="valid" time="0.00"/>
      </proof>
      <proof
       prover="1"
       timelimit="10"
       memlimit="0"
       obsolete="false"
       archived="false">
       <result status="valid" time="0.00"/>
      </proof>
      <proof
       prover="0"
       timelimit="3"
       memlimit="0"
       obsolete="false"
       archived="false">
       <result status="valid" time="0.01"/>
      </proof>
     </goal>
     <goal
      name="WP_parameter test_case.7"
      locfile="programs/vstte10_max_sum/../vstte10_max_sum.mlw"
      loclnum="61" loccnumb="6" loccnume="15"
      expl="precondition"
      sum="9e36cea44f8166be91945d009ebae7a4"
      proved="true"
      expanded="true"
      shape="ainfix &lt;c5c10Aainfix &lt;=c0c5Iainfix =V4asetV3c4c7FIainfix &lt;c4c10Aainfix &lt;=c0c4Iainfix =V3asetV2c3c2FIainfix &lt;c3c10Aainfix &lt;=c0c3Iainfix =V2asetV1c2c0FIainfix &lt;c2c10Aainfix &lt;=c0c2Iainfix =V1asetV0c1c5FIainfix &lt;c1c10Aainfix &lt;=c0c1Iainfix =V0asetaconstc0c0c9FIainfix &lt;c0c10Aainfix &lt;=c0c0Iainfix &gt;=c10c0">
      <label
       name="expl:parameter test_case"/>
      <proof
       prover="3"
       timelimit="10"
       memlimit="0"
       obsolete="false"
       archived="false">
       <result status="valid" time="0.00"/>
      </proof>
      <proof
       prover="1"
       timelimit="10"
       memlimit="0"
       obsolete="false"
       archived="false">
       <result status="valid" time="0.00"/>
      </proof>
      <proof
       prover="0"
       timelimit="10"
       memlimit="0"
       obsolete="false"
       archived="false">
       <result status="valid" time="0.01"/>
      </proof>
     </goal>
     <goal
      name="WP_parameter test_case.8"
      locfile="programs/vstte10_max_sum/../vstte10_max_sum.mlw"
      loclnum="61" loccnumb="6" loccnume="15"
      expl="precondition"
      sum="1d0d11d9c4e488bcfc91164d044e4fb3"
      proved="true"
      expanded="true"
      shape="ainfix &lt;c6c10Aainfix &lt;=c0c6Iainfix =V5asetV4c5c3FIainfix &lt;c5c10Aainfix &lt;=c0c5Iainfix =V4asetV3c4c7FIainfix &lt;c4c10Aainfix &lt;=c0c4Iainfix =V3asetV2c3c2FIainfix &lt;c3c10Aainfix &lt;=c0c3Iainfix =V2asetV1c2c0FIainfix &lt;c2c10Aainfix &lt;=c0c2Iainfix =V1asetV0c1c5FIainfix &lt;c1c10Aainfix &lt;=c0c1Iainfix =V0asetaconstc0c0c9FIainfix &lt;c0c10Aainfix &lt;=c0c0Iainfix &gt;=c10c0">
      <label
       name="expl:parameter test_case"/>
      <proof
       prover="3"
       timelimit="10"
       memlimit="0"
       obsolete="false"
       archived="false">
       <result status="valid" time="0.00"/>
      </proof>
      <proof
       prover="1"
       timelimit="10"
       memlimit="0"
       obsolete="false"
       archived="false">
       <result status="valid" time="0.00"/>
      </proof>
      <proof
       prover="0"
       timelimit="10"
       memlimit="0"
       obsolete="false"
       archived="false">
       <result status="valid" time="0.01"/>
      </proof>
     </goal>
     <goal
      name="WP_parameter test_case.9"
      locfile="programs/vstte10_max_sum/../vstte10_max_sum.mlw"
      loclnum="61" loccnumb="6" loccnume="15"
      expl="precondition"
      sum="54e1991af5707d41977745acc02771c0"
      proved="true"
      expanded="true"
      shape="ainfix &lt;c7c10Aainfix &lt;=c0c7Iainfix =V6asetV5c6c2FIainfix &lt;c6c10Aainfix &lt;=c0c6Iainfix =V5asetV4c5c3FIainfix &lt;c5c10Aainfix &lt;=c0c5Iainfix =V4asetV3c4c7FIainfix &lt;c4c10Aainfix &lt;=c0c4Iainfix =V3asetV2c3c2FIainfix &lt;c3c10Aainfix &lt;=c0c3Iainfix =V2asetV1c2c0FIainfix &lt;c2c10Aainfix &lt;=c0c2Iainfix =V1asetV0c1c5FIainfix &lt;c1c10Aainfix &lt;=c0c1Iainfix =V0asetaconstc0c0c9FIainfix &lt;c0c10Aainfix &lt;=c0c0Iainfix &gt;=c10c0">
      <label
       name="expl:parameter test_case"/>
      <proof
       prover="3"
       timelimit="10"
       memlimit="0"
       obsolete="false"
       archived="false">
       <result status="valid" time="0.00"/>
      </proof>
      <proof
       prover="0"
       timelimit="10"
       memlimit="0"
       obsolete="false"
       archived="false">
       <result status="valid" time="0.00"/>
      </proof>
      <proof
       prover="1"
       timelimit="10"
       memlimit="0"
       obsolete="false"
       archived="false">
       <result status="valid" time="0.00"/>
      </proof>
     </goal>
     <goal
      name="WP_parameter test_case.10"
      locfile="programs/vstte10_max_sum/../vstte10_max_sum.mlw"
      loclnum="61" loccnumb="6" loccnume="15"
      expl="precondition"
      sum="782096facc063d70fbad5af1ea3b20cb"
      proved="true"
      expanded="true"
      shape="ainfix &lt;c8c10Aainfix &lt;=c0c8Iainfix =V7asetV6c7c1FIainfix &lt;c7c10Aainfix &lt;=c0c7Iainfix =V6asetV5c6c2FIainfix &lt;c6c10Aainfix &lt;=c0c6Iainfix =V5asetV4c5c3FIainfix &lt;c5c10Aainfix &lt;=c0c5Iainfix =V4asetV3c4c7FIainfix &lt;c4c10Aainfix &lt;=c0c4Iainfix =V3asetV2c3c2FIainfix &lt;c3c10Aainfix &lt;=c0c3Iainfix =V2asetV1c2c0FIainfix &lt;c2c10Aainfix &lt;=c0c2Iainfix =V1asetV0c1c5FIainfix &lt;c1c10Aainfix &lt;=c0c1Iainfix =V0asetaconstc0c0c9FIainfix &lt;c0c10Aainfix &lt;=c0c0Iainfix &gt;=c10c0">
      <label
       name="expl:parameter test_case"/>
      <proof
       prover="3"
       timelimit="10"
       memlimit="0"
       obsolete="false"
       archived="false">
       <result status="valid" time="0.00"/>
      </proof>
      <proof
       prover="1"
       timelimit="10"
       memlimit="0"
       obsolete="false"
       archived="false">
       <result status="valid" time="0.00"/>
      </proof>
      <proof
       prover="0"
       timelimit="10"
       memlimit="0"
       obsolete="false"
       archived="false">
       <result status="valid" time="0.01"/>
      </proof>
     </goal>
     <goal
      name="WP_parameter test_case.11"
      locfile="programs/vstte10_max_sum/../vstte10_max_sum.mlw"
      loclnum="61" loccnumb="6" loccnume="15"
      expl="precondition"
      sum="48f5342aa0d5fdbd113609cf535f6908"
      proved="true"
      expanded="true"
      shape="ainfix &lt;c9c10Aainfix &lt;=c0c9Iainfix =V8asetV7c8c10FIainfix &lt;c8c10Aainfix &lt;=c0c8Iainfix =V7asetV6c7c1FIainfix &lt;c7c10Aainfix &lt;=c0c7Iainfix =V6asetV5c6c2FIainfix &lt;c6c10Aainfix &lt;=c0c6Iainfix =V5asetV4c5c3FIainfix &lt;c5c10Aainfix &lt;=c0c5Iainfix =V4asetV3c4c7FIainfix &lt;c4c10Aainfix &lt;=c0c4Iainfix =V3asetV2c3c2FIainfix &lt;c3c10Aainfix &lt;=c0c3Iainfix =V2asetV1c2c0FIainfix &lt;c2c10Aainfix &lt;=c0c2Iainfix =V1asetV0c1c5FIainfix &lt;c1c10Aainfix &lt;=c0c1Iainfix =V0asetaconstc0c0c9FIainfix &lt;c0c10Aainfix &lt;=c0c0Iainfix &gt;=c10c0">
      <label
       name="expl:parameter test_case"/>
      <proof
       prover="3"
       timelimit="10"
       memlimit="0"
       obsolete="false"
       archived="false">
       <result status="valid" time="0.00"/>
      </proof>
      <proof
       prover="1"
       timelimit="10"
       memlimit="0"
       obsolete="false"
       archived="false">
       <result status="valid" time="0.00"/>
      </proof>
      <proof
       prover="0"
       timelimit="10"
       memlimit="0"
       obsolete="false"
       archived="false">
       <result status="valid" time="0.01"/>
      </proof>
     </goal>
     <goal
      name="WP_parameter test_case.12"
      locfile="programs/vstte10_max_sum/../vstte10_max_sum.mlw"
      loclnum="61" loccnumb="6" loccnume="15"
      expl="precondition"
      sum="333242f2e2f770b3609b11ffcb6a8b13"
      proved="true"
      expanded="true"
      shape="ainfix &gt;=agetV9V10c0Iainfix &lt;V10c10Aainfix &lt;=c0V10FAainfix &lt;=c0c10Iainfix =V9asetV8c9c6FIainfix &lt;c9c10Aainfix &lt;=c0c9Iainfix =V8asetV7c8c10FIainfix &lt;c8c10Aainfix &lt;=c0c8Iainfix =V7asetV6c7c1FIainfix &lt;c7c10Aainfix &lt;=c0c7Iainfix =V6asetV5c6c2FIainfix &lt;c6c10Aainfix &lt;=c0c6Iainfix =V5asetV4c5c3FIainfix &lt;c5c10Aainfix &lt;=c0c5Iainfix =V4asetV3c4c7FIainfix &lt;c4c10Aainfix &lt;=c0c4Iainfix =V3asetV2c3c2FIainfix &lt;c3c10Aainfix &lt;=c0c3Iainfix =V2asetV1c2c0FIainfix &lt;c2c10Aainfix &lt;=c0c2Iainfix =V1asetV0c1c5FIainfix &lt;c1c10Aainfix &lt;=c0c1Iainfix =V0asetaconstc0c0c9FIainfix &lt;c0c10Aainfix &lt;=c0c0Iainfix &gt;=c10c0">
      <label
       name="expl:parameter test_case"/>
      <proof
       prover="3"
       timelimit="10"
       memlimit="0"
       obsolete="false"
       archived="false">
       <result status="valid" time="0.02"/>
      </proof>
      <proof
       prover="1"
       timelimit="10"
       memlimit="0"
       obsolete="false"
       archived="false">
       <result status="valid" time="0.01"/>
      </proof>
      <proof
       prover="0"
       timelimit="10"
       memlimit="0"
       obsolete="false"
       archived="false">
       <result status="valid" time="0.03"/>
      </proof>
     </goal>
     <goal
      name="WP_parameter test_case.13"
      locfile="programs/vstte10_max_sum/../vstte10_max_sum.mlw"
      loclnum="61" loccnumb="6" loccnume="15"
      expl="assertion"
      sum="a6fa6789995dcb43d93b05d7e947398b"
      proved="true"
      expanded="true"
      shape="ainfix =V10c45Iainfix &lt;=V10ainfix *c10V11Aais_maxamk arrayc10V9c0c10V11Aainfix =V10asumV9c0c10FIainfix &gt;=agetV9V12c0Iainfix &lt;V12c10Aainfix &lt;=c0V12FAainfix &lt;=c0c10Iainfix =V9asetV8c9c6FIainfix &lt;c9c10Aainfix &lt;=c0c9Iainfix =V8asetV7c8c10FIainfix &lt;c8c10Aainfix &lt;=c0c8Iainfix =V7asetV6c7c1FIainfix &lt;c7c10Aainfix &lt;=c0c7Iainfix =V6asetV5c6c2FIainfix &lt;c6c10Aainfix &lt;=c0c6Iainfix =V5asetV4c5c3FIainfix &lt;c5c10Aainfix &lt;=c0c5Iainfix =V4asetV3c4c7FIainfix &lt;c4c10Aainfix &lt;=c0c4Iainfix =V3asetV2c3c2FIainfix &lt;c3c10Aainfix &lt;=c0c3Iainfix =V2asetV1c2c0FIainfix &lt;c2c10Aainfix &lt;=c0c2Iainfix =V1asetV0c1c5FIainfix &lt;c1c10Aainfix &lt;=c0c1Iainfix =V0asetaconstc0c0c9FIainfix &lt;c0c10Aainfix &lt;=c0c0Iainfix &gt;=c10c0">
      <label
       name="expl:parameter test_case"/>
      <proof
       prover="3"
       timelimit="10"
       memlimit="0"
       obsolete="false"
       archived="false">
       <result status="valid" time="0.03"/>
      </proof>
      <proof
       prover="1"
       timelimit="10"
       memlimit="0"
       obsolete="false"
       archived="false">
       <result status="valid" time="0.08"/>
      </proof>
     </goal>
     <goal
      name="WP_parameter test_case.14"
      locfile="programs/vstte10_max_sum/../vstte10_max_sum.mlw"
      loclnum="61" loccnumb="6" loccnume="15"
      expl="assertion"
      sum="88d3b7fe5d2ffab1b108ed56a9780e5a"
      proved="true"
      expanded="true"
      shape="ainfix =V11c10Iainfix =V10c45Iainfix &lt;=V10ainfix *c10V11Aais_maxamk arrayc10V9c0c10V11Aainfix =V10asumV9c0c10FIainfix &gt;=agetV9V12c0Iainfix &lt;V12c10Aainfix &lt;=c0V12FAainfix &lt;=c0c10Iainfix =V9asetV8c9c6FIainfix &lt;c9c10Aainfix &lt;=c0c9Iainfix =V8asetV7c8c10FIainfix &lt;c8c10Aainfix &lt;=c0c8Iainfix =V7asetV6c7c1FIainfix &lt;c7c10Aainfix &lt;=c0c7Iainfix =V6asetV5c6c2FIainfix &lt;c6c10Aainfix &lt;=c0c6Iainfix =V5asetV4c5c3FIainfix &lt;c5c10Aainfix &lt;=c0c5Iainfix =V4asetV3c4c7FIainfix &lt;c4c10Aainfix &lt;=c0c4Iainfix =V3asetV2c3c2FIainfix &lt;c3c10Aainfix &lt;=c0c3Iainfix =V2asetV1c2c0FIainfix &lt;c2c10Aainfix &lt;=c0c2Iainfix =V1asetV0c1c5FIainfix &lt;c1c10Aainfix &lt;=c0c1Iainfix =V0asetaconstc0c0c9FIainfix &lt;c0c10Aainfix &lt;=c0c0Iainfix &gt;=c10c0">
      <label
       name="expl:parameter test_case"/>
      <proof
       prover="3"
       timelimit="10"
       memlimit="0"
       obsolete="false"
       archived="false">
       <result status="valid" time="0.02"/>
      </proof>
      <proof
       prover="0"
       timelimit="10"
       memlimit="0"
       obsolete="false"
       archived="false">
       <result status="valid" time="0.87"/>
      </proof>
     </goal>
    </transf>
   </goal>
  </theory>
 </file>
</why3session>
