<?xml version="1.0" encoding="UTF-8"?>
<!DOCTYPE why3session PUBLIC "-//Why3//proof session v5//EN"
"https://www.why3.org/why3session.dtd">
<why3session shape_version="6">
<prover id="0" name="CVC5" version="1.0.5" timelimit="1" steplimit="0" memlimit="1000"/>
<prover id="1" name="CVC3" version="2.4.1" timelimit="5" steplimit="0" memlimit="2000"/>
<prover id="2" name="Eprover" version="2.0" timelimit="5" steplimit="0" memlimit="2000"/>
<prover id="3" name="Alt-Ergo" version="2.2.0" timelimit="5" steplimit="0" memlimit="2000"/>
<prover id="5" name="Alt-Ergo" version="2.3.0" timelimit="5" steplimit="0" memlimit="2000"/>
<prover id="7" name="Z3" version="4.7.1" timelimit="5" steplimit="0" memlimit="2000"/>
<file format="whyml" proved="true">
<path name=".."/><path name="mpz_mul2exp.mlw"/>
<theory name="Zmul2exp" proved="true">
 <goal name="wmpz_mul_2exp&#39;vc" expl="VC for wmpz_mul_2exp" proved="true">
 <transf name="split_vc" proved="true" >
  <goal name="wmpz_mul_2exp&#39;vc.0" expl="precondition" proved="true">
  <proof prover="0"><result status="valid" time="0.060000" steps="7811"/></proof>
  </goal>
  <goal name="wmpz_mul_2exp&#39;vc.1" expl="division by zero" proved="true">
  <proof prover="0"><result status="valid" time="0.130000" steps="8186"/></proof>
  </goal>
  <goal name="wmpz_mul_2exp&#39;vc.2" expl="integer overflow" proved="true">
  <proof prover="0"><result status="valid" time="0.150000" steps="16680"/></proof>
  </goal>
  <goal name="wmpz_mul_2exp&#39;vc.3" expl="precondition" proved="true">
  <proof prover="0"><result status="valid" time="0.140000" steps="21125"/></proof>
  </goal>
  <goal name="wmpz_mul_2exp&#39;vc.4" expl="integer overflow" proved="true">
  <proof prover="0"><result status="valid" time="0.160000" steps="20448"/></proof>
  </goal>
  <goal name="wmpz_mul_2exp&#39;vc.5" expl="precondition" proved="true">
  <proof prover="3" timelimit="1" memlimit="1000"><result status="valid" time="0.020000" steps="37"/></proof>
  </goal>
  <goal name="wmpz_mul_2exp&#39;vc.6" expl="postcondition" proved="true">
  <proof prover="5" timelimit="1" memlimit="1000"><result status="valid" time="0.280000" steps="209"/></proof>
  </goal>
  <goal name="wmpz_mul_2exp&#39;vc.7" expl="postcondition" proved="true">
  <proof prover="0"><result status="valid" time="0.090000" steps="13251"/></proof>
  </goal>
  <goal name="wmpz_mul_2exp&#39;vc.8" expl="postcondition" proved="true">
  <proof prover="0"><result status="valid" time="0.100000" steps="12797"/></proof>
  </goal>
  <goal name="wmpz_mul_2exp&#39;vc.9" expl="integer overflow" proved="true">
  <proof prover="0"><result status="valid" time="0.130000" steps="21532"/></proof>
  </goal>
  <goal name="wmpz_mul_2exp&#39;vc.10" expl="precondition" proved="true">
  <proof prover="0"><result status="valid" time="0.060000" steps="9048"/></proof>
  </goal>
  <goal name="wmpz_mul_2exp&#39;vc.11" expl="precondition" proved="true">
  <proof prover="0"><result status="valid" time="0.070000" steps="9052"/></proof>
  </goal>
  <goal name="wmpz_mul_2exp&#39;vc.12" expl="division by zero" proved="true">
  <proof prover="0"><result status="valid" time="0.034391" steps="9720"/></proof>
  </goal>
  <goal name="wmpz_mul_2exp&#39;vc.13" expl="integer overflow" proved="true">
  <proof prover="0"><result status="valid" time="0.150000" steps="18805"/></proof>
  </goal>
  <goal name="wmpz_mul_2exp&#39;vc.14" expl="assertion" proved="true">
  <proof prover="5"><result status="valid" time="0.040000" steps="69"/></proof>
  <transf name="split_vc" proved="true" >
   <goal name="wmpz_mul_2exp&#39;vc.14.0" expl="assertion" proved="true">
   <proof prover="3" timelimit="1" memlimit="1000"><result status="valid" time="0.080000" steps="69"/></proof>
   </goal>
  </transf>
  </goal>
  <goal name="wmpz_mul_2exp&#39;vc.15" expl="assertion" proved="true">
  <transf name="split_vc" proved="true" >
   <goal name="wmpz_mul_2exp&#39;vc.15.0" expl="assertion" proved="true">
   <proof prover="3" timelimit="1" memlimit="1000"><result status="valid" time="0.110000" steps="71"/></proof>
   </goal>
   <goal name="wmpz_mul_2exp&#39;vc.15.1" expl="assertion" proved="true">
   <proof prover="3" timelimit="1" memlimit="1000"><result status="valid" time="0.100000" steps="71"/></proof>
   </goal>
   <goal name="wmpz_mul_2exp&#39;vc.15.2" expl="assertion" proved="true">
   <proof prover="0"><result status="valid" time="0.090000" steps="9797"/></proof>
   </goal>
   <goal name="wmpz_mul_2exp&#39;vc.15.3" expl="VC for wmpz_mul_2exp" proved="true">
   <proof prover="0"><result status="valid" time="0.080000" steps="13059"/></proof>
   </goal>
  </transf>
  </goal>
  <goal name="wmpz_mul_2exp&#39;vc.16" expl="assertion" proved="true">
  <proof prover="0"><result status="valid" time="0.120000" steps="12853"/></proof>
  </goal>
  <goal name="wmpz_mul_2exp&#39;vc.17" expl="precondition" proved="true">
  <proof prover="0"><result status="valid" time="0.220000" steps="20931"/></proof>
  </goal>
  <goal name="wmpz_mul_2exp&#39;vc.18" expl="precondition" proved="true">
  <proof prover="0"><result status="valid" time="0.323368" steps="31396"/></proof>
  </goal>
  <goal name="wmpz_mul_2exp&#39;vc.19" expl="precondition" proved="true">
  <proof prover="0"><result status="valid" time="0.301996" steps="31225"/></proof>
  </goal>
  <goal name="wmpz_mul_2exp&#39;vc.20" expl="precondition" proved="true">
  <proof prover="0"><result status="valid" time="0.190000" steps="22225"/></proof>
  </goal>
  <goal name="wmpz_mul_2exp&#39;vc.21" expl="precondition" proved="true">
  <proof prover="0"><result status="valid" time="0.140000" steps="10164"/></proof>
  </goal>
  <goal name="wmpz_mul_2exp&#39;vc.22" expl="precondition" proved="true">
  <proof prover="0"><result status="valid" time="0.140000" steps="21009"/></proof>
  </goal>
  <goal name="wmpz_mul_2exp&#39;vc.23" expl="precondition" proved="true">
  <proof prover="0"><result status="valid" time="0.120000" steps="21643"/></proof>
  </goal>
  <goal name="wmpz_mul_2exp&#39;vc.24" expl="precondition" proved="true">
  <proof prover="2"><result status="valid" time="4.757750"/></proof>
  </goal>
  <goal name="wmpz_mul_2exp&#39;vc.25" expl="assertion" proved="true">
  <proof prover="2"><result status="valid" time="0.020000"/></proof>
  </goal>
  <goal name="wmpz_mul_2exp&#39;vc.26" expl="assertion" proved="true">
  <proof prover="2"><result status="valid" time="0.020000"/></proof>
  </goal>
  <goal name="wmpz_mul_2exp&#39;vc.27" expl="precondition" proved="true">
  <proof prover="0" timelimit="5" memlimit="2000"><result status="valid" time="0.243207" steps="23263"/></proof>
  </goal>
  <goal name="wmpz_mul_2exp&#39;vc.28" expl="precondition" proved="true">
  <proof prover="0" timelimit="5" memlimit="2000"><result status="valid" time="0.031602" steps="10628"/></proof>
  </goal>
  <goal name="wmpz_mul_2exp&#39;vc.29" expl="precondition" proved="true">
  <proof prover="0" timelimit="5" memlimit="2000"><result status="valid" time="0.230000" steps="24590"/></proof>
  </goal>
  <goal name="wmpz_mul_2exp&#39;vc.30" expl="precondition" proved="true">
  <proof prover="0" timelimit="5" memlimit="2000"><result status="valid" time="0.232056" steps="24230"/></proof>
  </goal>
  <goal name="wmpz_mul_2exp&#39;vc.31" expl="assertion" proved="true">
  <proof prover="0" timelimit="5" memlimit="2000"><result status="valid" time="0.040000" steps="10662"/></proof>
  </goal>
  <goal name="wmpz_mul_2exp&#39;vc.32" expl="assertion" proved="true">
  <proof prover="0" timelimit="5" memlimit="2000"><result status="valid" time="0.090000" steps="10663"/></proof>
  </goal>
  <goal name="wmpz_mul_2exp&#39;vc.33" expl="precondition" proved="true">
  <proof prover="0"><result status="valid" time="0.272484" steps="25980"/></proof>
  </goal>
  <goal name="wmpz_mul_2exp&#39;vc.34" expl="precondition" proved="true">
  <proof prover="0"><result status="valid" time="0.090000" steps="10710"/></proof>
  </goal>
  <goal name="wmpz_mul_2exp&#39;vc.35" expl="precondition" proved="true">
  <proof prover="7" timelimit="1" memlimit="1000"><result status="valid" time="0.040000" steps="98628"/></proof>
  </goal>
  <goal name="wmpz_mul_2exp&#39;vc.36" expl="assertion" proved="true">
  <transf name="split_vc" proved="true" >
   <goal name="wmpz_mul_2exp&#39;vc.36.0" expl="assertion" proved="true">
   <proof prover="0" timelimit="5" memlimit="2000"><result status="valid" time="0.140000" steps="14750"/></proof>
   </goal>
   <goal name="wmpz_mul_2exp&#39;vc.36.1" expl="assertion" proved="true">
   <proof prover="7"><result status="valid" time="0.060000" steps="64288"/></proof>
   </goal>
   <goal name="wmpz_mul_2exp&#39;vc.36.2" expl="assertion" proved="true">
   <proof prover="2"><result status="valid" time="0.110000"/></proof>
   </goal>
   <goal name="wmpz_mul_2exp&#39;vc.36.3" expl="assertion" proved="true">
   <proof prover="0" timelimit="5" memlimit="2000"><result status="valid" time="0.100000" steps="10923"/></proof>
   </goal>
   <goal name="wmpz_mul_2exp&#39;vc.36.4" expl="assertion" proved="true">
   <proof prover="1"><result status="valid" time="1.340000"/></proof>
   </goal>
   <goal name="wmpz_mul_2exp&#39;vc.36.5" expl="VC for wmpz_mul_2exp" proved="true">
   <proof prover="0" timelimit="5" memlimit="2000"><result status="valid" time="0.130000" steps="15115"/></proof>
   </goal>
   <goal name="wmpz_mul_2exp&#39;vc.36.6" expl="VC for wmpz_mul_2exp" proved="true">
   <proof prover="2"><result status="valid" time="0.060000"/></proof>
   </goal>
  </transf>
  </goal>
  <goal name="wmpz_mul_2exp&#39;vc.37" expl="precondition" proved="true">
  <proof prover="0"><result status="valid" time="0.253860" steps="27163"/></proof>
  </goal>
  <goal name="wmpz_mul_2exp&#39;vc.38" expl="integer overflow" proved="true">
  <transf name="case" proved="true" arg1="(rlimb &lt;&gt; 0)">
   <goal name="wmpz_mul_2exp&#39;vc.38.0" expl="true case (integer overflow)" proved="true">
   <proof prover="2"><result status="valid" time="0.020000"/></proof>
   </goal>
   <goal name="wmpz_mul_2exp&#39;vc.38.1" expl="false case (integer overflow)" proved="true">
   <proof prover="0"><result status="valid" time="0.277840" steps="27269"/></proof>
   </goal>
  </transf>
  </goal>
  <goal name="wmpz_mul_2exp&#39;vc.39" expl="assertion" proved="true">
  <proof prover="2"><result status="valid" time="0.270000"/></proof>
  </goal>
  <goal name="wmpz_mul_2exp&#39;vc.40" expl="assertion" proved="true">
  <transf name="split_vc" proved="true" >
   <goal name="wmpz_mul_2exp&#39;vc.40.0" expl="assertion" proved="true">
   <proof prover="2"><result status="valid" time="0.080000"/></proof>
   </goal>
   <goal name="wmpz_mul_2exp&#39;vc.40.1" expl="assertion" proved="true">
   <proof prover="1"><result status="valid" time="4.020000"/></proof>
   </goal>
   <goal name="wmpz_mul_2exp&#39;vc.40.2" expl="assertion" proved="true">
   <proof prover="7" timelimit="1" memlimit="1000"><result status="valid" time="0.870000" steps="1104838"/></proof>
   </goal>
   <goal name="wmpz_mul_2exp&#39;vc.40.3" expl="VC for wmpz_mul_2exp" proved="true">
   <proof prover="0"><result status="valid" time="0.090000" steps="11215"/></proof>
   </goal>
   <goal name="wmpz_mul_2exp&#39;vc.40.4" expl="VC for wmpz_mul_2exp" proved="true">
   <transf name="apply" proved="true" arg1="prod_compat_r">
    <goal name="wmpz_mul_2exp&#39;vc.40.4.0" expl="apply premises" proved="true">
    <proof prover="0"><result status="valid" time="0.240000" steps="28161"/></proof>
    </goal>
    <goal name="wmpz_mul_2exp&#39;vc.40.4.1" expl="apply premises" proved="true">
    <proof prover="0"><result status="valid" time="0.305676" steps="29114"/></proof>
    </goal>
   </transf>
   </goal>
   <goal name="wmpz_mul_2exp&#39;vc.40.5" expl="VC for wmpz_mul_2exp" proved="true">
   <proof prover="1"><result status="valid" time="0.130000"/></proof>
   <proof prover="2"><result status="valid" time="0.250000"/></proof>
   </goal>
   <goal name="wmpz_mul_2exp&#39;vc.40.6" expl="VC for wmpz_mul_2exp" proved="true">
   <proof prover="0"><result status="valid" time="0.140000" steps="15449"/></proof>
   </goal>
   <goal name="wmpz_mul_2exp&#39;vc.40.7" expl="VC for wmpz_mul_2exp" proved="true">
   <proof prover="0"><result status="valid" time="0.100000" steps="11258"/></proof>
   <proof prover="2"><result status="valid" time="1.516163"/></proof>
   </goal>
   <goal name="wmpz_mul_2exp&#39;vc.40.8" expl="VC for wmpz_mul_2exp" proved="true">
   <proof prover="0"><result status="valid" time="0.140000" steps="15366"/></proof>
   </goal>
   <goal name="wmpz_mul_2exp&#39;vc.40.9" expl="VC for wmpz_mul_2exp" proved="true">
   <proof prover="0"><result status="valid" time="0.090000" steps="10746"/></proof>
   </goal>
   <goal name="wmpz_mul_2exp&#39;vc.40.10" expl="VC for wmpz_mul_2exp" proved="true">
   <proof prover="1"><result status="valid" time="0.910000"/></proof>
   </goal>
   <goal name="wmpz_mul_2exp&#39;vc.40.11" expl="VC for wmpz_mul_2exp" proved="true">
   <proof prover="2"><result status="valid" time="0.200000"/></proof>
   </goal>
   <goal name="wmpz_mul_2exp&#39;vc.40.12" expl="VC for wmpz_mul_2exp" proved="true">
   <transf name="rewrite" proved="true" arg1="&lt;-" arg2="Power_sum">
    <goal name="wmpz_mul_2exp&#39;vc.40.12.0" expl="VC for wmpz_mul_2exp" proved="true">
    <proof prover="2"><result status="valid" time="0.027320"/></proof>
    </goal>
    <goal name="wmpz_mul_2exp&#39;vc.40.12.1" expl="rewrite premises" proved="true">
    <proof prover="0"><result status="valid" time="0.240000" steps="27972"/></proof>
    </goal>
    <goal name="wmpz_mul_2exp&#39;vc.40.12.2" expl="rewrite premises" proved="true">
    <proof prover="0"><result status="valid" time="0.274541" steps="27976"/></proof>
    </goal>
   </transf>
   </goal>
   <goal name="wmpz_mul_2exp&#39;vc.40.13" expl="VC for wmpz_mul_2exp" proved="true">
   <proof prover="1"><result status="valid" time="1.890000"/></proof>
   </goal>
   <goal name="wmpz_mul_2exp&#39;vc.40.14" expl="VC for wmpz_mul_2exp" proved="true">
   <proof prover="0"><result status="valid" time="0.080000" steps="10859"/></proof>
   </goal>
   <goal name="wmpz_mul_2exp&#39;vc.40.15" expl="VC for wmpz_mul_2exp" proved="true">
   <proof prover="0"><result status="valid" time="0.140000" steps="15002"/></proof>
   </goal>
   <goal name="wmpz_mul_2exp&#39;vc.40.16" expl="VC for wmpz_mul_2exp" proved="true">
   <proof prover="0"><result status="valid" time="0.150000" steps="15667"/></proof>
   </goal>
  </transf>
  </goal>
  <goal name="wmpz_mul_2exp&#39;vc.41" expl="precondition" proved="true">
  <transf name="split_vc" proved="true" >
   <goal name="wmpz_mul_2exp&#39;vc.41.0" expl="precondition" proved="true">
   <proof prover="0"><result status="valid" time="0.240000" steps="28141"/></proof>
   </goal>
   <goal name="wmpz_mul_2exp&#39;vc.41.1" expl="precondition" proved="true">
   <proof prover="0" timelimit="5" memlimit="2000"><result status="valid" time="0.282761" steps="28830"/></proof>
   </goal>
  </transf>
  </goal>
  <goal name="wmpz_mul_2exp&#39;vc.42" expl="assertion" proved="true">
  <proof prover="0"><result status="valid" time="0.150000" steps="15648"/></proof>
  </goal>
  <goal name="wmpz_mul_2exp&#39;vc.43" expl="precondition" proved="true">
  <proof prover="0"><result status="valid" time="0.722127" steps="64683"/></proof>
  </goal>
  <goal name="wmpz_mul_2exp&#39;vc.44" expl="precondition" proved="true">
  <proof prover="0"><result status="valid" time="0.090000" steps="11263"/></proof>
  </goal>
  <goal name="wmpz_mul_2exp&#39;vc.45" expl="precondition" proved="true">
  <proof prover="0"><result status="valid" time="0.672782" steps="58651"/></proof>
  </goal>
  <goal name="wmpz_mul_2exp&#39;vc.46" expl="precondition" proved="true">
  <proof prover="0"><result status="valid" time="0.281928" steps="30167"/></proof>
  </goal>
  <goal name="wmpz_mul_2exp&#39;vc.47" expl="assertion" proved="true">
  <proof prover="0" timelimit="5" memlimit="2000"><result status="valid" time="0.050000" steps="11540"/></proof>
  </goal>
  <goal name="wmpz_mul_2exp&#39;vc.48" expl="assertion" proved="true">
  <transf name="split_vc" proved="true" >
   <goal name="wmpz_mul_2exp&#39;vc.48.0" expl="assertion" proved="true">
   <proof prover="1"><result status="valid" time="0.090000"/></proof>
   </goal>
   <goal name="wmpz_mul_2exp&#39;vc.48.1" expl="assertion" proved="true">
   <proof prover="0" timelimit="5" memlimit="2000"><result status="valid" time="0.100000" steps="11104"/></proof>
   </goal>
  </transf>
  </goal>
  <goal name="wmpz_mul_2exp&#39;vc.49" expl="assertion" proved="true">
  <proof prover="0"><result status="valid" time="0.140000" steps="15286"/></proof>
  </goal>
  <goal name="wmpz_mul_2exp&#39;vc.50" expl="precondition" proved="true">
  <transf name="split_vc" proved="true" >
   <goal name="wmpz_mul_2exp&#39;vc.50.0" expl="precondition" proved="true">
   <proof prover="0"><result status="valid" time="0.150000" steps="15139"/></proof>
   </goal>
   <goal name="wmpz_mul_2exp&#39;vc.50.1" expl="precondition" proved="true">
   <proof prover="0"><result status="valid" time="0.150000" steps="15131"/></proof>
   </goal>
  </transf>
  </goal>
  <goal name="wmpz_mul_2exp&#39;vc.51" expl="integer overflow" proved="true">
  <proof prover="7"><result status="valid" time="0.650000" steps="1079869"/></proof>
  </goal>
  <goal name="wmpz_mul_2exp&#39;vc.52" expl="assertion" proved="true">
  <transf name="split_vc" proved="true" >
   <goal name="wmpz_mul_2exp&#39;vc.52.0" expl="assertion" proved="true">
   <proof prover="2"><result status="valid" time="0.940000"/></proof>
   </goal>
   <goal name="wmpz_mul_2exp&#39;vc.52.1" expl="VC for wmpz_mul_2exp" proved="true">
   <proof prover="1"><result status="valid" time="0.100000"/></proof>
   </goal>
  </transf>
  </goal>
  <goal name="wmpz_mul_2exp&#39;vc.53" expl="assertion" proved="true">
  <transf name="split_vc" proved="true" >
   <goal name="wmpz_mul_2exp&#39;vc.53.0" expl="assertion" proved="true">
   <proof prover="2"><result status="valid" time="1.619296"/></proof>
   </goal>
   <goal name="wmpz_mul_2exp&#39;vc.53.1" expl="assertion" proved="true">
   <proof prover="1"><result status="valid" time="0.120000"/></proof>
   </goal>
   <goal name="wmpz_mul_2exp&#39;vc.53.2" expl="VC for wmpz_mul_2exp" proved="true">
   <proof prover="2"><result status="valid" time="0.090000"/></proof>
   </goal>
   <goal name="wmpz_mul_2exp&#39;vc.53.3" expl="VC for wmpz_mul_2exp" proved="true">
   <proof prover="0" timelimit="5" memlimit="2000"><result status="valid" time="0.319503" steps="32389"/></proof>
   </goal>
   <goal name="wmpz_mul_2exp&#39;vc.53.4" expl="VC for wmpz_mul_2exp" proved="true">
   <proof prover="2"><result status="valid" time="0.300000"/></proof>
   </goal>
   <goal name="wmpz_mul_2exp&#39;vc.53.5" expl="VC for wmpz_mul_2exp" proved="true">
   <proof prover="0" timelimit="5" memlimit="2000"><result status="valid" time="0.315053" steps="32675"/></proof>
   </goal>
   <goal name="wmpz_mul_2exp&#39;vc.53.6" expl="VC for wmpz_mul_2exp" proved="true">
   <proof prover="2"><result status="valid" time="0.570000"/></proof>
   </goal>
  </transf>
  </goal>
  <goal name="wmpz_mul_2exp&#39;vc.54" expl="precondition" proved="true">
  <proof prover="0"><result status="valid" time="0.090000" steps="15505"/></proof>
  </goal>
  <goal name="wmpz_mul_2exp&#39;vc.55" expl="integer overflow" proved="true">
  <proof prover="0"><result status="valid" time="0.230000" steps="32001"/></proof>
  </goal>
  <goal name="wmpz_mul_2exp&#39;vc.56" expl="precondition" proved="true">
  <proof prover="0"><result status="valid" time="0.100000" steps="15895"/></proof>
  </goal>
  <goal name="wmpz_mul_2exp&#39;vc.57" expl="precondition" proved="true">
  <proof prover="0"><result status="valid" time="0.100000" steps="11492"/></proof>
  </goal>
  <goal name="wmpz_mul_2exp&#39;vc.58" expl="precondition" proved="true">
  <proof prover="0"><result status="valid" time="0.120000" steps="12585"/></proof>
  </goal>
  <goal name="wmpz_mul_2exp&#39;vc.59" expl="precondition" proved="true">
  <proof prover="0"><result status="valid" time="0.080000" steps="12591"/></proof>
  </goal>
  <goal name="wmpz_mul_2exp&#39;vc.60" expl="precondition" proved="true">
  <proof prover="2"><result status="valid" time="0.020000"/></proof>
  </goal>
  <goal name="wmpz_mul_2exp&#39;vc.61" expl="precondition" proved="true">
  <proof prover="0"><result status="valid" time="0.885026" steps="76984"/></proof>
  </goal>
  <goal name="wmpz_mul_2exp&#39;vc.62" expl="precondition" proved="true">
  <proof prover="0"><result status="valid" time="0.110000" steps="15879"/></proof>
  </goal>
  <goal name="wmpz_mul_2exp&#39;vc.63" expl="precondition" proved="true">
  <proof prover="0"><result status="valid" time="0.215619" steps="20621"/></proof>
  </goal>
  <goal name="wmpz_mul_2exp&#39;vc.64" expl="precondition" proved="true">
  <proof prover="0"><result status="valid" time="0.120000" steps="16375"/></proof>
  </goal>
  <goal name="wmpz_mul_2exp&#39;vc.65" expl="precondition" proved="true">
  <proof prover="0"><result status="valid" time="0.060000" steps="16108"/></proof>
  </goal>
  <goal name="wmpz_mul_2exp&#39;vc.66" expl="precondition" proved="true">
  <transf name="split_vc" proved="true" >
   <goal name="wmpz_mul_2exp&#39;vc.66.0" expl="precondition" proved="true">
   <proof prover="0" timelimit="5" memlimit="2000"><result status="valid" time="0.070000" steps="12745"/></proof>
   </goal>
   <goal name="wmpz_mul_2exp&#39;vc.66.1" expl="precondition" proved="true">
   <proof prover="1"><result status="valid" time="0.130000"/></proof>
   </goal>
  </transf>
  </goal>
  <goal name="wmpz_mul_2exp&#39;vc.67" expl="precondition" proved="true">
  <proof prover="1"><result status="valid" time="0.080000"/></proof>
  </goal>
  <goal name="wmpz_mul_2exp&#39;vc.68" expl="precondition" proved="true">
  <proof prover="0" timelimit="5" memlimit="2000"><result status="valid" time="0.150000" steps="16072"/></proof>
  </goal>
  <goal name="wmpz_mul_2exp&#39;vc.69" expl="assertion" proved="true">
  <proof prover="1"><result status="valid" time="1.220000"/></proof>
  </goal>
  <goal name="wmpz_mul_2exp&#39;vc.70" expl="postcondition" proved="true">
  <proof prover="0" timelimit="5" memlimit="2000"><result status="valid" time="0.080000" steps="16632"/></proof>
  </goal>
  <goal name="wmpz_mul_2exp&#39;vc.71" expl="postcondition" proved="true">
  <transf name="apply" proved="true" arg1="unchanged_transitive" arg2="with" arg3="mpz1">
   <goal name="wmpz_mul_2exp&#39;vc.71.0" expl="apply premises" proved="true">
   <proof prover="0"><result status="valid" time="0.443478" steps="41475"/></proof>
   </goal>
   <goal name="wmpz_mul_2exp&#39;vc.71.1" expl="apply premises" proved="true">
   <transf name="apply" proved="true" arg1="unchanged_transitive" arg2="with" arg3="mpz2">
    <goal name="wmpz_mul_2exp&#39;vc.71.1.0" expl="apply premises" proved="true">
    <proof prover="0"><result status="valid" time="0.160000" steps="17312"/></proof>
    <proof prover="7" timelimit="1" memlimit="1000"><result status="valid" time="0.050000" steps="81282"/></proof>
    </goal>
    <goal name="wmpz_mul_2exp&#39;vc.71.1.1" expl="apply premises" proved="true">
    <proof prover="0"><result status="valid" time="0.140000" steps="17312"/></proof>
    <proof prover="7" timelimit="1" memlimit="1000"><result status="valid" time="0.060000" steps="81280"/></proof>
    </goal>
   </transf>
   </goal>
  </transf>
  </goal>
  <goal name="wmpz_mul_2exp&#39;vc.72" expl="postcondition" proved="true">
  <proof prover="0"><result status="valid" time="0.080000" steps="16055"/></proof>
  </goal>
  <goal name="wmpz_mul_2exp&#39;vc.73" expl="assertion" proved="true">
  <proof prover="0"><result status="valid" time="0.210000" steps="20334"/></proof>
  </goal>
  <goal name="wmpz_mul_2exp&#39;vc.74" expl="assertion" proved="true">
  <proof prover="0"><result status="valid" time="0.050000" steps="9466"/></proof>
  </goal>
  <goal name="wmpz_mul_2exp&#39;vc.75" expl="precondition" proved="true">
  <proof prover="0"><result status="valid" time="0.260000" steps="20675"/></proof>
  </goal>
  <goal name="wmpz_mul_2exp&#39;vc.76" expl="precondition" proved="true">
  <proof prover="0"><result status="valid" time="0.270000" steps="34611"/></proof>
  </goal>
  <goal name="wmpz_mul_2exp&#39;vc.77" expl="precondition" proved="true">
  <proof prover="5"><result status="valid" time="0.170000" steps="464"/></proof>
  </goal>
  <goal name="wmpz_mul_2exp&#39;vc.78" expl="precondition" proved="true">
  <proof prover="3"><result status="valid" time="0.140000" steps="102"/></proof>
  </goal>
  <goal name="wmpz_mul_2exp&#39;vc.79" expl="precondition" proved="true">
  <proof prover="0"><result status="valid" time="0.180000" steps="21452"/></proof>
  </goal>
  <goal name="wmpz_mul_2exp&#39;vc.80" expl="precondition" proved="true">
  <proof prover="3"><result status="valid" time="0.070000" steps="129"/></proof>
  </goal>
  <goal name="wmpz_mul_2exp&#39;vc.81" expl="assertion" proved="true">
  <proof prover="5"><result status="valid" time="0.120000" steps="131"/></proof>
  </goal>
  <goal name="wmpz_mul_2exp&#39;vc.82" expl="precondition" proved="true">
  <proof prover="0"><result status="valid" time="0.200000" steps="23117"/></proof>
  </goal>
  <goal name="wmpz_mul_2exp&#39;vc.83" expl="assertion" proved="true">
  <proof prover="5"><result status="valid" time="0.090000" steps="131"/></proof>
  </goal>
  <goal name="wmpz_mul_2exp&#39;vc.84" expl="assertion" proved="true">
  <transf name="split_vc" proved="true" >
   <goal name="wmpz_mul_2exp&#39;vc.84.0" expl="assertion" proved="true">
   <proof prover="0" timelimit="5" memlimit="2000"><result status="valid" time="0.745553" steps="63184"/></proof>
   </goal>
   <goal name="wmpz_mul_2exp&#39;vc.84.1" expl="VC for wmpz_mul_2exp" proved="true">
   <proof prover="3"><result status="valid" time="0.080000" steps="134"/></proof>
   </goal>
   <goal name="wmpz_mul_2exp&#39;vc.84.2" expl="VC for wmpz_mul_2exp" proved="true">
   <proof prover="3"><result status="valid" time="2.240000" steps="623"/></proof>
   </goal>
   <goal name="wmpz_mul_2exp&#39;vc.84.3" expl="VC for wmpz_mul_2exp" proved="true">
   <proof prover="3"><result status="valid" time="2.810000" steps="556"/></proof>
   </goal>
  </transf>
  </goal>
  <goal name="wmpz_mul_2exp&#39;vc.85" expl="precondition" proved="true">
  <proof prover="0" timelimit="5" memlimit="2000"><result status="valid" time="0.503944" steps="49054"/></proof>
  </goal>
  <goal name="wmpz_mul_2exp&#39;vc.86" expl="precondition" proved="true">
  <proof prover="0"><result status="valid" time="0.080000" steps="10641"/></proof>
  </goal>
  <goal name="wmpz_mul_2exp&#39;vc.87" expl="precondition" proved="true">
  <transf name="split_vc" proved="true" >
   <goal name="wmpz_mul_2exp&#39;vc.87.0" expl="precondition" proved="true">
   <proof prover="3"><result status="valid" time="2.380000" steps="528"/></proof>
   </goal>
  </transf>
  </goal>
  <goal name="wmpz_mul_2exp&#39;vc.88" expl="precondition" proved="true">
  <transf name="split_vc" proved="true" >
   <goal name="wmpz_mul_2exp&#39;vc.88.0" expl="precondition" proved="true">
   <proof prover="0" timelimit="5" memlimit="2000"><result status="valid" time="0.250245" steps="26041"/></proof>
   </goal>
   <goal name="wmpz_mul_2exp&#39;vc.88.1" expl="precondition" proved="true">
   <proof prover="0" timelimit="5" memlimit="2000"><result status="valid" time="0.256272" steps="25126"/></proof>
   </goal>
  </transf>
  </goal>
  <goal name="wmpz_mul_2exp&#39;vc.89" expl="assertion" proved="true">
  <proof prover="0"><result status="valid" time="0.100000" steps="10916"/></proof>
  </goal>
  <goal name="wmpz_mul_2exp&#39;vc.90" expl="assertion" proved="true">
  <proof prover="5"><result status="valid" time="0.080000" steps="152"/></proof>
  <transf name="split_vc" proved="true" >
   <goal name="wmpz_mul_2exp&#39;vc.90.0" expl="assertion" proved="true">
   <proof prover="5"><result status="valid" time="0.090000" steps="152"/></proof>
   </goal>
   <goal name="wmpz_mul_2exp&#39;vc.90.1" expl="assertion" proved="true">
   <proof prover="0" timelimit="5" memlimit="2000"><result status="valid" time="0.080000" steps="10481"/></proof>
   </goal>
  </transf>
  </goal>
  <goal name="wmpz_mul_2exp&#39;vc.91" expl="assertion" proved="true">
  <transf name="split_vc" proved="true" >
   <goal name="wmpz_mul_2exp&#39;vc.91.0" expl="assertion" proved="true">
   <proof prover="3"><result status="valid" time="0.130000" steps="153"/></proof>
   </goal>
   <goal name="wmpz_mul_2exp&#39;vc.91.1" expl="assertion" proved="true">
   <proof prover="3"><result status="valid" time="0.140000" steps="153"/></proof>
   </goal>
  </transf>
  </goal>
  <goal name="wmpz_mul_2exp&#39;vc.92" expl="precondition" proved="true">
  <proof prover="0" timelimit="5" memlimit="2000"><result status="valid" time="0.080000" steps="14316"/></proof>
  </goal>
  <goal name="wmpz_mul_2exp&#39;vc.93" expl="integer overflow" proved="true">
  <proof prover="0"><result status="valid" time="0.249452" steps="26009"/></proof>
  </goal>
  <goal name="wmpz_mul_2exp&#39;vc.94" expl="assertion" proved="true">
  <transf name="split_vc" proved="true" >
   <goal name="wmpz_mul_2exp&#39;vc.94.0" expl="assertion" proved="true">
   <proof prover="5"><result status="valid" time="1.440000" steps="869"/></proof>
   </goal>
   <goal name="wmpz_mul_2exp&#39;vc.94.1" expl="VC for wmpz_mul_2exp" proved="true">
   <proof prover="0" timelimit="5" memlimit="2000"><result status="valid" time="0.080000" steps="16961"/></proof>
   </goal>
  </transf>
  </goal>
  <goal name="wmpz_mul_2exp&#39;vc.95" expl="assertion" proved="true">
  <transf name="split_vc" proved="true" >
   <goal name="wmpz_mul_2exp&#39;vc.95.0" expl="assertion" proved="true">
   <proof prover="5"><result status="valid" time="0.320000" steps="168"/></proof>
   </goal>
   <goal name="wmpz_mul_2exp&#39;vc.95.1" expl="assertion" proved="true">
   <proof prover="5"><result status="valid" time="0.380000" steps="168"/></proof>
   </goal>
   <goal name="wmpz_mul_2exp&#39;vc.95.2" expl="VC for wmpz_mul_2exp" proved="true">
   <proof prover="2"><result status="valid" time="0.100000"/></proof>
   </goal>
   <goal name="wmpz_mul_2exp&#39;vc.95.3" expl="VC for wmpz_mul_2exp" proved="true">
   <proof prover="7"><result status="valid" time="0.080000" steps="88582"/></proof>
   </goal>
   <goal name="wmpz_mul_2exp&#39;vc.95.4" expl="VC for wmpz_mul_2exp" proved="true">
   <proof prover="2"><result status="valid" time="0.340000"/></proof>
   </goal>
   <goal name="wmpz_mul_2exp&#39;vc.95.5" expl="VC for wmpz_mul_2exp" proved="true">
   <proof prover="2"><result status="valid" time="1.571435"/></proof>
   </goal>
   <goal name="wmpz_mul_2exp&#39;vc.95.6" expl="VC for wmpz_mul_2exp" proved="true">
   <proof prover="5"><result status="valid" time="1.810000" steps="397"/></proof>
   </goal>
  </transf>
  </goal>
  <goal name="wmpz_mul_2exp&#39;vc.96" expl="precondition" proved="true">
  <proof prover="0"><result status="valid" time="0.060000" steps="14588"/></proof>
  </goal>
  <goal name="wmpz_mul_2exp&#39;vc.97" expl="integer overflow" proved="true">
  <proof prover="0"><result status="valid" time="0.251542" steps="27482"/></proof>
  </goal>
  <goal name="wmpz_mul_2exp&#39;vc.98" expl="precondition" proved="true">
  <proof prover="0"><result status="valid" time="0.130000" steps="14975"/></proof>
  </goal>
  <goal name="wmpz_mul_2exp&#39;vc.99" expl="precondition" proved="true">
  <proof prover="0"><result status="valid" time="0.110000" steps="10868"/></proof>
  </goal>
  <goal name="wmpz_mul_2exp&#39;vc.100" expl="precondition" proved="true">
  <proof prover="0" timelimit="5" memlimit="2000"><result status="valid" time="0.110000" steps="11820"/></proof>
  </goal>
  <goal name="wmpz_mul_2exp&#39;vc.101" expl="precondition" proved="true">
  <proof prover="0" timelimit="5" memlimit="2000"><result status="valid" time="0.140000" steps="11826"/></proof>
  </goal>
  <goal name="wmpz_mul_2exp&#39;vc.102" expl="precondition" proved="true">
  <proof prover="0" timelimit="5" memlimit="2000"><result status="valid" time="0.120000" steps="16382"/></proof>
  </goal>
  <goal name="wmpz_mul_2exp&#39;vc.103" expl="precondition" proved="true">
  <proof prover="0" timelimit="5" memlimit="2000"><result status="valid" time="0.627363" steps="53267"/></proof>
  </goal>
  <goal name="wmpz_mul_2exp&#39;vc.104" expl="precondition" proved="true">
  <proof prover="0" timelimit="5" memlimit="2000"><result status="valid" time="0.160000" steps="14976"/></proof>
  </goal>
  <goal name="wmpz_mul_2exp&#39;vc.105" expl="precondition" proved="true">
  <proof prover="0" timelimit="5" memlimit="2000"><result status="valid" time="0.212418" steps="19578"/></proof>
  </goal>
  <goal name="wmpz_mul_2exp&#39;vc.106" expl="precondition" proved="true">
  <transf name="split_vc" proved="true" >
   <goal name="wmpz_mul_2exp&#39;vc.106.0" expl="precondition" proved="true">
   <proof prover="1"><result status="valid" time="0.120000"/></proof>
   </goal>
   <goal name="wmpz_mul_2exp&#39;vc.106.1" expl="precondition" proved="true">
   <proof prover="0" timelimit="5" memlimit="2000"><result status="valid" time="0.070000" steps="15382"/></proof>
   </goal>
  </transf>
  </goal>
  <goal name="wmpz_mul_2exp&#39;vc.107" expl="precondition" proved="true">
  <proof prover="3"><result status="valid" time="0.200000" steps="173"/></proof>
  </goal>
  <goal name="wmpz_mul_2exp&#39;vc.108" expl="precondition" proved="true">
  <proof prover="0" timelimit="5" memlimit="2000"><result status="valid" time="0.110000" steps="12036"/></proof>
  </goal>
  <goal name="wmpz_mul_2exp&#39;vc.109" expl="precondition" proved="true">
  <proof prover="0" timelimit="5" memlimit="2000"><result status="valid" time="0.090000" steps="16744"/></proof>
  </goal>
  <goal name="wmpz_mul_2exp&#39;vc.110" expl="precondition" proved="true">
  <proof prover="0"><result status="valid" time="0.070000" steps="15160"/></proof>
  </goal>
  <goal name="wmpz_mul_2exp&#39;vc.111" expl="assertion" proved="true">
  <proof prover="1"><result status="valid" time="0.360000"/></proof>
  </goal>
  <goal name="wmpz_mul_2exp&#39;vc.112" expl="postcondition" proved="true">
  <proof prover="0"><result status="valid" time="0.150000" steps="15715"/></proof>
  </goal>
  <goal name="wmpz_mul_2exp&#39;vc.113" expl="postcondition" proved="true">
  <transf name="apply" proved="true" arg1="unchanged_transitive" arg2="with" arg3="mpz1">
   <goal name="wmpz_mul_2exp&#39;vc.113.0" expl="apply premises" proved="true">
   <proof prover="0"><result status="valid" time="0.350012" steps="32880"/></proof>
   </goal>
   <goal name="wmpz_mul_2exp&#39;vc.113.1" expl="apply premises" proved="true">
   <transf name="apply" proved="true" arg1="unchanged_transitive" arg2="with" arg3="mpz2">
    <goal name="wmpz_mul_2exp&#39;vc.113.1.0" expl="apply premises" proved="true">
    <proof prover="0"><result status="valid" time="0.140000" steps="16322"/></proof>
    <proof prover="3" timelimit="1" memlimit="1000"><result status="valid" time="0.530000" steps="202"/></proof>
    <proof prover="7" timelimit="1" memlimit="1000"><result status="valid" time="0.060000" steps="70581"/></proof>
    </goal>
    <goal name="wmpz_mul_2exp&#39;vc.113.1.1" expl="apply premises" proved="true">
    <proof prover="0"><result status="valid" time="0.140000" steps="16322"/></proof>
    <proof prover="3" timelimit="1" memlimit="1000"><result status="valid" time="0.570000" steps="202"/></proof>
    <proof prover="7" timelimit="1" memlimit="1000"><result status="valid" time="0.050000" steps="70579"/></proof>
    </goal>
   </transf>
   </goal>
  </transf>
  </goal>
  <goal name="wmpz_mul_2exp&#39;vc.114" expl="postcondition" proved="true">
  <proof prover="0"><result status="valid" time="0.130000" steps="15138"/></proof>
  </goal>
  <goal name="wmpz_mul_2exp&#39;vc.115" expl="precondition" proved="true">
  <proof prover="0"><result status="valid" time="0.130000" steps="13560"/></proof>
  </goal>
  <goal name="wmpz_mul_2exp&#39;vc.116" expl="precondition" proved="true">
  <proof prover="0" timelimit="5" memlimit="2000"><result status="valid" time="0.100000" steps="9569"/></proof>
  </goal>
  <goal name="wmpz_mul_2exp&#39;vc.117" expl="precondition" proved="true">
  <proof prover="0"><result status="valid" time="0.230000" steps="24178"/></proof>
  </goal>
  <goal name="wmpz_mul_2exp&#39;vc.118" expl="precondition" proved="true">
  <proof prover="0"><result status="valid" time="0.390035" steps="37752"/></proof>
  </goal>
  <goal name="wmpz_mul_2exp&#39;vc.119" expl="precondition" proved="true">
  <proof prover="1"><result status="valid" time="0.280000"/></proof>
  </goal>
  <goal name="wmpz_mul_2exp&#39;vc.120" expl="precondition" proved="true">
  <proof prover="5"><result status="valid" time="0.140000" steps="140"/></proof>
  </goal>
  <goal name="wmpz_mul_2exp&#39;vc.121" expl="precondition" proved="true">
  <proof prover="0" timelimit="5" memlimit="2000"><result status="valid" time="0.080000" steps="10598"/></proof>
  </goal>
  <goal name="wmpz_mul_2exp&#39;vc.122" expl="precondition" proved="true">
  <proof prover="0"><result status="valid" time="0.220000" steps="23595"/></proof>
  </goal>
  <goal name="wmpz_mul_2exp&#39;vc.123" expl="precondition" proved="true">
  <proof prover="0" timelimit="5" memlimit="2000"><result status="valid" time="0.240000" steps="25209"/></proof>
  </goal>
  <goal name="wmpz_mul_2exp&#39;vc.124" expl="assertion" proved="true">
  <proof prover="2"><result status="valid" time="0.030000"/></proof>
  </goal>
  <goal name="wmpz_mul_2exp&#39;vc.125" expl="assertion" proved="true">
  <proof prover="5"><result status="valid" time="0.180000" steps="161"/></proof>
  </goal>
  <goal name="wmpz_mul_2exp&#39;vc.126" expl="precondition" proved="true">
  <proof prover="0" timelimit="5" memlimit="2000"><result status="valid" time="0.240000" steps="26283"/></proof>
  </goal>
  <goal name="wmpz_mul_2exp&#39;vc.127" expl="precondition" proved="true">
  <proof prover="0" timelimit="5" memlimit="2000"><result status="valid" time="0.100000" steps="10931"/></proof>
  </goal>
  <goal name="wmpz_mul_2exp&#39;vc.128" expl="precondition" proved="true">
  <proof prover="0"><result status="valid" time="0.230000" steps="27030"/></proof>
  </goal>
  <goal name="wmpz_mul_2exp&#39;vc.129" expl="precondition" proved="true">
  <proof prover="0"><result status="valid" time="0.258444" steps="27265"/></proof>
  </goal>
  <goal name="wmpz_mul_2exp&#39;vc.130" expl="assertion" proved="true">
  <transf name="split_vc" proved="true" >
  </transf>
  </goal>
  <goal name="wmpz_mul_2exp&#39;vc.131" expl="assertion" proved="true">
  <transf name="split_vc" proved="true" >
  </transf>
  </goal>
  <goal name="wmpz_mul_2exp&#39;vc.132" expl="precondition" proved="true">
  <proof prover="0"><result status="valid" time="0.302271" steps="28902"/></proof>
  </goal>
  <goal name="wmpz_mul_2exp&#39;vc.133" expl="precondition" proved="true">
  <proof prover="5"><result status="valid" time="0.190000" steps="170"/></proof>
  </goal>
  <goal name="wmpz_mul_2exp&#39;vc.134" expl="precondition" proved="true">
  <proof prover="7"><result status="valid" time="0.040000" steps="96386"/></proof>
  </goal>
  <goal name="wmpz_mul_2exp&#39;vc.135" expl="assertion" proved="true">
  <transf name="split_vc" proved="true" >
   <goal name="wmpz_mul_2exp&#39;vc.135.0" expl="assertion" proved="true">
   <proof prover="1"><result status="valid" time="0.160000"/></proof>
   </goal>
   <goal name="wmpz_mul_2exp&#39;vc.135.1" expl="assertion" proved="true">
   <proof prover="7"><result status="valid" time="0.070000" steps="66162"/></proof>
   </goal>
   <goal name="wmpz_mul_2exp&#39;vc.135.2" expl="assertion" proved="true">
   <proof prover="2"><result status="valid" time="0.130000"/></proof>
   </goal>
   <goal name="wmpz_mul_2exp&#39;vc.135.3" expl="assertion" proved="true">
   <proof prover="0" timelimit="5" memlimit="2000"><result status="valid" time="0.110000" steps="11267"/></proof>
   </goal>
   <goal name="wmpz_mul_2exp&#39;vc.135.4" expl="assertion" proved="true">
   <proof prover="1"><result status="valid" time="1.130000"/></proof>
   </goal>
   <goal name="wmpz_mul_2exp&#39;vc.135.5" expl="VC for wmpz_mul_2exp" proved="true">
   <proof prover="0" timelimit="5" memlimit="2000"><result status="valid" time="0.150000" steps="15390"/></proof>
   </goal>
   <goal name="wmpz_mul_2exp&#39;vc.135.6" expl="VC for wmpz_mul_2exp" proved="true">
   <proof prover="5"><result status="valid" time="0.530000" steps="191"/></proof>
   </goal>
  </transf>
  </goal>
  <goal name="wmpz_mul_2exp&#39;vc.136" expl="precondition" proved="true">
  <proof prover="0" timelimit="5" memlimit="2000"><result status="valid" time="0.296269" steps="30018"/></proof>
  </goal>
  <goal name="wmpz_mul_2exp&#39;vc.137" expl="integer overflow" proved="true">
  <transf name="split_vc" proved="true" >
   <goal name="wmpz_mul_2exp&#39;vc.137.0" expl="integer overflow" proved="true">
   <proof prover="0" timelimit="5" memlimit="2000"><result status="valid" time="0.307507" steps="31061"/></proof>
   </goal>
   <goal name="wmpz_mul_2exp&#39;vc.137.1" expl="integer overflow" proved="true">
   <proof prover="0" timelimit="5" memlimit="2000"><result status="valid" time="0.150000" steps="15813"/></proof>
   </goal>
  </transf>
  </goal>
  <goal name="wmpz_mul_2exp&#39;vc.138" expl="assertion" proved="true">
  <proof prover="5"><result status="valid" time="1.430000" steps="194"/></proof>
  </goal>
  <goal name="wmpz_mul_2exp&#39;vc.139" expl="assertion" proved="true">
  <transf name="split_vc" proved="true" >
   <goal name="wmpz_mul_2exp&#39;vc.139.0" expl="assertion" proved="true">
   <proof prover="1"><result status="valid" time="0.220000"/></proof>
   </goal>
   <goal name="wmpz_mul_2exp&#39;vc.139.1" expl="assertion" proved="true">
   <proof prover="0" timelimit="5" memlimit="2000"><result status="valid" time="1.414038" steps="104054"/></proof>
   </goal>
   <goal name="wmpz_mul_2exp&#39;vc.139.2" expl="VC for wmpz_mul_2exp" proved="true">
   <proof prover="1"><result status="valid" time="0.220000"/></proof>
   </goal>
   <goal name="wmpz_mul_2exp&#39;vc.139.3" expl="VC for wmpz_mul_2exp" proved="true">
   <proof prover="0"><result status="valid" time="0.100000" steps="11784"/></proof>
   </goal>
   <goal name="wmpz_mul_2exp&#39;vc.139.4" expl="VC for wmpz_mul_2exp" proved="true">
   <proof prover="0" timelimit="5" memlimit="2000"><result status="valid" time="0.120000" steps="11565"/></proof>
   </goal>
   <goal name="wmpz_mul_2exp&#39;vc.139.5" expl="VC for wmpz_mul_2exp" proved="true">
   <transf name="apply" proved="true" arg1="prod_compat_r">
    <goal name="wmpz_mul_2exp&#39;vc.139.5.0" expl="apply premises" proved="true">
    <proof prover="0"><result status="valid" time="0.250000" steps="31440"/></proof>
    </goal>
    <goal name="wmpz_mul_2exp&#39;vc.139.5.1" expl="apply premises" proved="true">
    <proof prover="0"><result status="valid" time="0.224844" steps="32559"/></proof>
    </goal>
   </transf>
   </goal>
   <goal name="wmpz_mul_2exp&#39;vc.139.6" expl="VC for wmpz_mul_2exp" proved="true">
   <proof prover="2"><result status="valid" time="0.260000"/></proof>
   </goal>
   <goal name="wmpz_mul_2exp&#39;vc.139.7" expl="VC for wmpz_mul_2exp" proved="true">
   <proof prover="0" timelimit="5" memlimit="2000"><result status="valid" time="0.160000" steps="15776"/></proof>
   </goal>
   <goal name="wmpz_mul_2exp&#39;vc.139.8" expl="VC for wmpz_mul_2exp" proved="true">
   <proof prover="0" timelimit="5" memlimit="2000"><result status="valid" time="0.110000" steps="11608"/></proof>
   </goal>
   <goal name="wmpz_mul_2exp&#39;vc.139.9" expl="VC for wmpz_mul_2exp" proved="true">
   <proof prover="0" timelimit="5" memlimit="2000"><result status="valid" time="0.180000" steps="15689"/></proof>
   </goal>
   <goal name="wmpz_mul_2exp&#39;vc.139.10" expl="VC for wmpz_mul_2exp" proved="true">
   <proof prover="0" timelimit="5" memlimit="2000"><result status="valid" time="0.100000" steps="11006"/></proof>
   </goal>
   <goal name="wmpz_mul_2exp&#39;vc.139.11" expl="VC for wmpz_mul_2exp" proved="true">
   <proof prover="1"><result status="valid" time="0.270000"/></proof>
   </goal>
   <goal name="wmpz_mul_2exp&#39;vc.139.12" expl="VC for wmpz_mul_2exp" proved="true">
   <proof prover="2"><result status="valid" time="0.200000"/></proof>
   </goal>
   <goal name="wmpz_mul_2exp&#39;vc.139.13" expl="VC for wmpz_mul_2exp" proved="true">
   <transf name="rewrite" proved="true" arg1="&lt;-" arg2="Power_sum">
    <goal name="wmpz_mul_2exp&#39;vc.139.13.0" expl="VC for wmpz_mul_2exp" proved="true">
    <proof prover="2"><result status="valid" time="0.027902"/></proof>
    </goal>
    <goal name="wmpz_mul_2exp&#39;vc.139.13.1" expl="rewrite premises" proved="true">
    <proof prover="0"><result status="valid" time="0.307171" steps="30866"/></proof>
    </goal>
    <goal name="wmpz_mul_2exp&#39;vc.139.13.2" expl="rewrite premises" proved="true">
    <proof prover="0"><result status="valid" time="0.315051" steps="30821"/></proof>
    </goal>
   </transf>
   </goal>
   <goal name="wmpz_mul_2exp&#39;vc.139.14" expl="VC for wmpz_mul_2exp" proved="true">
   <proof prover="1"><result status="valid" time="0.270000"/></proof>
   </goal>
   <goal name="wmpz_mul_2exp&#39;vc.139.15" expl="VC for wmpz_mul_2exp" proved="true">
   <proof prover="0" timelimit="5" memlimit="2000"><result status="valid" time="0.100000" steps="11119"/></proof>
   </goal>
   <goal name="wmpz_mul_2exp&#39;vc.139.16" expl="VC for wmpz_mul_2exp" proved="true">
   <proof prover="0" timelimit="5" memlimit="2000"><result status="valid" time="0.160000" steps="15240"/></proof>
   </goal>
   <goal name="wmpz_mul_2exp&#39;vc.139.17" expl="VC for wmpz_mul_2exp" proved="true">
   <proof prover="0" timelimit="5" memlimit="2000"><result status="valid" time="0.170000" steps="15990"/></proof>
   </goal>
  </transf>
  </goal>
  <goal name="wmpz_mul_2exp&#39;vc.140" expl="precondition" proved="true">
  <proof prover="0"><result status="valid" time="0.320917" steps="31557"/></proof>
  </goal>
  <goal name="wmpz_mul_2exp&#39;vc.141" expl="assertion" proved="true">
  <proof prover="0"><result status="valid" time="0.170000" steps="15896"/></proof>
  </goal>
  <goal name="wmpz_mul_2exp&#39;vc.142" expl="precondition" proved="true">
  <proof prover="0"><result status="valid" time="0.110000" steps="11353"/></proof>
  </goal>
  <goal name="wmpz_mul_2exp&#39;vc.143" expl="precondition" proved="true">
  <proof prover="0" timelimit="5" memlimit="2000"><result status="valid" time="0.110000" steps="11384"/></proof>
  </goal>
  <goal name="wmpz_mul_2exp&#39;vc.144" expl="precondition" proved="true">
  <proof prover="0"><result status="valid" time="0.110000" steps="11815"/></proof>
  </goal>
  <goal name="wmpz_mul_2exp&#39;vc.145" expl="precondition" proved="true">
  <proof prover="0" timelimit="5" memlimit="2000"><result status="valid" time="0.130000" steps="11835"/></proof>
  </goal>
  <goal name="wmpz_mul_2exp&#39;vc.146" expl="precondition" proved="true">
  <proof prover="1"><result status="valid" time="2.273572"/></proof>
  </goal>
  <goal name="wmpz_mul_2exp&#39;vc.147" expl="precondition" proved="true">
  <transf name="split_vc" proved="true" >
   <goal name="wmpz_mul_2exp&#39;vc.147.0" expl="precondition" proved="true">
   <proof prover="0" timelimit="5" memlimit="2000"><result status="valid" time="0.130000" steps="11712"/></proof>
   </goal>
   <goal name="wmpz_mul_2exp&#39;vc.147.1" expl="precondition" proved="true">
   <proof prover="0" timelimit="5" memlimit="2000"><result status="valid" time="0.100000" steps="11711"/></proof>
   </goal>
  </transf>
  </goal>
  <goal name="wmpz_mul_2exp&#39;vc.148" expl="precondition" proved="true">
  <proof prover="0"><result status="valid" time="0.796800" steps="67898"/></proof>
  </goal>
  <goal name="wmpz_mul_2exp&#39;vc.149" expl="precondition" proved="true">
  <transf name="split_vc" proved="true" >
   <goal name="wmpz_mul_2exp&#39;vc.149.0" expl="precondition" proved="true">
   <proof prover="0" timelimit="5" memlimit="2000"><result status="valid" time="0.270000" steps="33124"/></proof>
   </goal>
   <goal name="wmpz_mul_2exp&#39;vc.149.1" expl="precondition" proved="true">
   <proof prover="0" timelimit="5" memlimit="2000"><result status="valid" time="0.338658" steps="34062"/></proof>
   </goal>
  </transf>
  </goal>
  <goal name="wmpz_mul_2exp&#39;vc.150" expl="assertion" proved="true">
  <transf name="split_vc" proved="true" >
   <goal name="wmpz_mul_2exp&#39;vc.150.0" expl="assertion" proved="true">
   <proof prover="7"><result status="valid" time="0.020000" steps="3408"/></proof>
   </goal>
   <goal name="wmpz_mul_2exp&#39;vc.150.1" expl="assertion" proved="true">
   <proof prover="7"><result status="valid" time="0.020000" steps="3410"/></proof>
   </goal>
  </transf>
  </goal>
  <goal name="wmpz_mul_2exp&#39;vc.151" expl="assertion" proved="true">
  <transf name="split_vc" proved="true" >
   <goal name="wmpz_mul_2exp&#39;vc.151.0" expl="assertion" proved="true">
   <proof prover="7"><result status="valid" time="0.030000" steps="17061"/></proof>
   </goal>
   <goal name="wmpz_mul_2exp&#39;vc.151.1" expl="assertion" proved="true">
   <proof prover="0" timelimit="5" memlimit="2000"><result status="valid" time="0.110000" steps="11497"/></proof>
   </goal>
  </transf>
  </goal>
  <goal name="wmpz_mul_2exp&#39;vc.152" expl="assertion" proved="true">
  <proof prover="0"><result status="valid" time="0.080000" steps="15642"/></proof>
  </goal>
  <goal name="wmpz_mul_2exp&#39;vc.153" expl="precondition" proved="true">
  <proof prover="0"><result status="valid" time="0.110000" steps="11962"/></proof>
  </goal>
  <goal name="wmpz_mul_2exp&#39;vc.154" expl="integer overflow" proved="true">
  <proof prover="0"><result status="valid" time="0.346387" steps="34463"/></proof>
  </goal>
  <goal name="wmpz_mul_2exp&#39;vc.155" expl="assertion" proved="true">
  <transf name="split_vc" proved="true" >
   <goal name="wmpz_mul_2exp&#39;vc.155.0" expl="assertion" proved="true">
   <proof prover="2"><result status="valid" time="1.040000"/></proof>
   </goal>
   <goal name="wmpz_mul_2exp&#39;vc.155.1" expl="VC for wmpz_mul_2exp" proved="true">
   <proof prover="0" timelimit="5" memlimit="2000"><result status="valid" time="0.100000" steps="18999"/></proof>
   </goal>
  </transf>
  </goal>
  <goal name="wmpz_mul_2exp&#39;vc.156" expl="assertion" proved="true">
  <transf name="split_vc" proved="true" >
   <goal name="wmpz_mul_2exp&#39;vc.156.0" expl="assertion" proved="true">
   <proof prover="7"><result status="valid" time="1.020000" steps="1569199"/></proof>
   </goal>
   <goal name="wmpz_mul_2exp&#39;vc.156.1" expl="assertion" proved="true">
   <proof prover="7"><result status="valid" time="1.120572" steps="1563264"/></proof>
   </goal>
   <goal name="wmpz_mul_2exp&#39;vc.156.2" expl="VC for wmpz_mul_2exp" proved="true">
   <proof prover="2"><result status="valid" time="0.130000"/></proof>
   </goal>
   <goal name="wmpz_mul_2exp&#39;vc.156.3" expl="VC for wmpz_mul_2exp" proved="true">
   <proof prover="2"><result status="valid" time="0.939133"/></proof>
   </goal>
   <goal name="wmpz_mul_2exp&#39;vc.156.4" expl="VC for wmpz_mul_2exp" proved="true">
   <proof prover="2"><result status="valid" time="0.310000"/></proof>
   </goal>
   <goal name="wmpz_mul_2exp&#39;vc.156.5" expl="VC for wmpz_mul_2exp" proved="true">
   <proof prover="2"><result status="valid" time="1.641351"/></proof>
   </goal>
   <goal name="wmpz_mul_2exp&#39;vc.156.6" expl="VC for wmpz_mul_2exp" proved="true">
   <proof prover="2"><result status="valid" time="0.630000"/></proof>
   </goal>
  </transf>
  </goal>
  <goal name="wmpz_mul_2exp&#39;vc.157" expl="precondition" proved="true">
  <proof prover="0"><result status="valid" time="0.120000" steps="12232"/></proof>
  </goal>
  <goal name="wmpz_mul_2exp&#39;vc.158" expl="integer overflow" proved="true">
  <proof prover="0" timelimit="5" memlimit="2000"><result status="valid" time="0.363604" steps="35982"/></proof>
  </goal>
  <goal name="wmpz_mul_2exp&#39;vc.159" expl="precondition" proved="true">
  <proof prover="0"><result status="valid" time="0.180000" steps="16595"/></proof>
  </goal>
  <goal name="wmpz_mul_2exp&#39;vc.160" expl="precondition" proved="true">
  <proof prover="2"><result status="valid" time="0.170000"/></proof>
  </goal>
  <goal name="wmpz_mul_2exp&#39;vc.161" expl="precondition" proved="true">
  <proof prover="0" timelimit="5" memlimit="2000"><result status="valid" time="0.120000" steps="13105"/></proof>
  </goal>
  <goal name="wmpz_mul_2exp&#39;vc.162" expl="precondition" proved="true">
  <proof prover="0"><result status="valid" time="0.060000" steps="13111"/></proof>
  </goal>
  <goal name="wmpz_mul_2exp&#39;vc.163" expl="precondition" proved="true">
  <proof prover="0" timelimit="5" memlimit="2000"><result status="valid" time="0.180000" steps="17952"/></proof>
  </goal>
  <goal name="wmpz_mul_2exp&#39;vc.164" expl="precondition" proved="true">
  <proof prover="0" timelimit="5" memlimit="2000"><result status="valid" time="1.103483" steps="87195"/></proof>
  </goal>
  <goal name="wmpz_mul_2exp&#39;vc.165" expl="precondition" proved="true">
  <transf name="split_vc" proved="true" >
   <goal name="wmpz_mul_2exp&#39;vc.165.0" expl="precondition" proved="true">
   <proof prover="0" timelimit="5" memlimit="2000"><result status="valid" time="0.080000" steps="16565"/></proof>
   </goal>
   <goal name="wmpz_mul_2exp&#39;vc.165.1" expl="precondition" proved="true">
   <transf name="inline_goal" proved="true" >
    <goal name="wmpz_mul_2exp&#39;vc.165.1.0" expl="precondition" proved="true">
    <proof prover="1"><result status="valid" time="0.170000"/></proof>
    </goal>
   </transf>
   </goal>
  </transf>
  </goal>
  <goal name="wmpz_mul_2exp&#39;vc.166" expl="precondition" proved="true">
  <proof prover="0" timelimit="5" memlimit="2000"><result status="valid" time="0.244358" steps="24478"/></proof>
  </goal>
  <goal name="wmpz_mul_2exp&#39;vc.167" expl="precondition" proved="true">
  <proof prover="0" timelimit="5" memlimit="2000"><result status="valid" time="0.080000" steps="16804"/></proof>
  </goal>
  <goal name="wmpz_mul_2exp&#39;vc.168" expl="precondition" proved="true">
  <proof prover="0"><result status="valid" time="0.270000" steps="35686"/></proof>
  </goal>
  <goal name="wmpz_mul_2exp&#39;vc.169" expl="precondition" proved="true">
  <proof prover="0" timelimit="5" memlimit="2000"><result status="valid" time="0.070000" steps="13289"/></proof>
  </goal>
  <goal name="wmpz_mul_2exp&#39;vc.170" expl="precondition" proved="true">
  <proof prover="0" timelimit="5" memlimit="2000"><result status="valid" time="0.100000" steps="18186"/></proof>
  </goal>
  <goal name="wmpz_mul_2exp&#39;vc.171" expl="precondition" proved="true">
  <proof prover="0" timelimit="5" memlimit="2000"><result status="valid" time="0.110000" steps="16366"/></proof>
  </goal>
  <goal name="wmpz_mul_2exp&#39;vc.172" expl="assertion" proved="true">
  <transf name="split_vc" proved="true" >
   <goal name="wmpz_mul_2exp&#39;vc.172.0" expl="assertion" proved="true">
   <transf name="inline_goal" proved="true" >
    <goal name="wmpz_mul_2exp&#39;vc.172.0.0" expl="assertion" proved="true">
    <proof prover="1"><result status="valid" time="0.250000"/></proof>
    </goal>
   </transf>
   </goal>
   <goal name="wmpz_mul_2exp&#39;vc.172.1" expl="assertion" proved="true">
   <proof prover="0" timelimit="5" memlimit="2000"><result status="valid" time="0.060000" steps="12759"/></proof>
   </goal>
  </transf>
  </goal>
  <goal name="wmpz_mul_2exp&#39;vc.173" expl="postcondition" proved="true">
  <proof prover="0"><result status="valid" time="0.061667" steps="16969"/></proof>
  </goal>
  <goal name="wmpz_mul_2exp&#39;vc.174" expl="postcondition" proved="true">
  <transf name="apply" proved="true" arg1="unchanged_transitive" arg2="with" arg3="mpz1">
   <goal name="wmpz_mul_2exp&#39;vc.174.0" expl="apply premises" proved="true">
   <proof prover="0"><result status="valid" time="0.522671" steps="48588"/></proof>
   </goal>
   <goal name="wmpz_mul_2exp&#39;vc.174.1" expl="apply premises" proved="true">
   <transf name="apply" proved="true" arg1="unchanged_transitive" arg2="with" arg3="mpz2">
    <goal name="wmpz_mul_2exp&#39;vc.174.1.0" expl="apply premises" proved="true">
    <proof prover="0"><result status="valid" time="0.180000" steps="17707"/></proof>
    </goal>
    <goal name="wmpz_mul_2exp&#39;vc.174.1.1" expl="apply premises" proved="true">
    <transf name="apply" proved="true" arg1="unchanged_transitive" arg2="with" arg3="mpz4">
     <goal name="wmpz_mul_2exp&#39;vc.174.1.1.0" expl="apply premises" proved="true">
     <proof prover="0" timelimit="5" memlimit="2000"><result status="valid" time="1.460260" steps="99466"/></proof>
     </goal>
     <goal name="wmpz_mul_2exp&#39;vc.174.1.1.1" expl="apply premises" proved="true">
     <proof prover="0"><result status="valid" time="0.170000" steps="17707"/></proof>
     </goal>
    </transf>
    </goal>
   </transf>
   </goal>
  </transf>
  </goal>
  <goal name="wmpz_mul_2exp&#39;vc.175" expl="postcondition" proved="true">
  <proof prover="0" timelimit="5" memlimit="2000"><result status="valid" time="0.080000" steps="17217"/></proof>
  </goal>
  <goal name="wmpz_mul_2exp&#39;vc.176" expl="assertion" proved="true">
  <proof prover="3"><result status="valid" time="0.090000" steps="118"/></proof>
  </goal>
  <goal name="wmpz_mul_2exp&#39;vc.177" expl="precondition" proved="true">
  <proof prover="5"><result status="valid" time="0.130000" steps="280"/></proof>
  </goal>
  <goal name="wmpz_mul_2exp&#39;vc.178" expl="precondition" proved="true">
  <transf name="split_vc" proved="true" >
   <goal name="wmpz_mul_2exp&#39;vc.178.0" expl="precondition" proved="true">
   <proof prover="0" timelimit="5" memlimit="2000"><result status="valid" time="0.420304" steps="42354"/></proof>
   </goal>
  </transf>
  </goal>
  <goal name="wmpz_mul_2exp&#39;vc.179" expl="precondition" proved="true">
  <proof prover="0"><result status="valid" time="0.254235" steps="25357"/></proof>
  </goal>
  <goal name="wmpz_mul_2exp&#39;vc.180" expl="precondition" proved="true">
  <proof prover="0"><result status="valid" time="0.080000" steps="10572"/></proof>
  </goal>
  <goal name="wmpz_mul_2exp&#39;vc.181" expl="precondition" proved="true">
  <proof prover="0" timelimit="5" memlimit="2000"><result status="valid" time="0.050000" steps="11434"/></proof>
  </goal>
  <goal name="wmpz_mul_2exp&#39;vc.182" expl="assertion" proved="true">
  <proof prover="5"><result status="valid" time="0.130000" steps="165"/></proof>
  </goal>
  <goal name="wmpz_mul_2exp&#39;vc.183" expl="precondition" proved="true">
  <proof prover="0"><result status="valid" time="0.252012" steps="27406"/></proof>
  </goal>
  <goal name="wmpz_mul_2exp&#39;vc.184" expl="assertion" proved="true">
  <proof prover="5"><result status="valid" time="0.130000" steps="166"/></proof>
  </goal>
  <goal name="wmpz_mul_2exp&#39;vc.185" expl="assertion" proved="true">
  <transf name="split_vc" proved="true" >
   <goal name="wmpz_mul_2exp&#39;vc.185.0" expl="assertion" proved="true">
   <proof prover="5"><result status="valid" time="0.250000" steps="171"/></proof>
   </goal>
   <goal name="wmpz_mul_2exp&#39;vc.185.1" expl="VC for wmpz_mul_2exp" proved="true">
   <proof prover="5"><result status="valid" time="0.130000" steps="169"/></proof>
   </goal>
   <goal name="wmpz_mul_2exp&#39;vc.185.2" expl="VC for wmpz_mul_2exp" proved="true">
   <proof prover="5"><result status="valid" time="0.810000" steps="689"/></proof>
   </goal>
   <goal name="wmpz_mul_2exp&#39;vc.185.3" expl="VC for wmpz_mul_2exp" proved="true">
   <proof prover="5"><result status="valid" time="2.480000" steps="176"/></proof>
   </goal>
  </transf>
  </goal>
  <goal name="wmpz_mul_2exp&#39;vc.186" expl="precondition" proved="true">
  <proof prover="0"><result status="valid" time="0.110000" steps="10869"/></proof>
  </goal>
  <goal name="wmpz_mul_2exp&#39;vc.187" expl="precondition" proved="true">
  <proof prover="0"><result status="valid" time="0.110000" steps="10741"/></proof>
  </goal>
  <goal name="wmpz_mul_2exp&#39;vc.188" expl="precondition" proved="true">
  <transf name="split_vc" proved="true" >
   <goal name="wmpz_mul_2exp&#39;vc.188.0" expl="precondition" proved="true">
   <proof prover="3"><result status="valid" time="0.110000" steps="170"/></proof>
   </goal>
  </transf>
  </goal>
  <goal name="wmpz_mul_2exp&#39;vc.189" expl="precondition" proved="true">
  <proof prover="0"><result status="valid" time="0.070000" steps="11351"/></proof>
  </goal>
  <goal name="wmpz_mul_2exp&#39;vc.190" expl="precondition" proved="true">
  <proof prover="1"><result status="valid" time="0.300000"/></proof>
  </goal>
  <goal name="wmpz_mul_2exp&#39;vc.191" expl="precondition" proved="true">
  <transf name="split_vc" proved="true" >
   <goal name="wmpz_mul_2exp&#39;vc.191.0" expl="precondition" proved="true">
   <proof prover="0" timelimit="5" memlimit="2000"><result status="valid" time="0.100000" steps="11272"/></proof>
   </goal>
  </transf>
  </goal>
  <goal name="wmpz_mul_2exp&#39;vc.192" expl="precondition" proved="true">
  <proof prover="7"><result status="valid" time="0.080000" steps="86316"/></proof>
  </goal>
  <goal name="wmpz_mul_2exp&#39;vc.193" expl="precondition" proved="true">
  <proof prover="0"><result status="valid" time="0.295406" steps="30106"/></proof>
  </goal>
  <goal name="wmpz_mul_2exp&#39;vc.194" expl="assertion" proved="true">
  <proof prover="0" timelimit="5" memlimit="2000"><result status="valid" time="0.090000" steps="11512"/></proof>
  </goal>
  <goal name="wmpz_mul_2exp&#39;vc.195" expl="assertion" proved="true">
  <transf name="split_vc" proved="true" >
   <goal name="wmpz_mul_2exp&#39;vc.195.0" expl="assertion" proved="true">
   <proof prover="5"><result status="valid" time="0.190000" steps="199"/></proof>
   </goal>
   <goal name="wmpz_mul_2exp&#39;vc.195.1" expl="assertion" proved="true">
   <proof prover="0" timelimit="5" memlimit="2000"><result status="valid" time="0.100000" steps="11013"/></proof>
   </goal>
  </transf>
  </goal>
  <goal name="wmpz_mul_2exp&#39;vc.196" expl="assertion" proved="true">
  <proof prover="0"><result status="valid" time="0.120000" steps="14861"/></proof>
  </goal>
  <goal name="wmpz_mul_2exp&#39;vc.197" expl="precondition" proved="true">
  <proof prover="0"><result status="valid" time="0.100000" steps="11315"/></proof>
  </goal>
  <goal name="wmpz_mul_2exp&#39;vc.198" expl="integer overflow" proved="true">
  <proof prover="0"><result status="valid" time="0.299127" steps="29810"/></proof>
  </goal>
  <goal name="wmpz_mul_2exp&#39;vc.199" expl="assertion" proved="true">
  <transf name="split_vc" proved="true" >
   <goal name="wmpz_mul_2exp&#39;vc.199.0" expl="assertion" proved="true">
   <proof prover="5"><result status="valid" time="1.770000" steps="1038"/></proof>
   </goal>
   <goal name="wmpz_mul_2exp&#39;vc.199.1" expl="VC for wmpz_mul_2exp" proved="true">
   <proof prover="0" timelimit="5" memlimit="2000"><result status="valid" time="0.100000" steps="17852"/></proof>
   </goal>
  </transf>
  </goal>
  <goal name="wmpz_mul_2exp&#39;vc.200" expl="assertion" proved="true">
  <transf name="split_vc" proved="true" >
   <goal name="wmpz_mul_2exp&#39;vc.200.0" expl="assertion" proved="true">
   <proof prover="2"><result status="valid" time="0.146196"/></proof>
   </goal>
   <goal name="wmpz_mul_2exp&#39;vc.200.1" expl="assertion" proved="true">
   <proof prover="3"><result status="valid" time="0.360000" steps="215"/></proof>
   </goal>
   <goal name="wmpz_mul_2exp&#39;vc.200.2" expl="VC for wmpz_mul_2exp" proved="true">
   <proof prover="2"><result status="valid" time="0.090000"/></proof>
   </goal>
   <goal name="wmpz_mul_2exp&#39;vc.200.3" expl="VC for wmpz_mul_2exp" proved="true">
   <proof prover="0" timelimit="5" memlimit="2000"><result status="valid" time="0.205408" steps="31112"/></proof>
   </goal>
   <goal name="wmpz_mul_2exp&#39;vc.200.4" expl="VC for wmpz_mul_2exp" proved="true">
   <proof prover="2"><result status="valid" time="0.340000"/></proof>
   </goal>
   <goal name="wmpz_mul_2exp&#39;vc.200.5" expl="VC for wmpz_mul_2exp" proved="true">
   <proof prover="0" timelimit="5" memlimit="2000"><result status="valid" time="0.299361" steps="32493"/></proof>
   </goal>
   <goal name="wmpz_mul_2exp&#39;vc.200.6" expl="VC for wmpz_mul_2exp" proved="true">
   <proof prover="1"><result status="valid" time="0.550000"/></proof>
   </goal>
  </transf>
  </goal>
  <goal name="wmpz_mul_2exp&#39;vc.201" expl="precondition" proved="true">
  <proof prover="0"><result status="valid" time="0.110000" steps="11585"/></proof>
  </goal>
  <goal name="wmpz_mul_2exp&#39;vc.202" expl="integer overflow" proved="true">
  <proof prover="0" timelimit="5" memlimit="2000"><result status="valid" time="0.250000" steps="31527"/></proof>
  </goal>
  <goal name="wmpz_mul_2exp&#39;vc.203" expl="precondition" proved="true">
  <proof prover="0" timelimit="5" memlimit="2000"><result status="valid" time="0.160000" steps="15772"/></proof>
  </goal>
  <goal name="wmpz_mul_2exp&#39;vc.204" expl="precondition" proved="true">
  <proof prover="0" timelimit="5" memlimit="2000"><result status="valid" time="0.200000" steps="29871"/></proof>
  </goal>
  <goal name="wmpz_mul_2exp&#39;vc.205" expl="precondition" proved="true">
  <proof prover="0" timelimit="5" memlimit="2000"><result status="valid" time="0.060000" steps="12460"/></proof>
  </goal>
  <goal name="wmpz_mul_2exp&#39;vc.206" expl="precondition" proved="true">
  <proof prover="0" timelimit="5" memlimit="2000"><result status="valid" time="0.160000" steps="12466"/></proof>
  </goal>
  <goal name="wmpz_mul_2exp&#39;vc.207" expl="precondition" proved="true">
  <transf name="split_vc" proved="true" >
   <goal name="wmpz_mul_2exp&#39;vc.207.0" expl="precondition" proved="true">
   <proof prover="0" timelimit="5" memlimit="2000"><result status="valid" time="0.170000" steps="17061"/></proof>
   </goal>
   <goal name="wmpz_mul_2exp&#39;vc.207.1" expl="precondition" proved="true">
   <proof prover="1"><result status="valid" time="0.170000"/></proof>
   </goal>
  </transf>
  </goal>
  <goal name="wmpz_mul_2exp&#39;vc.208" expl="precondition" proved="true">
  <proof prover="0"><result status="valid" time="0.781004" steps="64666"/></proof>
  </goal>
  <goal name="wmpz_mul_2exp&#39;vc.209" expl="precondition" proved="true">
  <proof prover="0" timelimit="5" memlimit="2000"><result status="valid" time="0.150000" steps="15782"/></proof>
  </goal>
  <goal name="wmpz_mul_2exp&#39;vc.210" expl="precondition" proved="true">
  <proof prover="0"><result status="valid" time="0.252094" steps="22780"/></proof>
  </goal>
  <goal name="wmpz_mul_2exp&#39;vc.211" expl="precondition" proved="true">
  <proof prover="0" timelimit="5" memlimit="2000"><result status="valid" time="0.180000" steps="15981"/></proof>
  </goal>
  <goal name="wmpz_mul_2exp&#39;vc.212" expl="precondition" proved="true">
  <proof prover="0" timelimit="5" memlimit="2000"><result status="valid" time="0.289649" steps="32172"/></proof>
  </goal>
  <goal name="wmpz_mul_2exp&#39;vc.213" expl="precondition" proved="true">
  <proof prover="0" timelimit="5" memlimit="2000"><result status="valid" time="0.120000" steps="12644"/></proof>
  </goal>
  <goal name="wmpz_mul_2exp&#39;vc.214" expl="precondition" proved="true">
  <proof prover="0" timelimit="5" memlimit="2000"><result status="valid" time="0.070237" steps="17345"/></proof>
  </goal>
  <goal name="wmpz_mul_2exp&#39;vc.215" expl="precondition" proved="true">
  <proof prover="0"><result status="valid" time="0.100000" steps="15580"/></proof>
  </goal>
  <goal name="wmpz_mul_2exp&#39;vc.216" expl="assertion" proved="true">
  <proof prover="1"><result status="valid" time="1.490000"/></proof>
  </goal>
  <goal name="wmpz_mul_2exp&#39;vc.217" expl="postcondition" proved="true">
  <proof prover="0" timelimit="5" memlimit="2000"><result status="valid" time="0.160000" steps="16188"/></proof>
  </goal>
  <goal name="wmpz_mul_2exp&#39;vc.218" expl="postcondition" proved="true">
  <transf name="apply" proved="true" arg1="unchanged_transitive" arg2="with" arg3="mpz1">
   <goal name="wmpz_mul_2exp&#39;vc.218.0" expl="apply premises" proved="true">
   <proof prover="0"><result status="valid" time="0.397483" steps="38861"/></proof>
   </goal>
   <goal name="wmpz_mul_2exp&#39;vc.218.1" expl="apply premises" proved="true">
   <transf name="apply" proved="true" arg1="unchanged_transitive" arg2="with" arg3="mpz2">
    <goal name="wmpz_mul_2exp&#39;vc.218.1.0" expl="apply premises" proved="true">
    <proof prover="0"><result status="valid" time="0.180000" steps="16850"/></proof>
    </goal>
    <goal name="wmpz_mul_2exp&#39;vc.218.1.1" expl="apply premises" proved="true">
    <transf name="apply" proved="true" arg1="unchanged_transitive" arg2="with" arg3="mpz4">
     <goal name="wmpz_mul_2exp&#39;vc.218.1.1.0" expl="apply premises" proved="true">
     <proof prover="0"><result status="valid" time="1.078168" steps="95759"/></proof>
     </goal>
     <goal name="wmpz_mul_2exp&#39;vc.218.1.1.1" expl="apply premises" proved="true">
     <proof prover="0"><result status="valid" time="0.180000" steps="16850"/></proof>
     </goal>
    </transf>
    </goal>
   </transf>
   </goal>
  </transf>
  </goal>
  <goal name="wmpz_mul_2exp&#39;vc.219" expl="postcondition" proved="true">
  <proof prover="0" timelimit="5" memlimit="2000"><result status="valid" time="0.180000" steps="16360"/></proof>
  </goal>
 </transf>
 </goal>
</theory>
</file>
</why3session>
