<?xml version="1.0" encoding="UTF-8"?>
<!DOCTYPE why3session PUBLIC "-//Why3//proof session v5//EN"
"http://why3.lri.fr/why3session.dtd">
<why3session shape_version="6">
<prover id="0" name="Eprover" version="1.9.1-001" timelimit="5" steplimit="0" memlimit="2000"/>
<prover id="1" name="CVC3" version="2.4.1" timelimit="5" steplimit="0" memlimit="1000"/>
<prover id="2" name="CVC4" version="1.5" timelimit="1" steplimit="0" memlimit="1000"/>
<prover id="3" name="Z3" version="4.5.0" timelimit="5" steplimit="0" memlimit="1000"/>
<prover id="4" name="Eprover" version="2.0" timelimit="5" steplimit="0" memlimit="2000"/>
<prover id="5" name="Alt-Ergo" version="2.0.0" timelimit="1" steplimit="0" memlimit="1000"/>
<prover id="6" name="Alt-Ergo" version="2.2.0" timelimit="1" steplimit="0" memlimit="1000"/>
<prover id="7" name="CVC4" version="1.6" timelimit="1" steplimit="0" memlimit="1000"/>
<prover id="8" name="Z3" version="4.6.0" timelimit="1" steplimit="0" memlimit="1000"/>
<prover id="9" name="Alt-Ergo" version="2.3.0" timelimit="5" steplimit="0" memlimit="2000"/>
<prover id="10" name="Alt-Ergo" version="2.4.0" timelimit="1" steplimit="0" memlimit="1000"/>
<file format="whyml" proved="true">
<path name=".."/><path name="add_1.mlw"/>
<theory name="Add_1" proved="true">
 <goal name="wmpn_add_1&#39;vc" expl="VC for wmpn_add_1" proved="true">
 <transf name="split_goal_right" proved="true" >
  <goal name="wmpn_add_1&#39;vc.0" expl="precondition" proved="true">
  <proof prover="2"><result status="valid" time="0.05" steps="14954"/></proof>
  </goal>
  <goal name="wmpn_add_1&#39;vc.1" expl="precondition" proved="true">
  <proof prover="5" timelimit="5"><result status="valid" time="0.05" steps="25"/></proof>
  </goal>
  <goal name="wmpn_add_1&#39;vc.2" expl="precondition" proved="true">
  <proof prover="3"><result status="valid" time="0.02" steps="24330"/></proof>
  </goal>
  <goal name="wmpn_add_1&#39;vc.3" expl="assertion" proved="true">
  <proof prover="3"><result status="valid" time="0.03" steps="46974"/></proof>
  <proof prover="5" timelimit="5"><result status="valid" time="0.04" steps="48"/></proof>
  </goal>
  <goal name="wmpn_add_1&#39;vc.4" expl="loop invariant init" proved="true">
  <proof prover="5" timelimit="5"><result status="valid" time="0.01" steps="26"/></proof>
  </goal>
  <goal name="wmpn_add_1&#39;vc.5" expl="loop invariant init" proved="true">
  <proof prover="3"><result status="valid" time="0.03" steps="28832"/></proof>
  <proof prover="5" timelimit="5"><result status="valid" time="0.04" steps="28"/></proof>
  </goal>
  <goal name="wmpn_add_1&#39;vc.6" expl="loop invariant init" proved="true">
  <proof prover="2"><result status="valid" time="0.04" steps="14958"/></proof>
  </goal>
  <goal name="wmpn_add_1&#39;vc.7" expl="loop invariant init" proved="true">
  <proof prover="7"><result status="valid" time="0.32" steps="37209"/></proof>
  </goal>
  <goal name="wmpn_add_1&#39;vc.8" expl="loop invariant init" proved="true">
  <proof prover="2"><result status="valid" time="0.08" steps="16958"/></proof>
  </goal>
  <goal name="wmpn_add_1&#39;vc.9" expl="assertion" proved="true">
  <proof prover="5" timelimit="5"><result status="valid" time="0.03" steps="39"/></proof>
  </goal>
  <goal name="wmpn_add_1&#39;vc.10" expl="precondition" proved="true">
  <transf name="split_goal_right" proved="true" >
   <goal name="wmpn_add_1&#39;vc.10.0" expl="VC for wmpn_add_1" proved="true">
   <proof prover="1" memlimit="2000"><result status="valid" time="0.05"/></proof>
   </goal>
   <goal name="wmpn_add_1&#39;vc.10.1" expl="VC for wmpn_add_1" proved="true">
   <transf name="introduce_premises" proved="true" >
    <goal name="wmpn_add_1&#39;vc.10.1.0" expl="VC for wmpn_add_1" proved="true">
    <proof prover="0"><result status="valid" time="0.35"/></proof>
    </goal>
   </transf>
   </goal>
  </transf>
  </goal>
  <goal name="wmpn_add_1&#39;vc.11" expl="precondition" proved="true">
  <proof prover="7"><result status="valid" time="0.12" steps="22260"/></proof>
  </goal>
  <goal name="wmpn_add_1&#39;vc.12" expl="precondition" proved="true">
  <proof prover="3"><result status="valid" time="0.03" steps="28559"/></proof>
  </goal>
  <goal name="wmpn_add_1&#39;vc.13" expl="assertion" proved="true">
  <proof prover="6"><result status="valid" time="0.25" steps="326"/></proof>
  </goal>
  <goal name="wmpn_add_1&#39;vc.14" expl="precondition" proved="true">
  <proof prover="2"><result status="valid" time="0.13" steps="19906"/></proof>
  </goal>
  <goal name="wmpn_add_1&#39;vc.15" expl="precondition" proved="true">
  <proof prover="2"><result status="valid" time="0.11" steps="20190"/></proof>
  </goal>
  <goal name="wmpn_add_1&#39;vc.16" expl="integer overflow" proved="true">
  <proof prover="5"><result status="valid" time="0.26" steps="64"/></proof>
  </goal>
  <goal name="wmpn_add_1&#39;vc.17" expl="assertion" proved="true">
  <proof prover="2"><result status="valid" time="0.23" steps="32639"/></proof>
  </goal>
  <goal name="wmpn_add_1&#39;vc.18" expl="assertion" proved="true">
  <proof prover="6"><result status="valid" time="0.86" steps="113"/></proof>
  </goal>
  <goal name="wmpn_add_1&#39;vc.19" expl="loop invariant init" proved="true">
  <proof prover="2"><result status="valid" time="0.05" steps="19593"/></proof>
  </goal>
  <goal name="wmpn_add_1&#39;vc.20" expl="loop invariant init" proved="true">
  <proof prover="2"><result status="valid" time="0.13" steps="21852"/></proof>
  </goal>
  <goal name="wmpn_add_1&#39;vc.21" expl="loop invariant init" proved="true">
  <proof prover="2"><result status="valid" time="0.14" steps="20244"/></proof>
  </goal>
  <goal name="wmpn_add_1&#39;vc.22" expl="loop invariant init" proved="true">
  <proof prover="2"><result status="valid" time="0.11" steps="26496"/></proof>
  </goal>
  <goal name="wmpn_add_1&#39;vc.23" expl="precondition" proved="true">
  <proof prover="5"><result status="valid" time="0.46" steps="79"/></proof>
  </goal>
  <goal name="wmpn_add_1&#39;vc.24" expl="precondition" proved="true">
  <proof prover="2"><result status="valid" time="0.16" steps="28596"/></proof>
  </goal>
  <goal name="wmpn_add_1&#39;vc.25" expl="precondition" proved="true">
  <proof prover="2"><result status="valid" time="0.05" steps="24449"/></proof>
  </goal>
  <goal name="wmpn_add_1&#39;vc.26" expl="assertion" proved="true">
  <proof prover="6" timelimit="5" memlimit="2000"><result status="valid" time="2.24" steps="501"/></proof>
  </goal>
  <goal name="wmpn_add_1&#39;vc.27" expl="precondition" proved="true">
  <proof prover="1"><result status="valid" time="0.06"/></proof>
  </goal>
  <goal name="wmpn_add_1&#39;vc.28" expl="precondition" proved="true">
  <proof prover="2"><result status="valid" time="0.04" steps="16155"/></proof>
  </goal>
  <goal name="wmpn_add_1&#39;vc.29" expl="integer overflow" proved="true">
  <proof prover="2"><result status="valid" time="0.20" steps="32066"/></proof>
  </goal>
  <goal name="wmpn_add_1&#39;vc.30" expl="loop variant decrease" proved="true">
  <proof prover="5"><result status="valid" time="0.50" steps="83"/></proof>
  </goal>
  <goal name="wmpn_add_1&#39;vc.31" expl="loop invariant preservation" proved="true">
  <proof prover="2"><result status="valid" time="0.11" steps="24909"/></proof>
  </goal>
  <goal name="wmpn_add_1&#39;vc.32" expl="loop invariant preservation" proved="true">
  <proof prover="5" timelimit="5"><result status="valid" time="0.50" steps="83"/></proof>
  </goal>
  <goal name="wmpn_add_1&#39;vc.33" expl="loop invariant preservation" proved="true">
  <proof prover="6" timelimit="5" memlimit="2000"><result status="valid" time="0.87" steps="165"/></proof>
  </goal>
  <goal name="wmpn_add_1&#39;vc.34" expl="loop invariant preservation" proved="true">
  <proof prover="7"><result status="valid" time="0.23" steps="34718"/></proof>
  </goal>
  <goal name="wmpn_add_1&#39;vc.35" expl="postcondition" proved="true">
  <proof prover="2"><result status="valid" time="0.14" steps="24392"/></proof>
  </goal>
  <goal name="wmpn_add_1&#39;vc.36" expl="postcondition" proved="true">
  <proof prover="5"><result status="valid" time="0.46" steps="70"/></proof>
  </goal>
  <goal name="wmpn_add_1&#39;vc.37" expl="postcondition" proved="true">
  <proof prover="2"><result status="valid" time="0.19" steps="29154"/></proof>
  </goal>
  <goal name="wmpn_add_1&#39;vc.38" expl="assertion" proved="true">
  <proof prover="7"><result status="valid" time="0.20" steps="32895"/></proof>
  </goal>
  <goal name="wmpn_add_1&#39;vc.39" expl="assertion" proved="true">
  <proof prover="6" timelimit="5" memlimit="2000"><result status="valid" time="0.71" steps="113"/></proof>
  </goal>
  <goal name="wmpn_add_1&#39;vc.40" expl="loop variant decrease" proved="true">
  <proof prover="3"><result status="valid" time="0.04" steps="38638"/></proof>
  </goal>
  <goal name="wmpn_add_1&#39;vc.41" expl="loop invariant preservation" proved="true">
  <proof prover="0"><result status="valid" time="3.52"/></proof>
  </goal>
  <goal name="wmpn_add_1&#39;vc.42" expl="loop invariant preservation" proved="true">
  <proof prover="2" timelimit="5"><result status="valid" time="0.14" steps="21569"/></proof>
  </goal>
  <goal name="wmpn_add_1&#39;vc.43" expl="loop invariant preservation" proved="true">
  <proof prover="2"><result status="valid" time="0.06" steps="16626"/></proof>
  </goal>
  <goal name="wmpn_add_1&#39;vc.44" expl="loop invariant preservation" proved="true">
  <proof prover="6"><result status="valid" time="0.65" steps="115"/></proof>
  </goal>
  <goal name="wmpn_add_1&#39;vc.45" expl="loop invariant preservation" proved="true">
  <proof prover="2"><result status="valid" time="0.15" steps="26351"/></proof>
  </goal>
  <goal name="wmpn_add_1&#39;vc.46" expl="loop invariant init" proved="true">
  <proof prover="2"><result status="valid" time="0.07" steps="17679"/></proof>
  </goal>
  <goal name="wmpn_add_1&#39;vc.47" expl="loop invariant init" proved="true">
  <proof prover="2"><result status="valid" time="0.12" steps="17728"/></proof>
  </goal>
  <goal name="wmpn_add_1&#39;vc.48" expl="loop invariant init" proved="true">
  <proof prover="2"><result status="valid" time="0.10" steps="14519"/></proof>
  </goal>
  <goal name="wmpn_add_1&#39;vc.49" expl="loop invariant init" proved="true">
  <proof prover="0"><result status="valid" time="0.06"/></proof>
  </goal>
  <goal name="wmpn_add_1&#39;vc.50" expl="precondition" proved="true">
  <proof prover="2"><result status="valid" time="0.04" steps="23045"/></proof>
  </goal>
  <goal name="wmpn_add_1&#39;vc.51" expl="precondition" proved="true">
  <proof prover="2"><result status="valid" time="0.14" steps="23108"/></proof>
  </goal>
  <goal name="wmpn_add_1&#39;vc.52" expl="precondition" proved="true">
  <proof prover="2"><result status="valid" time="0.11" steps="19605"/></proof>
  </goal>
  <goal name="wmpn_add_1&#39;vc.53" expl="assertion" proved="true">
  <proof prover="4"><result status="valid" time="0.29"/></proof>
  </goal>
  <goal name="wmpn_add_1&#39;vc.54" expl="precondition" proved="true">
  <proof prover="2"><result status="valid" time="0.06" steps="15448"/></proof>
  </goal>
  <goal name="wmpn_add_1&#39;vc.55" expl="precondition" proved="true">
  <proof prover="3"><result status="valid" time="0.03" steps="30976"/></proof>
  </goal>
  <goal name="wmpn_add_1&#39;vc.56" expl="integer overflow" proved="true">
  <proof prover="5"><result status="valid" time="0.15" steps="72"/></proof>
  </goal>
  <goal name="wmpn_add_1&#39;vc.57" expl="loop variant decrease" proved="true">
  <proof prover="2"><result status="valid" time="0.10" steps="21725"/></proof>
  </goal>
  <goal name="wmpn_add_1&#39;vc.58" expl="loop invariant preservation" proved="true">
  <proof prover="5"><result status="valid" time="0.02" steps="64"/></proof>
  </goal>
  <goal name="wmpn_add_1&#39;vc.59" expl="loop invariant preservation" proved="true">
  <proof prover="5" timelimit="5"><result status="valid" time="0.04" steps="62"/></proof>
  </goal>
  <goal name="wmpn_add_1&#39;vc.60" expl="loop invariant preservation" proved="true">
  <proof prover="6"><result status="valid" time="0.21" steps="125"/></proof>
  </goal>
  <goal name="wmpn_add_1&#39;vc.61" expl="loop invariant preservation" proved="true">
  <proof prover="2"><result status="valid" time="0.16" steps="27143"/></proof>
  </goal>
  <goal name="wmpn_add_1&#39;vc.62" expl="postcondition" proved="true">
  <proof prover="5" timelimit="5"><result status="valid" time="0.08" steps="48"/></proof>
  </goal>
  <goal name="wmpn_add_1&#39;vc.63" expl="postcondition" proved="true">
  <proof prover="5" timelimit="5"><result status="valid" time="0.06" steps="49"/></proof>
  </goal>
  <goal name="wmpn_add_1&#39;vc.64" expl="postcondition" proved="true">
  <proof prover="3"><result status="valid" time="0.02" steps="36042"/></proof>
  </goal>
  <goal name="wmpn_add_1&#39;vc.65" expl="loop invariant init" proved="true">
  <proof prover="3"><result status="valid" time="0.12" steps="2272"/></proof>
  <proof prover="5" timelimit="5"><result status="valid" time="0.06" steps="10"/></proof>
  </goal>
  <goal name="wmpn_add_1&#39;vc.66" expl="loop invariant init" proved="true">
  <proof prover="5" timelimit="5"><result status="valid" time="0.04" steps="23"/></proof>
  </goal>
  <goal name="wmpn_add_1&#39;vc.67" expl="loop invariant init" proved="true">
  <proof prover="5" timelimit="5"><result status="valid" time="0.08" steps="95"/></proof>
  </goal>
  <goal name="wmpn_add_1&#39;vc.68" expl="loop invariant init" proved="true">
  <proof prover="3"><result status="valid" time="0.03" steps="31238"/></proof>
  <proof prover="5" timelimit="5"><result status="valid" time="0.05" steps="49"/></proof>
  </goal>
  <goal name="wmpn_add_1&#39;vc.69" expl="precondition" proved="true">
  <proof prover="3"><result status="valid" time="0.14" steps="169858"/></proof>
  </goal>
  <goal name="wmpn_add_1&#39;vc.70" expl="precondition" proved="true">
  <proof prover="7"><result status="valid" time="0.15" steps="20247"/></proof>
  </goal>
  <goal name="wmpn_add_1&#39;vc.71" expl="precondition" proved="true">
  <proof prover="2"><result status="valid" time="0.08" steps="17368"/></proof>
  </goal>
  <goal name="wmpn_add_1&#39;vc.72" expl="assertion" proved="true">
  <proof prover="6" timelimit="5" memlimit="2000"><result status="valid" time="1.00" steps="433"/></proof>
  </goal>
  <goal name="wmpn_add_1&#39;vc.73" expl="precondition" proved="true">
  <proof prover="2"><result status="valid" time="0.07" steps="14937"/></proof>
  </goal>
  <goal name="wmpn_add_1&#39;vc.74" expl="precondition" proved="true">
  <proof prover="5"><result status="valid" time="0.04" steps="44"/></proof>
  </goal>
  <goal name="wmpn_add_1&#39;vc.75" expl="integer overflow" proved="true">
  <proof prover="5"><result status="valid" time="0.04" steps="57"/></proof>
  </goal>
  <goal name="wmpn_add_1&#39;vc.76" expl="loop variant decrease" proved="true">
  <proof prover="2"><result status="valid" time="0.06" steps="19267"/></proof>
  </goal>
  <goal name="wmpn_add_1&#39;vc.77" expl="loop invariant preservation" proved="true">
  <proof prover="2"><result status="valid" time="0.06" steps="12060"/></proof>
  </goal>
  <goal name="wmpn_add_1&#39;vc.78" expl="loop invariant preservation" proved="true">
  <proof prover="2"><result status="valid" time="0.10" steps="19290"/></proof>
  </goal>
  <goal name="wmpn_add_1&#39;vc.79" expl="loop invariant preservation" proved="true">
  <proof prover="5"><result status="valid" time="0.06" steps="49"/></proof>
  </goal>
  <goal name="wmpn_add_1&#39;vc.80" expl="loop invariant preservation" proved="true">
  <proof prover="7"><result status="valid" time="0.12" steps="24102"/></proof>
  </goal>
  <goal name="wmpn_add_1&#39;vc.81" expl="postcondition" proved="true">
  <proof prover="7"><result status="valid" time="0.07" steps="17653"/></proof>
  </goal>
  <goal name="wmpn_add_1&#39;vc.82" expl="postcondition" proved="true">
  <proof prover="7"><result status="valid" time="0.05" steps="14435"/></proof>
  </goal>
  <goal name="wmpn_add_1&#39;vc.83" expl="postcondition" proved="true">
  <proof prover="7"><result status="valid" time="0.09" steps="20463"/></proof>
  </goal>
 </transf>
 </goal>
 <goal name="wmpn_incr&#39;vc" expl="VC for wmpn_incr" proved="true">
 <transf name="split_vc" proved="true" >
  <goal name="wmpn_incr&#39;vc.0" expl="precondition" proved="true">
  <proof prover="7"><result status="valid" time="0.10" steps="16291"/></proof>
  </goal>
  <goal name="wmpn_incr&#39;vc.1" expl="precondition" proved="true">
  <proof prover="7"><result status="valid" time="0.10" steps="16297"/></proof>
  </goal>
  <goal name="wmpn_incr&#39;vc.2" expl="precondition" proved="true">
  <proof prover="7"><result status="valid" time="0.18" steps="17588"/></proof>
  </goal>
  <goal name="wmpn_incr&#39;vc.3" expl="precondition" proved="true">
  <proof prover="7"><result status="valid" time="0.04" steps="12616"/></proof>
  </goal>
  <goal name="wmpn_incr&#39;vc.4" expl="assertion" proved="true">
  <proof prover="7"><result status="valid" time="0.13" steps="21620"/></proof>
  </goal>
  <goal name="wmpn_incr&#39;vc.5" expl="loop invariant init" proved="true">
  <proof prover="6"><result status="valid" time="0.01" steps="76"/></proof>
  </goal>
  <goal name="wmpn_incr&#39;vc.6" expl="loop invariant init" proved="true">
  <proof prover="7"><result status="valid" time="0.12" steps="14838"/></proof>
  </goal>
  <goal name="wmpn_incr&#39;vc.7" expl="loop invariant init" proved="true">
  <proof prover="6"><result status="valid" time="0.02" steps="81"/></proof>
  </goal>
  <goal name="wmpn_incr&#39;vc.8" expl="loop invariant init" proved="true">
  <proof prover="6"><result status="valid" time="0.02" steps="83"/></proof>
  </goal>
  <goal name="wmpn_incr&#39;vc.9" expl="loop invariant init" proved="true">
  <transf name="split_vc" proved="true" >
   <goal name="wmpn_incr&#39;vc.9.0" expl="loop invariant init" proved="true">
   <proof prover="7"><result status="valid" time="0.08" steps="14683"/></proof>
   </goal>
   <goal name="wmpn_incr&#39;vc.9.1" expl="loop invariant init" proved="true">
   <proof prover="7"><result status="valid" time="0.07" steps="14688"/></proof>
   </goal>
  </transf>
  </goal>
  <goal name="wmpn_incr&#39;vc.10" expl="loop invariant init" proved="true">
  <proof prover="7"><result status="valid" time="0.18" steps="20903"/></proof>
  </goal>
  <goal name="wmpn_incr&#39;vc.11" expl="loop invariant init" proved="true">
  <proof prover="7"><result status="valid" time="0.04" steps="14509"/></proof>
  </goal>
  <goal name="wmpn_incr&#39;vc.12" expl="loop invariant init" proved="true">
  <proof prover="4"><result status="valid" time="0.02"/></proof>
  </goal>
  <goal name="wmpn_incr&#39;vc.13" expl="loop invariant init" proved="true">
  <proof prover="10"><result status="valid" time="0.16" steps="1563"/></proof>
  </goal>
  <goal name="wmpn_incr&#39;vc.14" expl="loop invariant init" proved="true">
  <proof prover="6"><result status="valid" time="0.02" steps="99"/></proof>
  </goal>
  <goal name="wmpn_incr&#39;vc.15" expl="loop invariant init" proved="true">
  <transf name="replace" proved="true" arg1="(pelts x)" arg2="(pelts xp)">
   <goal name="wmpn_incr&#39;vc.15.0" expl="loop invariant init" proved="true">
   <proof prover="7"><result status="valid" time="0.12" steps="15583"/></proof>
   </goal>
   <goal name="wmpn_incr&#39;vc.15.1" expl="equality hypothesis" proved="true">
   <proof prover="7"><result status="valid" time="0.05" steps="13950"/></proof>
   </goal>
  </transf>
  </goal>
  <goal name="wmpn_incr&#39;vc.16" expl="assertion" proved="true">
  <proof prover="7"><result status="valid" time="0.11" steps="15304"/></proof>
  </goal>
  <goal name="wmpn_incr&#39;vc.17" expl="precondition" proved="true">
  <proof prover="7"><result status="valid" time="0.07" steps="19216"/></proof>
  </goal>
  <goal name="wmpn_incr&#39;vc.18" expl="assertion" proved="true">
  <proof prover="6"><result status="valid" time="0.08" steps="123"/></proof>
  </goal>
  <goal name="wmpn_incr&#39;vc.19" expl="precondition" proved="true">
  <proof prover="6"><result status="valid" time="0.09" steps="127"/></proof>
  </goal>
  <goal name="wmpn_incr&#39;vc.20" expl="precondition" proved="true">
  <proof prover="7"><result status="valid" time="0.08" steps="14202"/></proof>
  </goal>
  <goal name="wmpn_incr&#39;vc.21" expl="precondition" proved="true">
  <proof prover="7"><result status="valid" time="0.07" steps="21131"/></proof>
  </goal>
  <goal name="wmpn_incr&#39;vc.22" expl="precondition" proved="true">
  <proof prover="7"><result status="valid" time="0.12" steps="13978"/></proof>
  </goal>
  <goal name="wmpn_incr&#39;vc.23" expl="assertion" proved="true">
  <proof prover="6"><result status="valid" time="0.24" steps="392"/></proof>
  </goal>
  <goal name="wmpn_incr&#39;vc.24" expl="assertion" proved="true">
  <proof prover="4"><result status="valid" time="0.50"/></proof>
  </goal>
  <goal name="wmpn_incr&#39;vc.25" expl="precondition" proved="true">
  <proof prover="6"><result status="valid" time="0.07" steps="157"/></proof>
  </goal>
  <goal name="wmpn_incr&#39;vc.26" expl="precondition" proved="true">
  <proof prover="7"><result status="valid" time="0.12" steps="16294"/></proof>
  </goal>
  <goal name="wmpn_incr&#39;vc.27" expl="integer overflow" proved="true">
  <proof prover="7"><result status="valid" time="0.19" steps="22221"/></proof>
  </goal>
  <goal name="wmpn_incr&#39;vc.28" expl="precondition" proved="true">
  <proof prover="7"><result status="valid" time="0.22" steps="22871"/></proof>
  </goal>
  <goal name="wmpn_incr&#39;vc.29" expl="assertion" proved="true">
  <proof prover="7"><result status="valid" time="0.24" steps="23502"/></proof>
  </goal>
  <goal name="wmpn_incr&#39;vc.30" expl="assertion" proved="true">
  <proof prover="6"><result status="valid" time="0.52" steps="187"/></proof>
  </goal>
  <goal name="wmpn_incr&#39;vc.31" expl="assertion" proved="true">
  <proof prover="6"><result status="valid" time="0.88" steps="659"/></proof>
  </goal>
  <goal name="wmpn_incr&#39;vc.32" expl="precondition" proved="true">
  <proof prover="7"><result status="valid" time="0.15" steps="17620"/></proof>
  </goal>
  <goal name="wmpn_incr&#39;vc.33" expl="precondition" proved="true">
  <proof prover="7"><result status="valid" time="0.11" steps="17761"/></proof>
  </goal>
  <goal name="wmpn_incr&#39;vc.34" expl="assertion" proved="true">
  <transf name="split_vc" proved="true" >
   <goal name="wmpn_incr&#39;vc.34.0" expl="assertion" proved="true">
   <proof prover="7"><result status="valid" time="0.09" steps="15419"/></proof>
   </goal>
   <goal name="wmpn_incr&#39;vc.34.1" expl="assertion" proved="true">
   <proof prover="7"><result status="valid" time="0.08" steps="15432"/></proof>
   </goal>
   <goal name="wmpn_incr&#39;vc.34.2" expl="VC for wmpn_incr" proved="true">
   <proof prover="4"><result status="valid" time="1.86"/></proof>
   </goal>
   <goal name="wmpn_incr&#39;vc.34.3" expl="VC for wmpn_incr" proved="true">
   <proof prover="7"><result status="valid" time="0.09" steps="15558"/></proof>
   </goal>
  </transf>
  </goal>
  <goal name="wmpn_incr&#39;vc.35" expl="precondition" proved="true">
  <proof prover="7"><result status="valid" time="0.20" steps="25067"/></proof>
  </goal>
  <goal name="wmpn_incr&#39;vc.36" expl="postcondition" proved="true">
  <proof prover="6"><result status="valid" time="0.13" steps="193"/></proof>
  </goal>
  <goal name="wmpn_incr&#39;vc.37" expl="postcondition" proved="true">
  <proof prover="7"><result status="valid" time="0.13" steps="25498"/></proof>
  </goal>
  <goal name="wmpn_incr&#39;vc.38" expl="assertion" proved="true">
  <proof prover="7"><result status="valid" time="0.22" steps="23705"/></proof>
  </goal>
  <goal name="wmpn_incr&#39;vc.39" expl="assertion" proved="true">
  <transf name="split_vc" proved="true" >
   <goal name="wmpn_incr&#39;vc.39.0" expl="assertion" proved="true">
   <proof prover="9"><result status="valid" time="0.25" steps="187"/></proof>
   </goal>
   <goal name="wmpn_incr&#39;vc.39.1" expl="VC for wmpn_incr" proved="true">
   <proof prover="9"><result status="valid" time="0.28" steps="189"/></proof>
   </goal>
  </transf>
  </goal>
  <goal name="wmpn_incr&#39;vc.40" expl="assertion" proved="true">
  <proof prover="7"><result status="valid" time="0.60" steps="70188"/></proof>
  </goal>
  <goal name="wmpn_incr&#39;vc.41" expl="loop variant decrease" proved="true">
  <proof prover="6"><result status="valid" time="0.16" steps="189"/></proof>
  </goal>
  <goal name="wmpn_incr&#39;vc.42" expl="loop invariant preservation" proved="true">
  <proof prover="7"><result status="valid" time="0.06" steps="17503"/></proof>
  </goal>
  <goal name="wmpn_incr&#39;vc.43" expl="loop invariant preservation" proved="true">
  <proof prover="7"><result status="valid" time="0.13" steps="17602"/></proof>
  </goal>
  <goal name="wmpn_incr&#39;vc.44" expl="loop invariant preservation" proved="true">
  <proof prover="4"><result status="valid" time="0.01"/></proof>
  </goal>
  <goal name="wmpn_incr&#39;vc.45" expl="loop invariant preservation" proved="true">
  <proof prover="6"><result status="valid" time="0.27" steps="197"/></proof>
  </goal>
  <goal name="wmpn_incr&#39;vc.46" expl="loop invariant preservation" proved="true">
  <proof prover="7"><result status="valid" time="0.10" steps="17385"/></proof>
  </goal>
  <goal name="wmpn_incr&#39;vc.47" expl="loop invariant preservation" proved="true">
  <proof prover="7"><result status="valid" time="0.10" steps="15039"/></proof>
  </goal>
  <goal name="wmpn_incr&#39;vc.48" expl="loop invariant preservation" proved="true">
  <proof prover="6"><result status="valid" time="0.20" steps="199"/></proof>
  </goal>
  <goal name="wmpn_incr&#39;vc.49" expl="loop invariant preservation" proved="true">
  <proof prover="7"><result status="valid" time="0.15" steps="15023"/></proof>
  </goal>
  <goal name="wmpn_incr&#39;vc.50" expl="loop invariant preservation" proved="true">
  <proof prover="6"><result status="valid" time="0.19" steps="199"/></proof>
  </goal>
  <goal name="wmpn_incr&#39;vc.51" expl="loop invariant preservation" proved="true">
  <proof prover="6"><result status="valid" time="0.26" steps="206"/></proof>
  </goal>
  <goal name="wmpn_incr&#39;vc.52" expl="loop invariant preservation" proved="true">
  <proof prover="7"><result status="valid" time="0.12" steps="24151"/></proof>
  </goal>
  <goal name="wmpn_incr&#39;vc.53" expl="precondition" proved="true">
  <proof prover="7"><result status="valid" time="0.07" steps="15205"/></proof>
  </goal>
  <goal name="wmpn_incr&#39;vc.54" expl="precondition" proved="true">
  <proof prover="7"><result status="valid" time="0.10" steps="15280"/></proof>
  </goal>
  <goal name="wmpn_incr&#39;vc.55" expl="assertion" proved="true">
  <transf name="split_vc" proved="true" >
   <goal name="wmpn_incr&#39;vc.55.0" expl="assertion" proved="true">
   <proof prover="7"><result status="valid" time="0.07" steps="14134"/></proof>
   </goal>
   <goal name="wmpn_incr&#39;vc.55.1" expl="assertion" proved="true">
   <proof prover="7"><result status="valid" time="0.06" steps="14147"/></proof>
   </goal>
   <goal name="wmpn_incr&#39;vc.55.2" expl="VC for wmpn_incr" proved="true">
   <proof prover="6"><result status="valid" time="0.10" steps="129"/></proof>
   </goal>
   <goal name="wmpn_incr&#39;vc.55.3" expl="VC for wmpn_incr" proved="true">
   <proof prover="7"><result status="valid" time="0.04" steps="14421"/></proof>
   </goal>
  </transf>
  </goal>
  <goal name="wmpn_incr&#39;vc.56" expl="precondition" proved="true">
  <proof prover="7"><result status="valid" time="0.10" steps="20695"/></proof>
  </goal>
  <goal name="wmpn_incr&#39;vc.57" expl="postcondition" proved="true">
  <proof prover="6"><result status="valid" time="0.04" steps="122"/></proof>
  </goal>
  <goal name="wmpn_incr&#39;vc.58" expl="postcondition" proved="true">
  <proof prover="7"><result status="valid" time="0.11" steps="20725"/></proof>
  </goal>
  <goal name="wmpn_incr&#39;vc.59" expl="precondition" proved="true">
  <proof prover="7"><result status="valid" time="0.04" steps="12988"/></proof>
  </goal>
  <goal name="wmpn_incr&#39;vc.60" expl="precondition" proved="true">
  <proof prover="6"><result status="valid" time="0.06" steps="72"/></proof>
  </goal>
  <goal name="wmpn_incr&#39;vc.61" expl="assertion" proved="true">
  <proof prover="7"><result status="valid" time="0.08" steps="15131"/></proof>
  </goal>
  <goal name="wmpn_incr&#39;vc.62" expl="precondition" proved="true">
  <proof prover="7"><result status="valid" time="0.11" steps="18942"/></proof>
  </goal>
  <goal name="wmpn_incr&#39;vc.63" expl="postcondition" proved="true">
  <proof prover="6"><result status="valid" time="0.18" steps="78"/></proof>
  </goal>
  <goal name="wmpn_incr&#39;vc.64" expl="postcondition" proved="true">
  <proof prover="7"><result status="valid" time="0.08" steps="15357"/></proof>
  </goal>
 </transf>
 </goal>
 <goal name="wmpn_incr_1&#39;vc" expl="VC for wmpn_incr_1" proved="true">
 <transf name="split_vc" proved="true" >
  <goal name="wmpn_incr_1&#39;vc.0" expl="precondition" proved="true">
  <proof prover="3"><result status="valid" time="0.02" steps="23255"/></proof>
  </goal>
  <goal name="wmpn_incr_1&#39;vc.1" expl="loop invariant init" proved="true">
  <proof prover="5"><result status="valid" time="0.02" steps="20"/></proof>
  </goal>
  <goal name="wmpn_incr_1&#39;vc.2" expl="loop invariant init" proved="true">
  <proof prover="3"><result status="valid" time="0.03" steps="26842"/></proof>
  </goal>
  <goal name="wmpn_incr_1&#39;vc.3" expl="loop invariant init" proved="true">
  <transf name="split_vc" proved="true" >
   <goal name="wmpn_incr_1&#39;vc.3.0" expl="loop invariant init" proved="true">
   <proof prover="5" timelimit="5"><result status="valid" time="0.02" steps="24"/></proof>
   </goal>
  </transf>
  </goal>
  <goal name="wmpn_incr_1&#39;vc.4" expl="loop invariant init" proved="true">
  <proof prover="7"><result status="valid" time="0.04" steps="13150"/></proof>
  </goal>
  <goal name="wmpn_incr_1&#39;vc.5" expl="loop invariant init" proved="true">
  <proof prover="3"><result status="valid" time="0.03" steps="2470"/></proof>
  </goal>
  <goal name="wmpn_incr_1&#39;vc.6" expl="loop invariant init" proved="true">
  <proof prover="5"><result status="valid" time="0.06" steps="24"/></proof>
  </goal>
  <goal name="wmpn_incr_1&#39;vc.7" expl="loop invariant init" proved="true">
  <proof prover="3"><result status="valid" time="0.02" steps="2434"/></proof>
  </goal>
  <goal name="wmpn_incr_1&#39;vc.8" expl="loop invariant init" proved="true">
  <proof prover="7"><result status="valid" time="0.11" steps="12623"/></proof>
  </goal>
  <goal name="wmpn_incr_1&#39;vc.9" expl="loop invariant init" proved="true">
  <proof prover="6"><result status="valid" time="0.02" steps="46"/></proof>
  </goal>
  <goal name="wmpn_incr_1&#39;vc.10" expl="loop invariant init" proved="true">
  <proof prover="6"><result status="valid" time="0.02" steps="48"/></proof>
  </goal>
  <goal name="wmpn_incr_1&#39;vc.11" expl="loop invariant init" proved="true">
  <proof prover="7"><result status="valid" time="0.11" steps="12699"/></proof>
  </goal>
  <goal name="wmpn_incr_1&#39;vc.12" expl="loop invariant init" proved="true">
  <proof prover="3"><result status="valid" time="0.02" steps="2462"/></proof>
  </goal>
  <goal name="wmpn_incr_1&#39;vc.13" expl="precondition" proved="true">
  <proof prover="7"><result status="valid" time="0.09" steps="17818"/></proof>
  </goal>
  <goal name="wmpn_incr_1&#39;vc.14" expl="assertion" proved="true">
  <proof prover="5"><result status="valid" time="0.02" steps="57"/></proof>
  </goal>
  <goal name="wmpn_incr_1&#39;vc.15" expl="assertion" proved="true">
  <proof prover="5"><result status="valid" time="0.04" steps="70"/></proof>
  </goal>
  <goal name="wmpn_incr_1&#39;vc.16" expl="precondition" proved="true">
  <proof prover="5"><result status="valid" time="0.07" steps="113"/></proof>
  </goal>
  <goal name="wmpn_incr_1&#39;vc.17" expl="precondition" proved="true">
  <proof prover="5"><result status="valid" time="0.02" steps="50"/></proof>
  </goal>
  <goal name="wmpn_incr_1&#39;vc.18" expl="precondition" proved="true">
  <proof prover="7"><result status="valid" time="0.12" steps="19664"/></proof>
  </goal>
  <goal name="wmpn_incr_1&#39;vc.19" expl="precondition" proved="true">
  <proof prover="3"><result status="valid" time="0.01" steps="2662"/></proof>
  </goal>
  <goal name="wmpn_incr_1&#39;vc.20" expl="assertion" proved="true">
  <proof prover="5"><result status="valid" time="0.05" steps="141"/></proof>
  </goal>
  <goal name="wmpn_incr_1&#39;vc.21" expl="assertion" proved="true">
  <proof prover="4"><result status="valid" time="0.52"/></proof>
  </goal>
  <goal name="wmpn_incr_1&#39;vc.22" expl="precondition" proved="true">
  <proof prover="4"><result status="valid" time="0.02"/></proof>
  </goal>
  <goal name="wmpn_incr_1&#39;vc.23" expl="precondition" proved="true">
  <proof prover="3"><result status="valid" time="0.01" steps="2838"/></proof>
  </goal>
  <goal name="wmpn_incr_1&#39;vc.24" expl="assertion" proved="true">
  <transf name="split_vc" proved="true" >
   <goal name="wmpn_incr_1&#39;vc.24.0" expl="assertion" proved="true">
   <proof prover="4"><result status="valid" time="1.36"/></proof>
   </goal>
   <goal name="wmpn_incr_1&#39;vc.24.1" expl="VC for wmpn_incr_1" proved="true">
   <proof prover="4"><result status="valid" time="0.33"/></proof>
   </goal>
   <goal name="wmpn_incr_1&#39;vc.24.2" expl="VC for wmpn_incr_1" proved="true">
   <proof prover="9"><result status="valid" time="0.06" steps="131"/></proof>
   </goal>
  </transf>
  </goal>
  <goal name="wmpn_incr_1&#39;vc.25" expl="integer overflow" proved="true">
  <proof prover="5"><result status="valid" time="0.03" steps="153"/></proof>
  </goal>
  <goal name="wmpn_incr_1&#39;vc.26" expl="precondition" proved="true">
  <proof prover="7"><result status="valid" time="0.19" steps="21657"/></proof>
  </goal>
  <goal name="wmpn_incr_1&#39;vc.27" expl="assertion" proved="true">
  <proof prover="8"><result status="valid" time="0.30" steps="356102"/></proof>
  </goal>
  <goal name="wmpn_incr_1&#39;vc.28" expl="loop variant decrease" proved="true">
  <proof prover="7"><result status="valid" time="0.10" steps="16240"/></proof>
  </goal>
  <goal name="wmpn_incr_1&#39;vc.29" expl="loop invariant preservation" proved="true">
  <proof prover="3"><result status="valid" time="0.32" steps="302153"/></proof>
  </goal>
  <goal name="wmpn_incr_1&#39;vc.30" expl="loop invariant preservation" proved="true">
  <proof prover="5"><result status="valid" time="0.07" steps="80"/></proof>
  </goal>
  <goal name="wmpn_incr_1&#39;vc.31" expl="loop invariant preservation" proved="true">
  <proof prover="7"><result status="valid" time="0.08" steps="16810"/></proof>
  </goal>
  <goal name="wmpn_incr_1&#39;vc.32" expl="loop invariant preservation" proved="true">
  <proof prover="4"><result status="valid" time="0.02"/></proof>
  </goal>
  <goal name="wmpn_incr_1&#39;vc.33" expl="loop invariant preservation" proved="true">
  <proof prover="4"><result status="valid" time="0.02"/></proof>
  </goal>
  <goal name="wmpn_incr_1&#39;vc.34" expl="loop invariant preservation" proved="true">
  <proof prover="6"><result status="valid" time="0.08" steps="157"/></proof>
  </goal>
  <goal name="wmpn_incr_1&#39;vc.35" expl="loop invariant preservation" proved="true">
  <proof prover="7"><result status="valid" time="0.12" steps="16376"/></proof>
  </goal>
  <goal name="wmpn_incr_1&#39;vc.36" expl="loop invariant preservation" proved="true">
  <proof prover="3"><result status="valid" time="0.04" steps="40568"/></proof>
  </goal>
  <goal name="wmpn_incr_1&#39;vc.37" expl="loop invariant preservation" proved="true">
  <proof prover="3"><result status="valid" time="0.02" steps="16873"/></proof>
  </goal>
  <goal name="wmpn_incr_1&#39;vc.38" expl="loop invariant preservation" proved="true">
  <proof prover="5"><result status="valid" time="0.05" steps="87"/></proof>
  </goal>
  <goal name="wmpn_incr_1&#39;vc.39" expl="loop invariant preservation" proved="true">
  <proof prover="5"><result status="valid" time="0.02" steps="103"/></proof>
  </goal>
  <goal name="wmpn_incr_1&#39;vc.40" expl="loop invariant preservation" proved="true">
  <proof prover="5"><result status="valid" time="0.03" steps="106"/></proof>
  </goal>
  <goal name="wmpn_incr_1&#39;vc.41" expl="assertion" proved="true">
  <proof prover="7"><result status="valid" time="0.20" steps="24313"/></proof>
  </goal>
  <goal name="wmpn_incr_1&#39;vc.42" expl="precondition" proved="true">
  <proof prover="3"><result status="valid" time="0.01" steps="34911"/></proof>
  </goal>
  <goal name="wmpn_incr_1&#39;vc.43" expl="precondition" proved="true">
  <transf name="split_vc" proved="true" >
   <goal name="wmpn_incr_1&#39;vc.43.0" expl="precondition" proved="true">
   <proof prover="3"><result status="valid" time="0.03" steps="2716"/></proof>
   </goal>
  </transf>
  </goal>
  <goal name="wmpn_incr_1&#39;vc.44" expl="precondition" proved="true">
  <proof prover="5"><result status="valid" time="0.04" steps="165"/></proof>
  </goal>
  <goal name="wmpn_incr_1&#39;vc.45" expl="precondition" proved="true">
  <proof prover="5"><result status="valid" time="0.04" steps="52"/></proof>
  </goal>
  <goal name="wmpn_incr_1&#39;vc.46" expl="assertion" proved="true">
  <proof prover="6"><result status="valid" time="0.15" steps="342"/></proof>
  </goal>
  <goal name="wmpn_incr_1&#39;vc.47" expl="assertion" proved="true">
  <proof prover="4"><result status="valid" time="1.57"/></proof>
  </goal>
  <goal name="wmpn_incr_1&#39;vc.48" expl="precondition" proved="true">
  <proof prover="3"><result status="valid" time="0.04" steps="2822"/></proof>
  </goal>
  <goal name="wmpn_incr_1&#39;vc.49" expl="precondition" proved="true">
  <proof prover="5"><result status="valid" time="0.02" steps="66"/></proof>
  </goal>
  <goal name="wmpn_incr_1&#39;vc.50" expl="assertion" proved="true">
  <transf name="split_vc" proved="true" >
   <goal name="wmpn_incr_1&#39;vc.50.0" expl="assertion" proved="true">
   <proof prover="9"><result status="valid" time="0.08" steps="129"/></proof>
   </goal>
   <goal name="wmpn_incr_1&#39;vc.50.1" expl="VC for wmpn_incr_1" proved="true">
   <proof prover="4"><result status="valid" time="0.43"/></proof>
   </goal>
   <goal name="wmpn_incr_1&#39;vc.50.2" expl="VC for wmpn_incr_1" proved="true">
   <proof prover="9"><result status="valid" time="0.09" steps="131"/></proof>
   </goal>
  </transf>
  </goal>
  <goal name="wmpn_incr_1&#39;vc.51" expl="integer overflow" proved="true">
  <proof prover="5"><result status="valid" time="0.04" steps="150"/></proof>
  </goal>
  <goal name="wmpn_incr_1&#39;vc.52" expl="precondition" proved="true">
  <proof prover="7"><result status="valid" time="0.18" steps="21857"/></proof>
  </goal>
  <goal name="wmpn_incr_1&#39;vc.53" expl="assertion" proved="true">
  <proof prover="5"><result status="valid" time="0.01" steps="78"/></proof>
  </goal>
  <goal name="wmpn_incr_1&#39;vc.54" expl="loop variant decrease" proved="true">
  <proof prover="5"><result status="valid" time="0.02" steps="77"/></proof>
  </goal>
  <goal name="wmpn_incr_1&#39;vc.55" expl="loop invariant preservation" proved="true">
  <proof prover="7"><result status="valid" time="0.10" steps="16850"/></proof>
  </goal>
  <goal name="wmpn_incr_1&#39;vc.56" expl="loop invariant preservation" proved="true">
  <proof prover="7"><result status="valid" time="0.08" steps="14661"/></proof>
  </goal>
  <goal name="wmpn_incr_1&#39;vc.57" expl="loop invariant preservation" proved="true">
  <proof prover="7"><result status="valid" time="0.10" steps="16777"/></proof>
  </goal>
  <goal name="wmpn_incr_1&#39;vc.58" expl="loop invariant preservation" proved="true">
  <proof prover="4"><result status="valid" time="0.01"/></proof>
  </goal>
  <goal name="wmpn_incr_1&#39;vc.59" expl="loop invariant preservation" proved="true">
  <proof prover="4"><result status="valid" time="0.01"/></proof>
  </goal>
  <goal name="wmpn_incr_1&#39;vc.60" expl="loop invariant preservation" proved="true">
  <proof prover="3"><result status="valid" time="0.02" steps="41388"/></proof>
  </goal>
  <goal name="wmpn_incr_1&#39;vc.61" expl="loop invariant preservation" proved="true">
  <proof prover="7"><result status="valid" time="0.07" steps="16328"/></proof>
  </goal>
  <goal name="wmpn_incr_1&#39;vc.62" expl="loop invariant preservation" proved="true">
  <proof prover="7"><result status="valid" time="0.08" steps="16388"/></proof>
  </goal>
  <goal name="wmpn_incr_1&#39;vc.63" expl="loop invariant preservation" proved="true">
  <proof prover="7"><result status="valid" time="0.07" steps="14630"/></proof>
  </goal>
  <goal name="wmpn_incr_1&#39;vc.64" expl="loop invariant preservation" proved="true">
  <proof prover="6"><result status="valid" time="0.25" steps="161"/></proof>
  </goal>
  <goal name="wmpn_incr_1&#39;vc.65" expl="loop invariant preservation" proved="true">
  <proof prover="6"><result status="valid" time="0.26" steps="171"/></proof>
  </goal>
  <goal name="wmpn_incr_1&#39;vc.66" expl="loop invariant preservation" proved="true">
  <proof prover="7"><result status="valid" time="0.19" steps="23456"/></proof>
  </goal>
  <goal name="wmpn_incr_1&#39;vc.67" expl="precondition" proved="true">
  <proof prover="3"><result status="valid" time="0.04" steps="14602"/></proof>
  </goal>
  <goal name="wmpn_incr_1&#39;vc.68" expl="precondition" proved="true">
  <proof prover="5"><result status="valid" time="0.06" steps="42"/></proof>
  </goal>
  <goal name="wmpn_incr_1&#39;vc.69" expl="assertion" proved="true">
  <transf name="split_vc" proved="true" >
   <goal name="wmpn_incr_1&#39;vc.69.0" expl="assertion" proved="true">
   <proof prover="7"><result status="valid" time="0.07" steps="13686"/></proof>
   </goal>
   <goal name="wmpn_incr_1&#39;vc.69.1" expl="assertion" proved="true">
   <proof prover="7"><result status="valid" time="0.07" steps="13699"/></proof>
   </goal>
   <goal name="wmpn_incr_1&#39;vc.69.2" expl="VC for wmpn_incr_1" proved="true">
   <proof prover="6"><result status="valid" time="0.07" steps="91"/></proof>
   </goal>
   <goal name="wmpn_incr_1&#39;vc.69.3" expl="VC for wmpn_incr_1" proved="true">
   <proof prover="7"><result status="valid" time="0.05" steps="14006"/></proof>
   </goal>
  </transf>
  </goal>
  <goal name="wmpn_incr_1&#39;vc.70" expl="precondition" proved="true">
  <proof prover="3"><result status="valid" time="0.01" steps="49608"/></proof>
  </goal>
  <goal name="wmpn_incr_1&#39;vc.71" expl="postcondition" proved="true">
  <proof prover="6"><result status="valid" time="0.03" steps="85"/></proof>
  </goal>
  <goal name="wmpn_incr_1&#39;vc.72" expl="postcondition" proved="true">
  <proof prover="7"><result status="valid" time="0.19" steps="19844"/></proof>
  </goal>
 </transf>
 </goal>
 <goal name="wmpn_add_1_in_place&#39;vc" expl="VC for wmpn_add_1_in_place" proved="true">
 <transf name="split_vc" proved="true" >
  <goal name="wmpn_add_1_in_place&#39;vc.0" expl="precondition" proved="true">
  <proof prover="2"><result status="valid" time="0.09" steps="14670"/></proof>
  </goal>
  <goal name="wmpn_add_1_in_place&#39;vc.1" expl="precondition" proved="true">
  <proof prover="2"><result status="valid" time="0.09" steps="15209"/></proof>
  </goal>
  <goal name="wmpn_add_1_in_place&#39;vc.2" expl="precondition" proved="true">
  <proof prover="2"><result status="valid" time="0.04" steps="12229"/></proof>
  </goal>
  <goal name="wmpn_add_1_in_place&#39;vc.3" expl="assertion" proved="true">
  <proof prover="7"><result status="valid" time="0.14" steps="17913"/></proof>
  </goal>
  <goal name="wmpn_add_1_in_place&#39;vc.4" expl="loop invariant init" proved="true">
  <proof prover="2"><result status="valid" time="0.13" steps="12650"/></proof>
  </goal>
  <goal name="wmpn_add_1_in_place&#39;vc.5" expl="loop invariant init" proved="true">
  <proof prover="2"><result status="valid" time="0.05" steps="13499"/></proof>
  </goal>
  <goal name="wmpn_add_1_in_place&#39;vc.6" expl="loop invariant init" proved="true">
  <proof prover="2"><result status="valid" time="0.05" steps="12757"/></proof>
  </goal>
  <goal name="wmpn_add_1_in_place&#39;vc.7" expl="loop invariant init" proved="true">
  <proof prover="6" timelimit="5" memlimit="2000"><result status="valid" time="1.74" steps="204"/></proof>
  </goal>
  <goal name="wmpn_add_1_in_place&#39;vc.8" expl="loop invariant init" proved="true">
  <proof prover="2"><result status="valid" time="0.12" steps="14516"/></proof>
  </goal>
  <goal name="wmpn_add_1_in_place&#39;vc.9" expl="assertion" proved="true">
  <proof prover="5"><result status="valid" time="0.05" steps="38"/></proof>
  </goal>
  <goal name="wmpn_add_1_in_place&#39;vc.10" expl="precondition" proved="true">
  <proof prover="2"><result status="valid" time="0.06" steps="17283"/></proof>
  </goal>
  <goal name="wmpn_add_1_in_place&#39;vc.11" expl="assertion" proved="true">
  <proof prover="6"><result status="valid" time="0.03" steps="77"/></proof>
  </goal>
  <goal name="wmpn_add_1_in_place&#39;vc.12" expl="precondition" proved="true">
  <proof prover="2"><result status="valid" time="0.04" steps="13494"/></proof>
  </goal>
  <goal name="wmpn_add_1_in_place&#39;vc.13" expl="precondition" proved="true">
  <proof prover="2"><result status="valid" time="0.06" steps="13521"/></proof>
  </goal>
  <goal name="wmpn_add_1_in_place&#39;vc.14" expl="precondition" proved="true">
  <proof prover="2"><result status="valid" time="0.05" steps="18805"/></proof>
  </goal>
  <goal name="wmpn_add_1_in_place&#39;vc.15" expl="precondition" proved="true">
  <proof prover="2"><result status="valid" time="0.07" steps="13309"/></proof>
  </goal>
  <goal name="wmpn_add_1_in_place&#39;vc.16" expl="assertion" proved="true">
  <proof prover="5"><result status="valid" time="0.04" steps="66"/></proof>
  </goal>
  <goal name="wmpn_add_1_in_place&#39;vc.17" expl="assertion" proved="true">
  <proof prover="7" timelimit="5" memlimit="2000"><result status="valid" time="0.70" steps="68244"/></proof>
  </goal>
  <goal name="wmpn_add_1_in_place&#39;vc.18" expl="precondition" proved="true">
  <proof prover="2"><result status="valid" time="0.11" steps="14851"/></proof>
  </goal>
  <goal name="wmpn_add_1_in_place&#39;vc.19" expl="precondition" proved="true">
  <proof prover="2"><result status="valid" time="0.05" steps="14913"/></proof>
  </goal>
  <goal name="wmpn_add_1_in_place&#39;vc.20" expl="integer overflow" proved="true">
  <proof prover="2"><result status="valid" time="0.12" steps="19349"/></proof>
  </goal>
  <goal name="wmpn_add_1_in_place&#39;vc.21" expl="assertion" proved="true">
  <proof prover="2"><result status="valid" time="0.16" steps="20216"/></proof>
  </goal>
  <goal name="wmpn_add_1_in_place&#39;vc.22" expl="assertion" proved="true">
  <proof prover="6"><result status="valid" time="0.73" steps="114"/></proof>
  </goal>
  <goal name="wmpn_add_1_in_place&#39;vc.23" expl="precondition" proved="true">
  <proof prover="2"><result status="valid" time="0.06" steps="15328"/></proof>
  </goal>
  <goal name="wmpn_add_1_in_place&#39;vc.24" expl="precondition" proved="true">
  <proof prover="2"><result status="valid" time="0.07" steps="15428"/></proof>
  </goal>
  <goal name="wmpn_add_1_in_place&#39;vc.25" expl="assertion" proved="true">
  <proof prover="2"><result status="valid" time="0.17" steps="22174"/></proof>
  </goal>
  <goal name="wmpn_add_1_in_place&#39;vc.26" expl="precondition" proved="true">
  <proof prover="7"><result status="valid" time="0.16" steps="22087"/></proof>
  </goal>
  <goal name="wmpn_add_1_in_place&#39;vc.27" expl="postcondition" proved="true">
  <proof prover="6"><result status="valid" time="0.81" steps="121"/></proof>
  </goal>
  <goal name="wmpn_add_1_in_place&#39;vc.28" expl="postcondition" proved="true">
  <proof prover="2"><result status="valid" time="0.04" steps="15634"/></proof>
  </goal>
  <goal name="wmpn_add_1_in_place&#39;vc.29" expl="postcondition" proved="true">
  <proof prover="5"><result status="valid" time="0.56" steps="86"/></proof>
  </goal>
  <goal name="wmpn_add_1_in_place&#39;vc.30" expl="assertion" proved="true">
  <proof prover="2"><result status="valid" time="0.14" steps="20192"/></proof>
  </goal>
  <goal name="wmpn_add_1_in_place&#39;vc.31" expl="assertion" proved="true">
  <proof prover="6"><result status="valid" time="0.68" steps="114"/></proof>
  </goal>
  <goal name="wmpn_add_1_in_place&#39;vc.32" expl="loop variant decrease" proved="true">
  <proof prover="2"><result status="valid" time="0.08" steps="15212"/></proof>
  </goal>
  <goal name="wmpn_add_1_in_place&#39;vc.33" expl="loop invariant preservation" proved="true">
  <proof prover="2"><result status="valid" time="0.05" steps="15321"/></proof>
  </goal>
  <goal name="wmpn_add_1_in_place&#39;vc.34" expl="loop invariant preservation" proved="true">
  <proof prover="2"><result status="valid" time="0.06" steps="13946"/></proof>
  </goal>
  <goal name="wmpn_add_1_in_place&#39;vc.35" expl="loop invariant preservation" proved="true">
  <proof prover="2"><result status="valid" time="0.10" steps="13964"/></proof>
  </goal>
  <goal name="wmpn_add_1_in_place&#39;vc.36" expl="loop invariant preservation" proved="true">
  <proof prover="2"><result status="valid" time="0.06" steps="15284"/></proof>
  </goal>
  <goal name="wmpn_add_1_in_place&#39;vc.37" expl="loop invariant preservation" proved="true">
  <proof prover="2"><result status="valid" time="0.13" steps="20688"/></proof>
  </goal>
  <goal name="wmpn_add_1_in_place&#39;vc.38" expl="precondition" proved="true">
  <proof prover="2"><result status="valid" time="0.05" steps="14007"/></proof>
  </goal>
  <goal name="wmpn_add_1_in_place&#39;vc.39" expl="precondition" proved="true">
  <proof prover="5"><result status="valid" time="0.02" steps="38"/></proof>
  </goal>
  <goal name="wmpn_add_1_in_place&#39;vc.40" expl="assertion" proved="true">
  <proof prover="5"><result status="valid" time="0.07" steps="40"/></proof>
  </goal>
  <goal name="wmpn_add_1_in_place&#39;vc.41" expl="precondition" proved="true">
  <proof prover="2"><result status="valid" time="0.12" steps="19160"/></proof>
  </goal>
  <goal name="wmpn_add_1_in_place&#39;vc.42" expl="postcondition" proved="true">
  <proof prover="5"><result status="valid" time="0.02" steps="40"/></proof>
  </goal>
  <goal name="wmpn_add_1_in_place&#39;vc.43" expl="postcondition" proved="true">
  <proof prover="2"><result status="valid" time="0.12" steps="13411"/></proof>
  </goal>
  <goal name="wmpn_add_1_in_place&#39;vc.44" expl="postcondition" proved="true">
  <proof prover="2"><result status="valid" time="0.07" steps="19211"/></proof>
  </goal>
  <goal name="wmpn_add_1_in_place&#39;vc.45" expl="precondition" proved="true">
  <proof prover="2"><result status="valid" time="0.03" steps="12619"/></proof>
  </goal>
  <goal name="wmpn_add_1_in_place&#39;vc.46" expl="precondition" proved="true">
  <proof prover="2"><result status="valid" time="0.09" steps="12689"/></proof>
  </goal>
  <goal name="wmpn_add_1_in_place&#39;vc.47" expl="assertion" proved="true">
  <proof prover="2"><result status="valid" time="0.10" steps="14305"/></proof>
  </goal>
  <goal name="wmpn_add_1_in_place&#39;vc.48" expl="precondition" proved="true">
  <proof prover="7"><result status="valid" time="0.08" steps="18242"/></proof>
  </goal>
  <goal name="wmpn_add_1_in_place&#39;vc.49" expl="postcondition" proved="true">
  <proof prover="6"><result status="valid" time="0.18" steps="47"/></proof>
  </goal>
  <goal name="wmpn_add_1_in_place&#39;vc.50" expl="postcondition" proved="true">
  <proof prover="2"><result status="valid" time="0.06" steps="12956"/></proof>
  </goal>
  <goal name="wmpn_add_1_in_place&#39;vc.51" expl="postcondition" proved="true">
  <proof prover="5"><result status="valid" time="0.02" steps="43"/></proof>
  </goal>
 </transf>
 </goal>
</theory>
</file>
</why3session>
